[
{ "id":1,"latitude":"49.182863","longitude":"-0.370679","type":"semem","color":"green","client":"600GEREFRA1771","contact":"ALAIN","address":"FRA 14 CAEN","phone1":"02 99 05 44 91","phone2":"alain.patrel@gefco.net","phone3":"<a href=mailto:alain.patrel@gefco.net> Contactez-moi </a> ","last_purchase_date":"24/04/2018 10:00" },
{ "id":2,"latitude":"49.327471","longitude":"0.827902","type":"semem","color":"yellow","client":"600GEREFRA0283","contact":"ALAIN","address":"FRA 27 THUIT HEBERT","phone1":"02 99 05 44 91","phone2":"alain.patrel@gefco.net","phone3":"<a href=mailto:alain.patrel@gefco.net> Contactez-moi </a> ","last_purchase_date":"23/04/2018 11:00" },
{ "id":3,"latitude":"48.1133774","longitude":"-1.5226751","type":"semem","color":"green","client":"600GEREFRA0343","contact":"ALAIN","address":"FRA 35 NOYAL SUR VILAINE","phone1":"02 99 05 44 91","phone2":"alain.patrel@gefco.net","phone3":"<a href=mailto:alain.patrel@gefco.net> Contactez-moi </a> ","last_purchase_date":"24/04/2018 09:00" },
{ "id":4,"latitude":"45.632449","longitude":"5.111562","type":"semem","color":"yellow","client":"600GEREFRA2259","contact":"ALAIN","address":"FRA 38 ST QUENTIN FALLAVIER","phone1":"02 99 05 44 91","phone2":"alain.patrel@gefco.net","phone3":"<a href=mailto:alain.patrel@gefco.net> Contactez-moi </a> ","last_purchase_date":"23/04/2018 11:00" },
{ "id":5,"latitude":"50.674339","longitude":"3.062324","type":"semem","color":"green","client":"600GEREFRA1170","contact":"ALAIN","address":"FRA 59 MARQUETTE LEZ LILLE","phone1":"02 99 05 44 91","phone2":"alain.patrel@gefco.net","phone3":"<a href=mailto:alain.patrel@gefco.net> Contactez-moi </a> ","last_purchase_date":"24/04/2018 07:00" },
{ "id":6,"latitude":"45.795463","longitude":"3.163237","type":"semem","color":"yellow","client":"600GEREFRA1855","contact":"ALAIN","address":"FRA 63 AULNAT","phone1":"02 99 05 44 91","phone2":"alain.patrel@gefco.net","phone3":"<a href=mailto:alain.patrel@gefco.net> Contactez-moi </a> ","last_purchase_date":"23/04/2018 08:00" },
{ "id":7,"latitude":"47.789641","longitude":"7.334499","type":"semem","color":"yellow","client":"600GEREFRA2250","contact":"ALAIN","address":"FRA 68 KINGERSHEIM","phone1":"02 99 05 44 91","phone2":"alain.patrel@gefco.net","phone3":"<a href=mailto:alain.patrel@gefco.net> Contactez-moi </a> ","last_purchase_date":"23/04/2018 00:01" },
{ "id":8,"latitude":"47.799426","longitude":"7.380038","type":"semem","color":"green","client":"600GEREFRA2249","contact":"ALAIN","address":"FRA 68 SAUSHEIM","phone1":"02 99 05 44 91","phone2":"alain.patrel@gefco.net","phone3":"<a href=mailto:alain.patrel@gefco.net> Contactez-moi </a> ","last_purchase_date":"24/04/2018 00:01" },
{ "id":9,"latitude":"45.796138","longitude":"5.050381","type":"semem","color":"yellow","client":"600GEREFRA0129","contact":"ALAIN","address":"FRA 69 JONAGE","phone1":"02 99 05 44 91","phone2":"alain.patrel@gefco.net","phone3":"<a href=mailto:alain.patrel@gefco.net> Contactez-moi </a> ","last_purchase_date":"23/04/2018 09:00" },
{ "id":10,"latitude":"47.619788","longitude":"6.15428","type":"semem","color":"green","client":"600GEREFRA1555","contact":"ALAIN","address":"FRA 70 VESOUL","phone1":"02 99 05 44 91","phone2":"alain.patrel@gefco.net","phone3":"<a href=mailto:alain.patrel@gefco.net> Contactez-moi </a> ","last_purchase_date":"24/04/2018 06:10" },
{ "id":11,"latitude":"49.411811","longitude":"1.041384","type":"semem","color":"green","client":"600GEREFRA0124","contact":"ALAIN","address":"FRA 76 GRAND QUEVILLY","phone1":"02 99 05 44 91","phone2":"alain.patrel@gefco.net","phone3":"<a href=mailto:alain.patrel@gefco.net> Contactez-moi </a> ","last_purchase_date":"24/04/2018 10:00" },
{ "id":12,"latitude":"49.49437","longitude":"0.107929","type":"semem","color":"green","client":"600GEREFRA0113","contact":"ALAIN","address":"FRA 76 LE HAVRE","phone1":"02 99 05 44 91","phone2":"alain.patrel@gefco.net","phone3":"<a href=mailto:alain.patrel@gefco.net> Contactez-moi </a> ","last_purchase_date":"24/04/2018 12:00" },
{ "id":13,"latitude":"49.818782","longitude":"2.7986749","type":"semem","color":"yellow","client":"600GEREFRA2016","contact":"ALAIN","address":"FRA 80 CHAULNES","phone1":"02 99 05 44 91","phone2":"alain.patrel@gefco.net","phone3":"<a href=mailto:alain.patrel@gefco.net> Contactez-moi </a> ","last_purchase_date":"23/04/2018 07:00" },
{ "id":14,"latitude":"44.474899","longitude":"2.462587","type":"semem","color":"green","client":"600GEREFRA2103","contact":"CHRISTEL","address":"FRA 12 MARCILLAC VALLON","phone1":"02 99 05 44 94","phone2":"christel.michel@gefco.net","phone3":"<a href=mailto:christel.michel@gefco.net> Contactez-moi </a> ","last_purchase_date":"24/04/2018 08:00" },
{ "id":15,"latitude":"44.485769","longitude":"4.716393","type":"semem","color":"yellow","client":"600GEREFRA1960","contact":"CHRISTEL","address":"FRA 26 CHATEAUNEUF DU RHONE","phone1":"02 99 05 44 94","phone2":"christel.michel@gefco.net","phone3":"<a href=mailto:christel.michel@gefco.net> Contactez-moi </a> ","last_purchase_date":"23/04/2018 12:00" },
{ "id":16,"latitude":"44.751895","longitude":"4.822375","type":"semem","color":"yellow","client":"600GEREFRA2104","contact":"CHRISTEL","address":"FRA 26 LORIOL SUR DROME","phone1":"02 99 05 44 94","phone2":"christel.michel@gefco.net","phone3":"<a href=mailto:christel.michel@gefco.net> Contactez-moi </a> ","last_purchase_date":"23/04/2018 10:00" },
{ "id":17,"latitude":"43.683214","longitude":"1.318086","type":"semem","color":"green","client":"600GEREFRA2260","contact":"CHRISTEL","address":"FRA 31 AUSSONNE","phone1":"02 99 05 44 94","phone2":"christel.michel@gefco.net","phone3":"<a href=mailto:christel.michel@gefco.net> Contactez-moi </a> ","last_purchase_date":"24/04/2018 00:00" },
{ "id":18,"latitude":"43.461574","longitude":"1.33071","type":"semem","color":"yellow","client":"600GEREFRA2071","contact":"CHRISTEL","address":"FRA 31 MURET","phone1":"02 99 05 44 94","phone2":"christel.michel@gefco.net","phone3":"<a href=mailto:christel.michel@gefco.net> Contactez-moi </a> ","last_purchase_date":"23/04/2018 00:00" },
{ "id":19,"latitude":"45.480702","longitude":"4.432911","type":"semem","color":"green","client":"600GEREFRA1439","contact":"CHRISTEL","address":"FRA 42 LA TALAUDIERE","phone1":"02 99 05 44 94","phone2":"christel.michel@gefco.net","phone3":"<a href=mailto:christel.michel@gefco.net> Contactez-moi </a> ","last_purchase_date":"24/04/2018 08:00" },
{ "id":21,"latitude":"48.0067537","longitude":"5.5474323","type":"semem","color":"yellow","client":"600GEREFRA1724","contact":"CHRISTEL","address":"FRA 52 MONTIGNY LE ROI","phone1":"02 99 05 44 94","phone2":"christel.michel@gefco.net","phone3":"<a href=mailto:christel.michel@gefco.net> Contactez-moi </a> ","last_purchase_date":"23/04/2018 05:30" },
{ "id":22,"latitude":"48.1080739","longitude":"-0.876521","type":"semem","color":"yellow","client":"600GEREFRA0045","contact":"CHRISTEL","address":"FRA 53 LE GENEST ST ISLE","phone1":"02 99 05 44 94","phone2":"christel.michel@gefco.net","phone3":"<a href=mailto:christel.michel@gefco.net> Contactez-moi </a> ","last_purchase_date":"23/04/2018 10:00" },
{ "id":23,"latitude":"49.150918","longitude":"6.1509979","type":"semem","color":"green","client":"600GEREFRA1405","contact":"CHRISTEL","address":"FRA 57 WOIPPY","phone1":"02 99 05 44 94","phone2":"christel.michel@gefco.net","phone3":"<a href=mailto:christel.michel@gefco.net> Contactez-moi </a> ","last_purchase_date":"25/04/2018 10:00" },
{ "id":24,"latitude":"47.629788","longitude":"6.16428","type":"semem","color":"yellow","client":"600GEREFRA2011","contact":"CHRISTEL","address":"FRA 70 VESOUL","phone1":"02 99 05 44 94","phone2":"christel.michel@gefco.net","phone3":"<a href=mailto:christel.michel@gefco.net> Contactez-moi </a> ","last_purchase_date":"23/04/2018 13:40" },
{ "id":25,"latitude":"48.98543","longitude":"2.619156","type":"semem","color":"yellow","client":"600GEREFRA2014","contact":"CHRISTEL","address":"FRA 77 MITRY MORY","phone1":"02 99 05 44 94","phone2":"christel.michel@gefco.net","phone3":"<a href=mailto:christel.michel@gefco.net> Contactez-moi </a> ","last_purchase_date":"23/04/2018 12:00" },
{ "id":26,"latitude":"48.789808","longitude":"1.601126","type":"semem","color":"yellow","client":"600GEREFRA2142","contact":"CHRISTEL","address":"FRA 78 HOUDAN","phone1":"02 99 05 44 94","phone2":"christel.michel@gefco.net","phone3":"<a href=mailto:christel.michel@gefco.net> Contactez-moi </a> ","last_purchase_date":"23/04/2018 08:00" },
{ "id":27,"latitude":"49.000847","longitude":"1.633063","type":"semem","color":"yellow","client":"600GEREFRA1541","contact":"CHRISTEL","address":"FRA 78 ROSNY SUR SEINE","phone1":"02 99 05 44 94","phone2":"christel.michel@gefco.net","phone3":"<a href=mailto:christel.michel@gefco.net> Contactez-moi </a> ","last_purchase_date":"23/04/2018 00:00" },
{ "id":28,"latitude":"43.699185","longitude":"1.820699","type":"semem","color":"yellow","client":"600GEREFRA2177","contact":"CHRISTEL","address":"FRA 81 LAVAUR","phone1":"02 99 05 44 94","phone2":"christel.michel@gefco.net","phone3":"<a href=mailto:christel.michel@gefco.net> Contactez-moi </a> ","last_purchase_date":"23/04/2018 11:00" },
{ "id":29,"latitude":"49.04313","longitude":"2.105287","type":"semem","color":"yellow","client":"600GEREFRA1805","contact":"CHRISTEL","address":"FRA 95 ST OUEN L AUMONE","phone1":"02 99 05 44 94","phone2":"christel.michel@gefco.net","phone3":"<a href=mailto:christel.michel@gefco.net> Contactez-moi </a> ","last_purchase_date":"23/04/2018 08:30" },
{ "id":30,"latitude":"48.3709108","longitude":"17.5833218","type":"semem","color":"blue","client":"600GEREFRA2055","contact":"CYRIAC","address":"SVK 91 TRNAVA","phone1":"02 99 05 48 97","phone2":"cyriac.gallez@gefco.net","phone3":"<a href=mailto:cyriac.gallez@gefco.net> Contactez-moi </a> ","last_purchase_date":"01/05/2018 01:00" },
{ "id":31,"latitude":"49.676651","longitude":"4.976835","type":"zebu","color":"green","client":"604GERELTU2063","contact":"DANIEL","address":"FRA 08 BAZEILLES","phone1":"05 61 37 39 26","phone2":"daniel.saez@gefco.net","phone3":"<a href=mailto:daniel.saez@gefco.net> Contactez-moi </a> ","last_purchase_date":"24/04/2018 00:01" },
{ "id":32,"latitude":"43.299813","longitude":"2.019357","type":"zebu","color":"yellow","client":"604GERELTU1738","contact":"DANIEL","address":"FRA 11 ST MARTIN LALANDE","phone1":"05 61 37 39 26","phone2":"daniel.saez@gefco.net","phone3":"<a href=mailto:daniel.saez@gefco.net> Contactez-moi </a> ","last_purchase_date":"23/04/2018 08:00" },
{ "id":33,"latitude":"43.4478278","longitude":"5.6413021","type":"zebu","color":"green","client":"604GERELTU1739","contact":"DANIEL","address":"FRA 13 PEYNIER","phone1":"05 61 37 39 26","phone2":"daniel.saez@gefco.net","phone3":"<a href=mailto:daniel.saez@gefco.net> Contactez-moi </a> ","last_purchase_date":"24/04/2018 08:00" },
{ "id":35,"latitude":"50.59787","longitude":"4.32851","type":"zebu","color":"green","client":"604GERELTU1732","contact":"DANIEL","address":"BEL 14 NIVELLES","phone1":"05 61 37 39 26","phone2":"daniel.saez@gefco.net","phone3":"<a href=mailto:daniel.saez@gefco.net> Contactez-moi </a> ","last_purchase_date":"26/04/2018 12:00" },
{ "id":36,"latitude":"45.4829255","longitude":"9.334504","type":"zebu","color":"green","client":"604GERELTU2292","contact":"DANIEL","address":"ITA 20 LIMITO","phone1":"05 61 37 39 26","phone2":"daniel.saez@gefco.net","phone3":"<a href=mailto:daniel.saez@gefco.net> Contactez-moi </a> ","last_purchase_date":"26/04/2018 08:00" },
{ "id":37,"latitude":"48.42543","longitude":"-2.055039","type":"zebu","color":"green","client":"604GERELTU2067","contact":"DANIEL","address":"FRA 22 ST CARNE","phone1":"05 61 37 39 26","phone2":"daniel.saez@gefco.net","phone3":"<a href=mailto:daniel.saez@gefco.net> Contactez-moi </a> ","last_purchase_date":"24/04/2018 12:00" },
{ "id":38,"latitude":"44.853449","longitude":"4.9333539","type":"zebu","color":"green","client":"604GERELTU1677","contact":"DANIEL","address":"FRA 26 MONTELEGER","phone1":"05 61 37 39 26","phone2":"daniel.saez@gefco.net","phone3":"<a href=mailto:daniel.saez@gefco.net> Contactez-moi </a> ","last_purchase_date":"24/04/2018 14:00" },
{ "id":39,"latitude":"45.2411559","longitude":"4.235165","type":"zebu","color":"green","client":"604GERELTU1885","contact":"DANIEL","address":"FRA 43 STE SIGOLENE","phone1":"05 61 37 39 26","phone2":"daniel.saez@gefco.net","phone3":"<a href=mailto:daniel.saez@gefco.net> Contactez-moi </a> ","last_purchase_date":"24/04/2018 15:00" },
{ "id":40,"latitude":"45.2511559","longitude":"4.245165","type":"zebu","color":"green","client":"604GERELTU2295","contact":"DANIEL","address":"FRA 43 STE SIGOLENE","phone1":"05 61 37 39 26","phone2":"daniel.saez@gefco.net","phone3":"<a href=mailto:daniel.saez@gefco.net> Contactez-moi </a> ","last_purchase_date":"24/04/2018 08:00" },
{ "id":41,"latitude":"44.359532","longitude":"1.4062079","type":"zebu","color":"green","client":"604GERELTU1668","contact":"DANIEL","address":"FRA 46 LHOSPITALET","phone1":"05 61 37 39 26","phone2":"daniel.saez@gefco.net","phone3":"<a href=mailto:daniel.saez@gefco.net> Contactez-moi </a> ","last_purchase_date":"24/04/2018 11:00" },
{ "id":42,"latitude":"48.0785146","longitude":"-0.7669906","type":"zebu","color":"green","client":"604GERELTU2062","contact":"DANIEL","address":"FRA 53 LAVAL","phone1":"05 61 37 39 26","phone2":"daniel.saez@gefco.net","phone3":"<a href=mailto:daniel.saez@gefco.net> Contactez-moi </a> ","last_purchase_date":"24/04/2018 16:00" },
{ "id":43,"latitude":"49.515432","longitude":"2.445059","type":"zebu","color":"green","client":"604GERELTU2258","contact":"DANIEL","address":"FRA 60 ST JUST EN CHAUSSEE","phone1":"05 61 37 39 26","phone2":"daniel.saez@gefco.net","phone3":"<a href=mailto:daniel.saez@gefco.net> Contactez-moi </a> ","last_purchase_date":"24/04/2018 08:00" },
{ "id":44,"latitude":"50.44783","longitude":"2.994979","type":"zebu","color":"green","client":"604GERELTU2274","contact":"DANIEL","address":"FRA 62 DOURGES","phone1":"05 61 37 39 26","phone2":"daniel.saez@gefco.net","phone3":"<a href=mailto:daniel.saez@gefco.net> Contactez-moi </a> ","last_purchase_date":"24/04/2018 12:00" },
{ "id":45,"latitude":"51.8697237","longitude":"5.7791067","type":"zebu","color":"green","client":"604GERELTU1886","contact":"DANIEL","address":"NLD 66 BEUNINGEN","phone1":"05 61 37 39 26","phone2":"daniel.saez@gefco.net","phone3":"<a href=mailto:daniel.saez@gefco.net> Contactez-moi </a> ","last_purchase_date":"24/04/2018 08:00" },
{ "id":46,"latitude":"47.8404856","longitude":"-0.3334185","type":"zebu","color":"green","client":"604GERELTU2080","contact":"DANIEL","address":"FRA 72 SABLE SUR SARTHE","phone1":"05 61 37 39 26","phone2":"daniel.saez@gefco.net","phone3":"<a href=mailto:daniel.saez@gefco.net> Contactez-moi </a> ","last_purchase_date":"24/04/2018 12:00" },
{ "id":47,"latitude":"48.627158","longitude":"2.593706","type":"zebu","color":"green","client":"604GERELTU2064","contact":"DANIEL","address":"FRA 77 MOISSY CRAMAYEL","phone1":"05 61 37 39 26","phone2":"daniel.saez@gefco.net","phone3":"<a href=mailto:daniel.saez@gefco.net> Contactez-moi </a> ","last_purchase_date":"25/04/2018 08:00" },
{ "id":48,"latitude":"51.3189468","longitude":"3.2068507","type":"zebu","color":"green","client":"604GERELTU2073","contact":"DANIEL","address":"BEL 83 ZEEBRUGGE","phone1":"05 61 37 39 26","phone2":"daniel.saez@gefco.net","phone3":"<a href=mailto:daniel.saez@gefco.net> Contactez-moi </a> ","last_purchase_date":"26/04/2018 09:00" },
{ "id":49,"latitude":"47.981432","longitude":"3.398961","type":"zebu","color":"green","client":"604GERELTU1701","contact":"DANIEL","address":"FRA 89 JOIGNY","phone1":"05 61 37 39 26","phone2":"daniel.saez@gefco.net","phone3":"<a href=mailto:daniel.saez@gefco.net> Contactez-moi </a> ","last_purchase_date":"24/04/2018 09:00" },
{ "id":50,"latitude":"51.0543422","longitude":"3.7174243","type":"zebu","color":"yellow","client":"604GEREBGR2257","contact":"DANIEL","address":"BEL 90 GENT","phone1":"05 61 37 39 26","phone2":"daniel.saez@gefco.net","phone3":"<a href=mailto:daniel.saez@gefco.net> Contactez-moi </a> ","last_purchase_date":"23/04/2018 13:00" },
{ "id":51,"latitude":"48.925525","longitude":"2.293275","type":"zebu","color":"green","client":"604GERELTU1766","contact":"DANIEL","address":"FRA 92 GENNEVILLIERS","phone1":"05 61 37 39 26","phone2":"daniel.saez@gefco.net","phone3":"<a href=mailto:daniel.saez@gefco.net> Contactez-moi </a> ","last_purchase_date":"25/04/2018 05:00" },
{ "id":52,"latitude":"48.7305769","longitude":"2.447488","type":"zebu","color":"green","client":"604GERELTU1735","contact":"DANIEL","address":"FRA 94 VILLENEUVE ST GEORGES","phone1":"05 61 37 39 26","phone2":"daniel.saez@gefco.net","phone3":"<a href=mailto:daniel.saez@gefco.net> Contactez-moi </a> ","last_purchase_date":"25/04/2018 08:00" },
{ "id":53,"latitude":"49.137693","longitude":"0.456406","type":"semem","color":"green","client":"600GEREFRA1768","contact":"GHISLAIN","address":"FRA 27 THIBERVILLE","phone1":"02 99 05 44 92","phone2":"ghislain.cailliau@gefco.net","phone3":"<a href=mailto:ghislain.cailliau@gefco.net> Contactez-moi </a> ","last_purchase_date":"24/04/2018 08:00" },
{ "id":54,"latitude":"48.406325","longitude":"-4.39258","type":"semem","color":"green","client":"600GEREFRA2277","contact":"GHISLAIN","address":"FRA 29 LE RELECQ KERHUON","phone1":"02 99 05 44 92","phone2":"ghislain.cailliau@gefco.net","phone3":"<a href=mailto:ghislain.cailliau@gefco.net> Contactez-moi </a> ","last_purchase_date":"24/04/2018 13:00" },
{ "id":55,"latitude":"43.677079","longitude":"4.433703","type":"semem","color":"green","client":"600GEREFRA2020","contact":"GHISLAIN","address":"FRA 30 ST GILLES","phone1":"02 99 05 44 92","phone2":"ghislain.cailliau@gefco.net","phone3":"<a href=mailto:ghislain.cailliau@gefco.net> Contactez-moi </a> ","last_purchase_date":"24/04/2018 11:00" },
{ "id":56,"latitude":"43.344233","longitude":"3.215795","type":"semem","color":"green","client":"600GEREFRA2111","contact":"GHISLAIN","address":"FRA 34 BEZIERS","phone1":"02 99 05 44 92","phone2":"ghislain.cailliau@gefco.net","phone3":"<a href=mailto:ghislain.cailliau@gefco.net> Contactez-moi </a> ","last_purchase_date":"24/04/2018 12:00" },
{ "id":57,"latitude":"48.040898","longitude":"-1.707289","type":"semem","color":"green","client":"600GEREFRA0686","contact":"GHISLAIN","address":"FRA 35 CHARTRES DE BRETAGNE","phone1":"02 99 05 44 92","phone2":"ghislain.cailliau@gefco.net","phone3":"<a href=mailto:ghislain.cailliau@gefco.net> Contactez-moi </a> ","last_purchase_date":"24/04/2018 08:01" },
{ "id":58,"latitude":"48.153561","longitude":"-1.683146","type":"semem","color":"yellow","client":"600GEREFRA1709","contact":"GHISLAIN","address":"FRA 35 ST GREGOIRE","phone1":"02 99 05 44 92","phone2":"ghislain.cailliau@gefco.net","phone3":"<a href=mailto:ghislain.cailliau@gefco.net> Contactez-moi </a> ","last_purchase_date":"23/04/2018 08:00" },
{ "id":59,"latitude":"48.070973","longitude":"-1.257552","type":"semem","color":"green","client":"600GEREFRA0401","contact":"GHISLAIN","address":"FRA 35 TORCE","phone1":"02 99 05 44 92","phone2":"ghislain.cailliau@gefco.net","phone3":"<a href=mailto:ghislain.cailliau@gefco.net> Contactez-moi </a> ","last_purchase_date":"24/04/2018 13:00" },
{ "id":60,"latitude":"47.1241","longitude":"0.459839","type":"semem","color":"green","client":"600GEREFRA1999","contact":"GHISLAIN","address":"FRA 37 CROUZILLES","phone1":"02 99 05 44 92","phone2":"ghislain.cailliau@gefco.net","phone3":"<a href=mailto:ghislain.cailliau@gefco.net> Contactez-moi </a> ","last_purchase_date":"24/04/2018 14:00" },
{ "id":61,"latitude":"49.366934","longitude":"2.744351","type":"semem","color":"green","client":"600GEREFRA0986","contact":"GHISLAIN","address":"FRA 60 LE MEUX","phone1":"02 99 05 44 92","phone2":"ghislain.cailliau@gefco.net","phone3":"<a href=mailto:ghislain.cailliau@gefco.net> Contactez-moi </a> ","last_purchase_date":"24/04/2018 11:00" },
{ "id":62,"latitude":"47.809426","longitude":"7.390038","type":"semem","color":"yellow","client":"600GEREFRA1854","contact":"GHISLAIN","address":"FRA 68 SAUSHEIM","phone1":"02 99 05 44 92","phone2":"ghislain.cailliau@gefco.net","phone3":"<a href=mailto:ghislain.cailliau@gefco.net> Contactez-moi </a> ","last_purchase_date":"23/04/2018 10:30" },
{ "id":63,"latitude":"49.828901","longitude":"0.912495","type":"semem","color":"green","client":"600GEREFRA0391","contact":"GHISLAIN","address":"FRA 76 LUNERAY","phone1":"02 99 05 44 92","phone2":"ghislain.cailliau@gefco.net","phone3":"<a href=mailto:ghislain.cailliau@gefco.net> Contactez-moi </a> ","last_purchase_date":"24/04/2018 10:00" },
{ "id":64,"latitude":"46.323716","longitude":"-0.464777","type":"semem","color":"green","client":"600GEREFRA1702","contact":"GHISLAIN","address":"FRA 79 NIORT","phone1":"02 99 05 44 92","phone2":"ghislain.cailliau@gefco.net","phone3":"<a href=mailto:ghislain.cailliau@gefco.net> Contactez-moi </a> ","last_purchase_date":"25/04/2018 08:00" },
{ "id":65,"latitude":"46.333716","longitude":"-0.454777","type":"semem","color":"green","client":"600GEREFRA1632","contact":"GHISLAIN","address":"FRA 79 NIORT","phone1":"02 99 05 44 92","phone2":"ghislain.cailliau@gefco.net","phone3":"<a href=mailto:ghislain.cailliau@gefco.net> Contactez-moi </a> ","last_purchase_date":"24/04/2018 10:00" },
{ "id":66,"latitude":"47.013127","longitude":"-1.115797","type":"semem","color":"green","client":"600GEREFRA2070","contact":"GHISLAIN","address":"FRA 85 TIFFAUGES","phone1":"02 99 05 44 92","phone2":"ghislain.cailliau@gefco.net","phone3":"<a href=mailto:ghislain.cailliau@gefco.net> Contactez-moi </a> ","last_purchase_date":"24/04/2018 10:01" },
{ "id":67,"latitude":"46.257773","longitude":"5.655335","type":"semem","color":"green","client":"600GEREFRA1022","contact":"ISABELLE","address":"FRA 01 OYONNAX","phone1":"02 99 05 85 87","phone2":"isabelle.leray@gefco.net","phone3":"<a href=mailto:isabelle.leray@gefco.net> Contactez-moi </a> ","last_purchase_date":"24/04/2018 10:00" },
{ "id":68,"latitude":"49.192863","longitude":"-0.360679","type":"semem","color":"green","client":"600GEREFRA1756","contact":"ISABELLE","address":"FRA 14 CAEN","phone1":"02 99 05 85 87","phone2":"isabelle.leray@gefco.net","phone3":"<a href=mailto:isabelle.leray@gefco.net> Contactez-moi </a> ","last_purchase_date":"25/04/2018 00:00" },
{ "id":69,"latitude":"49.202863","longitude":"-0.350679","type":"semem","color":"green","client":"600GEREFRA2261","contact":"ISABELLE","address":"FRA 14 CAEN","phone1":"02 99 05 85 87","phone2":"isabelle.leray@gefco.net","phone3":"<a href=mailto:isabelle.leray@gefco.net> Contactez-moi </a> ","last_purchase_date":"24/04/2018 11:00" },
{ "id":70,"latitude":"47.280302","longitude":"4.998667","type":"semem","color":"yellow","client":"600GEREFRA0461","contact":"ISABELLE","address":"FRA 21 MARSANNAY LA COTE","phone1":"02 99 05 85 87","phone2":"isabelle.leray@gefco.net","phone3":"<a href=mailto:isabelle.leray@gefco.net> Contactez-moi </a> ","last_purchase_date":"23/04/2018 08:30" },
{ "id":71,"latitude":"46.954174","longitude":"6.116989","type":"semem","color":"green","client":"600GEREFRA1757","contact":"ISABELLE","address":"FRA 25 LEVIER","phone1":"02 99 05 85 87","phone2":"isabelle.leray@gefco.net","phone3":"<a href=mailto:isabelle.leray@gefco.net> Contactez-moi </a> ","last_purchase_date":"24/04/2018 08:00" },
{ "id":72,"latitude":"47.4614199","longitude":"6.837516","type":"semem","color":"green","client":"600GEREFRA0032","contact":"ISABELLE","address":"FRA 25 VALENTIGNEY","phone1":"02 99 05 85 87","phone2":"isabelle.leray@gefco.net","phone3":"<a href=mailto:isabelle.leray@gefco.net> Contactez-moi </a> ","last_purchase_date":"24/04/2018 17:00" },
{ "id":73,"latitude":"45.044236","longitude":"5.052735","type":"semem","color":"green","client":"600GEREFRA1230","contact":"ISABELLE","address":"FRA 26 ROMANS SUR ISERE","phone1":"02 99 05 85 87","phone2":"isabelle.leray@gefco.net","phone3":"<a href=mailto:isabelle.leray@gefco.net> Contactez-moi </a> ","last_purchase_date":"24/04/2018 00:00" },
{ "id":74,"latitude":"48.050898","longitude":"-1.697289","type":"semem","color":"yellow","client":"600GEREFRA0397","contact":"ISABELLE","address":"FRA 35 CHARTRES DE BRETAGNE","phone1":"02 99 05 85 87","phone2":"isabelle.leray@gefco.net","phone3":"<a href=mailto:isabelle.leray@gefco.net> Contactez-moi </a> ","last_purchase_date":"23/04/2018 08:01" },
{ "id":78,"latitude":"48.109406","longitude":"-1.405353","type":"semem","color":"green","client":"600GEREFRA1062","contact":"ISABELLE","address":"FRA 35 CHATEAUBOURG","phone1":"02 99 05 85 87","phone2":"isabelle.leray@gefco.net","phone3":"<a href=mailto:isabelle.leray@gefco.net> Contactez-moi </a> ","last_purchase_date":"24/04/2018 08:01" },
{ "id":79,"latitude":"48.065963","longitude":"-1.722328","type":"semem","color":"yellow","client":"600GEREFRA1708","contact":"ISABELLE","address":"FRA 35 ST JACQUES DE LA LANDE","phone1":"02 99 05 85 87","phone2":"isabelle.leray@gefco.net","phone3":"<a href=mailto:isabelle.leray@gefco.net> Contactez-moi </a> ","last_purchase_date":"23/04/2018 10:00" },
{ "id":80,"latitude":"48.79582","longitude":"0.295245","type":"semem","color":"green","client":"600GEREFRA1160","contact":"ISABELLE","address":"FRA 61 GACE","phone1":"02 99 05 85 87","phone2":"isabelle.leray@gefco.net","phone3":"<a href=mailto:isabelle.leray@gefco.net> Contactez-moi </a> ","last_purchase_date":"24/04/2018 00:00" },
{ "id":81,"latitude":"47.819426","longitude":"7.400038","type":"semem","color":"green","client":"600GEREFRA0451","contact":"ISABELLE","address":"FRA 68 SAUSHEIM","phone1":"02 99 05 85 87","phone2":"isabelle.leray@gefco.net","phone3":"<a href=mailto:isabelle.leray@gefco.net> Contactez-moi </a> ","last_purchase_date":"24/04/2018 18:00" },
{ "id":82,"latitude":"47.69589","longitude":"-0.074646","type":"semem","color":"yellow","client":"600GEREFRA1159","contact":"ISABELLE","address":"FRA 72 LA FLECHE","phone1":"02 99 05 85 87","phone2":"isabelle.leray@gefco.net","phone3":"<a href=mailto:isabelle.leray@gefco.net> Contactez-moi </a> ","last_purchase_date":"23/04/2018 14:00" },
{ "id":83,"latitude":"48.911856","longitude":"2.333764","type":"semem","color":"green","client":"600GEREFRA0551","contact":"ISABELLE","address":"FRA 93 ST OUEN","phone1":"02 99 05 85 87","phone2":"isabelle.leray@gefco.net","phone3":"<a href=mailto:isabelle.leray@gefco.net> Contactez-moi </a> ","last_purchase_date":"24/04/2018 09:30" },
{ "id":84,"latitude":"44.40951","longitude":"2.287737","type":"zebu","color":"green","client":"604GERESVK2122","contact":"JULIEN","address":"FRA 12 RIGNAC","phone1":"05 61 37 39 07","phone2":"julien.breuilh@gefco.net","phone3":"<a href=mailto:julien.breuilh@gefco.net> Contactez-moi </a> ","last_purchase_date":"25/04/2018 08:00" },
{ "id":85,"latitude":"43.617073","longitude":"5.073777","type":"zebu","color":"green","client":"568PEPT604FRA0091","contact":"JULIEN","address":"FRA 13 GRANS","phone1":"05 61 37 39 07","phone2":"julien.breuilh@gefco.net","phone3":"<a href=mailto:julien.breuilh@gefco.net> Contactez-moi </a> ","last_purchase_date":"25/04/2018 12:00" },
{ "id":86,"latitude":"45.648377","longitude":"0.1562369","type":"zebu","color":"green","client":"568PEPT604FRA0036","contact":"JULIEN","address":"FRA 16 ANGOULEME","phone1":"05 61 37 39 07","phone2":"julien.breuilh@gefco.net","phone3":"<a href=mailto:julien.breuilh@gefco.net> Contactez-moi </a> ","last_purchase_date":"25/04/2018 10:00" },
{ "id":87,"latitude":"45.9119502","longitude":"0.5916408","type":"zebu","color":"green","client":"604GERESVK1868","contact":"JULIEN","address":"FRA 16 ROUMAZIERES","phone1":"05 61 37 39 07","phone2":"julien.breuilh@gefco.net","phone3":"<a href=mailto:julien.breuilh@gefco.net> Contactez-moi </a> ","last_purchase_date":"25/04/2018 08:00" },
{ "id":94,"latitude":"51.00311","longitude":"4.3026","type":"zebu","color":"green","client":"568PEPT604FRA0012","contact":"JULIEN","address":"BEL 18 LONDERZEEL","phone1":"05 61 37 39 07","phone2":"julien.breuilh@gefco.net","phone3":"<a href=mailto:julien.breuilh@gefco.net> Contactez-moi </a> ","last_purchase_date":"24/04/2018 08:00" },
{ "id":95,"latitude":"51.1352386","longitude":"4.4450064","type":"zebu","color":"green","client":"568PEPT604FRA0101","contact":"JULIEN","address":"BEL 25 KONTICH","phone1":"05 61 37 39 07","phone2":"julien.breuilh@gefco.net","phone3":"<a href=mailto:julien.breuilh@gefco.net> Contactez-moi </a> ","last_purchase_date":"25/04/2018 08:01" },
{ "id":96,"latitude":"45.040419","longitude":"5.050948","type":"zebu","color":"green","client":"568PEPT604FRA0078","contact":"JULIEN","address":"FRA 26 BOURG DE PEAGE","phone1":"05 61 37 39 07","phone2":"julien.breuilh@gefco.net","phone3":"<a href=mailto:julien.breuilh@gefco.net> Contactez-moi </a> ","last_purchase_date":"24/04/2018 08:00" },
{ "id":97,"latitude":"45.3097228","longitude":"9.503716","type":"zebu","color":"green","client":"568PEPT604FRA0027","contact":"JULIEN","address":"ITA 26 LODI","phone1":"05 61 37 39 07","phone2":"julien.breuilh@gefco.net","phone3":"<a href=mailto:julien.breuilh@gefco.net> Contactez-moi </a> ","last_purchase_date":"24/04/2018 08:00" },
{ "id":98,"latitude":"51.1683102","longitude":"4.3942868","type":"zebu","color":"green","client":"604GERESVK1876","contact":"JULIEN","address":"BEL 26 WILRIJK","phone1":"05 61 37 39 07","phone2":"julien.breuilh@gefco.net","phone3":"<a href=mailto:julien.breuilh@gefco.net> Contactez-moi </a> ","last_purchase_date":"25/04/2018 18:00" },
{ "id":99,"latitude":"45.1847248","longitude":"9.1582069","type":"zebu","color":"green","client":"568PEPT604FRA0108","contact":"JULIEN","address":"ITA 27 PAVIA","phone1":"05 61 37 39 07","phone2":"julien.breuilh@gefco.net","phone3":"<a href=mailto:julien.breuilh@gefco.net> Contactez-moi </a> ","last_purchase_date":"24/04/2018 08:00" },
{ "id":100,"latitude":"43.604652","longitude":"1.444209","type":"zebu","color":"green","client":"568PEPT604FRA0085","contact":"JULIEN","address":"FRA 31 TOULOUSE","phone1":"05 61 37 39 07","phone2":"julien.breuilh@gefco.net","phone3":"<a href=mailto:julien.breuilh@gefco.net> Contactez-moi </a> ","last_purchase_date":"24/04/2018 08:00" },
{ "id":101,"latitude":"43.614652","longitude":"1.454209","type":"zebu","color":"green","client":"568PEPT604FRA0123","contact":"JULIEN","address":"FRA 31 TOULOUSE","phone1":"05 61 37 39 07","phone2":"julien.breuilh@gefco.net","phone3":"<a href=mailto:julien.breuilh@gefco.net> Contactez-moi </a> ","last_purchase_date":"26/04/2018 08:00" },
{ "id":102,"latitude":"43.560704","longitude":"4.086072","type":"zebu","color":"green","client":"568PEPT604FRA0107","contact":"JULIEN","address":"FRA 34 LA GRANDE MOTTE","phone1":"05 61 37 39 07","phone2":"julien.breuilh@gefco.net","phone3":"<a href=mailto:julien.breuilh@gefco.net> Contactez-moi </a> ","last_purchase_date":"25/04/2018 12:00" },
{ "id":103,"latitude":"44.4183598","longitude":"12.2035294","type":"zebu","color":"green","client":"604GERESVK2123","contact":"JULIEN","address":"ITA 48 RAVENNA","phone1":"05 61 37 39 07","phone2":"julien.breuilh@gefco.net","phone3":"<a href=mailto:julien.breuilh@gefco.net> Contactez-moi </a> ","last_purchase_date":"24/04/2018 08:00" },
{ "id":104,"latitude":"51.6157885","longitude":"5.5392399","type":"zebu","color":"green","client":"568PEPT604FRA0103","contact":"JULIEN","address":"NLD 54 VEGHEL","phone1":"05 61 37 39 07","phone2":"julien.breuilh@gefco.net","phone3":"<a href=mailto:julien.breuilh@gefco.net> Contactez-moi </a> ","last_purchase_date":"24/04/2018 08:00" },
{ "id":105,"latitude":"51.3785373","longitude":"5.2658944","type":"zebu","color":"green","client":"568PEPT604FRA0093","contact":"JULIEN","address":"NLD 55 HAPERT","phone1":"05 61 37 39 07","phone2":"julien.breuilh@gefco.net","phone3":"<a href=mailto:julien.breuilh@gefco.net> Contactez-moi </a> ","last_purchase_date":"25/04/2018 08:00" },
{ "id":106,"latitude":"50.724993","longitude":"3.16207","type":"zebu","color":"green","client":"604GERESVK1869","contact":"JULIEN","address":"FRA 59 TOURCOING","phone1":"05 61 37 39 07","phone2":"julien.breuilh@gefco.net","phone3":"<a href=mailto:julien.breuilh@gefco.net> Contactez-moi </a> ","last_purchase_date":"25/04/2018 08:01" },
{ "id":107,"latitude":"47.639788","longitude":"6.17428","type":"zebu","color":"green","client":"568PEPT604FRA0119","contact":"JULIEN","address":"FRA 70 VESOUL","phone1":"05 61 37 39 07","phone2":"julien.breuilh@gefco.net","phone3":"<a href=mailto:julien.breuilh@gefco.net> Contactez-moi </a> ","last_purchase_date":"25/04/2018 14:00" },
{ "id":108,"latitude":"46.748342","longitude":"4.469799","type":"zebu","color":"green","client":"568PEPT604FRA0117","contact":"JULIEN","address":"FRA 71 MONTCHANIN","phone1":"05 61 37 39 07","phone2":"julien.breuilh@gefco.net","phone3":"<a href=mailto:julien.breuilh@gefco.net> Contactez-moi </a> ","last_purchase_date":"25/04/2018 08:00" },
{ "id":109,"latitude":"48.6105721","longitude":"2.6228436","type":"zebu","color":"yellow","client":"568PEPT604FRA0079","contact":"JULIEN","address":"FRA 77 REAU","phone1":"05 61 37 39 07","phone2":"julien.breuilh@gefco.net","phone3":"<a href=mailto:julien.breuilh@gefco.net> Contactez-moi </a> ","last_purchase_date":"23/04/2018 08:00" },
{ "id":110,"latitude":"48.787755","longitude":"1.819789","type":"zebu","color":"green","client":"568PEPT604FRA0106","contact":"JULIEN","address":"FRA 78 MERE","phone1":"05 61 37 39 07","phone2":"julien.breuilh@gefco.net","phone3":"<a href=mailto:julien.breuilh@gefco.net> Contactez-moi </a> ","last_purchase_date":"24/04/2018 09:00" },
{ "id":111,"latitude":"43.851815","longitude":"1.291067","type":"zebu","color":"green","client":"568PEPT604FRA0037","contact":"JULIEN","address":"FRA 82 CANALS","phone1":"05 61 37 39 07","phone2":"julien.breuilh@gefco.net","phone3":"<a href=mailto:julien.breuilh@gefco.net> Contactez-moi </a> ","last_purchase_date":"24/04/2018 12:00" },
{ "id":112,"latitude":"44.383724","longitude":"4.989187","type":"zebu","color":"green","client":"568PEPT604FRA0090","contact":"JULIEN","address":"FRA 84 VALREAS","phone1":"05 61 37 39 07","phone2":"julien.breuilh@gefco.net","phone3":"<a href=mailto:julien.breuilh@gefco.net> Contactez-moi </a> ","last_purchase_date":"27/04/2018 12:00" },
{ "id":113,"latitude":"48.935525","longitude":"2.303275","type":"zebu","color":"green","client":"568PEPT604FRA0099","contact":"JULIEN","address":"FRA 92 GENNEVILLIERS","phone1":"05 61 37 39 07","phone2":"julien.breuilh@gefco.net","phone3":"<a href=mailto:julien.breuilh@gefco.net> Contactez-moi </a> ","last_purchase_date":"24/04/2018 11:00" },
{ "id":114,"latitude":"53.3230048","longitude":"6.92796","type":"zebu","color":"green","client":"568PEPT604FRA0110","contact":"JULIEN","address":"NLD 99 FARMSUM","phone1":"05 61 37 39 07","phone2":"julien.breuilh@gefco.net","phone3":"<a href=mailto:julien.breuilh@gefco.net> Contactez-moi </a> ","last_purchase_date":"24/04/2018 08:00" },
{ "id":115,"latitude":"52.6353256","longitude":"-1.6938317","type":"zebu","color":"green","client":"568PEPT604FRA0094","contact":"JULIEN","address":"GBR B TAMWORTH","phone1":"05 61 37 39 07","phone2":"julien.breuilh@gefco.net","phone3":"<a href=mailto:julien.breuilh@gefco.net> Contactez-moi </a> ","last_purchase_date":"24/04/2018 08:00" },
{ "id":116,"latitude":"53.701688","longitude":"-1.298648","type":"zebu","color":"green","client":"568PEPT604FRA0104","contact":"JULIEN","address":"GBR WF PONTEFRACT","phone1":"05 61 37 39 07","phone2":"julien.breuilh@gefco.net","phone3":"<a href=mailto:julien.breuilh@gefco.net> Contactez-moi </a> ","last_purchase_date":"25/04/2018 11:00" },
{ "id":117,"latitude":"46.203896","longitude":"5.826733","type":"semem","color":"green","client":"600GEREFRA2225","contact":"LAURE","address":"FRA 01 CHAMPFROMIER","phone1":"02 99 05 44 90","phone2":"laure.boucher@gefco.net","phone3":"<a href=mailto:laure.boucher@gefco.net> Contactez-moi </a> ","last_purchase_date":"24/04/2018 00:01" },
{ "id":118,"latitude":"45.94094","longitude":"4.774296","type":"semem","color":"yellow","client":"600GEREFRA2273","contact":"LAURE","address":"FRA 01 TREVOUX","phone1":"02 99 05 44 90","phone2":"laure.boucher@gefco.net","phone3":"<a href=mailto:laure.boucher@gefco.net> Contactez-moi </a> ","last_purchase_date":"23/04/2018 15:00" },
{ "id":119,"latitude":"48.517732","longitude":"3.726275","type":"semem","color":"green","client":"600GEREFRA1747","contact":"LAURE","address":"FRA 10 ROMILLY SUR SEINE","phone1":"02 99 05 44 90","phone2":"laure.boucher@gefco.net","phone3":"<a href=mailto:laure.boucher@gefco.net> Contactez-moi </a> ","last_purchase_date":"24/04/2018 00:01" },
{ "id":120,"latitude":"48.1233774","longitude":"-1.5126751","type":"semem","color":"green","client":"600GEREFRA2297","contact":"LAURE","address":"FRA 35 NOYAL SUR VILAINE","phone1":"02 99 05 44 90","phone2":"laure.boucher@gefco.net","phone3":"<a href=mailto:laure.boucher@gefco.net> Contactez-moi </a> ","last_purchase_date":"24/04/2018 00:00" },
{ "id":121,"latitude":"45.1108608","longitude":"5.2573498","type":"semem","color":"green","client":"600GEREFRA1309","contact":"LAURE","address":"FRA 38 ST HILAIRE DU ROSIER","phone1":"02 99 05 44 90","phone2":"laure.boucher@gefco.net","phone3":"<a href=mailto:laure.boucher@gefco.net> Contactez-moi </a> ","last_purchase_date":"24/04/2018 16:00" },
{ "id":122,"latitude":"43.891922","longitude":"-1.135308","type":"semem","color":"green","client":"600GEREFRA2038","contact":"LAURE","address":"FRA 40 CASTETS","phone1":"02 99 05 44 90","phone2":"laure.boucher@gefco.net","phone3":"<a href=mailto:laure.boucher@gefco.net> Contactez-moi </a> ","last_purchase_date":"25/04/2018 09:00" },
{ "id":123,"latitude":"48.079215","longitude":"-0.81895","type":"semem","color":"green","client":"600GEREFRA2220","contact":"LAURE","address":"FRA 53 ST BERTHEVIN","phone1":"02 99 05 44 90","phone2":"laure.boucher@gefco.net","phone3":"<a href=mailto:laure.boucher@gefco.net> Contactez-moi </a> ","last_purchase_date":"24/04/2018 07:30" },
{ "id":124,"latitude":"49.505267","longitude":"0.370227","type":"semem","color":"green","client":"600GEREFRA2221","contact":"LAURE","address":"FRA 76 ST VIGOR D YMONVILLE","phone1":"02 99 05 44 90","phone2":"laure.boucher@gefco.net","phone3":"<a href=mailto:laure.boucher@gefco.net> Contactez-moi </a> ","last_purchase_date":"24/04/2018 10:00" },
{ "id":125,"latitude":"44.034945","longitude":"4.996762","type":"semem","color":"green","client":"600GEREFRA0870","contact":"LAURE","address":"FRA 84 MONTEUX","phone1":"02 99 05 44 90","phone2":"laure.boucher@gefco.net","phone3":"<a href=mailto:laure.boucher@gefco.net> Contactez-moi </a> ","last_purchase_date":"24/04/2018 12:01" },
{ "id":126,"latitude":"48.986011","longitude":"2.229632","type":"semem","color":"green","client":"600GEREFRA2084","contact":"LAURE","address":"FRA 95 FRANCONVILLE","phone1":"02 99 05 44 90","phone2":"laure.boucher@gefco.net","phone3":"<a href=mailto:laure.boucher@gefco.net> Contactez-moi </a> ","last_purchase_date":"25/04/2018 07:00" },
{ "id":127,"latitude":"48.996011","longitude":"2.239632","type":"semem","color":"yellow","client":"600GEREFRA2219","contact":"LAURE","address":"FRA 95 FRANCONVILLE","phone1":"02 99 05 44 90","phone2":"laure.boucher@gefco.net","phone3":"<a href=mailto:laure.boucher@gefco.net> Contactez-moi </a> ","last_purchase_date":"23/04/2018 07:00" },
{ "id":128,"latitude":"43.802389","longitude":"7.19712","type":"zebu","color":"green","client":"604GEREROM2082","contact":"STEVE","address":"FRA 06 CARROS","phone1":"05 61 37 38 78","phone2":"steve.pavie@gefco.net","phone3":"<a href=mailto:steve.pavie@gefco.net> Contactez-moi </a> ","last_purchase_date":"25/04/2018 09:00" },
{ "id":129,"latitude":"50.8503396","longitude":"4.3517103","type":"zebu","color":"green","client":"604GERELTU2171","contact":"STEVE","address":"BEL 10 BRUXELLES","phone1":"05 61 37 38 78","phone2":"steve.pavie@gefco.net","phone3":"<a href=mailto:steve.pavie@gefco.net> Contactez-moi </a> ","last_purchase_date":"24/04/2018 10:00" },
{ "id":130,"latitude":"43.588896","longitude":"5.002136","type":"zebu","color":"green","client":"604GERELTU1633","contact":"STEVE","address":"FRA 13 MIRAMAS","phone1":"05 61 37 38 78","phone2":"steve.pavie@gefco.net","phone3":"<a href=mailto:steve.pavie@gefco.net> Contactez-moi </a> ","last_purchase_date":"25/04/2018 05:00" },
{ "id":131,"latitude":"45.09975","longitude":"0.469484","type":"zebu","color":"green","client":"604GEREROM2017","contact":"STEVE","address":"FRA 24 NEUVIC","phone1":"05 61 37 38 78","phone2":"steve.pavie@gefco.net","phone3":"<a href=mailto:steve.pavie@gefco.net> Contactez-moi </a> ","last_purchase_date":"24/04/2018 11:00" },
{ "id":132,"latitude":"44.863449","longitude":"4.9433539","type":"zebu","color":"green","client":"604GERELTU1838","contact":"STEVE","address":"FRA 26 MONTELEGER","phone1":"05 61 37 38 78","phone2":"steve.pavie@gefco.net","phone3":"<a href=mailto:steve.pavie@gefco.net> Contactez-moi </a> ","last_purchase_date":"24/04/2018 09:00" },
{ "id":133,"latitude":"44.348678","longitude":"4.768295","type":"zebu","color":"green","client":"604GEREROM1966","contact":"STEVE","address":"FRA 26 ST PAUL TROIS CHATEAUX","phone1":"05 61 37 38 78","phone2":"steve.pavie@gefco.net","phone3":"<a href=mailto:steve.pavie@gefco.net> Contactez-moi </a> ","last_purchase_date":"24/04/2018 00:00" },
{ "id":134,"latitude":"50.81057","longitude":"4.93622","type":"zebu","color":"green","client":"604GEREROM2145","contact":"STEVE","address":"BEL 33 TIENEN","phone1":"05 61 37 38 78","phone2":"steve.pavie@gefco.net","phone3":"<a href=mailto:steve.pavie@gefco.net> Contactez-moi </a> ","last_purchase_date":"24/04/2018 08:00" },
{ "id":135,"latitude":"48.163561","longitude":"-1.673146","type":"zebu","color":"green","client":"604GERELTU1916","contact":"STEVE","address":"FRA 35 ST GREGOIRE","phone1":"05 61 37 38 78","phone2":"steve.pavie@gefco.net","phone3":"<a href=mailto:steve.pavie@gefco.net> Contactez-moi </a> ","last_purchase_date":"24/04/2018 00:01" },
{ "id":136,"latitude":"45.336168","longitude":"5.574722","type":"zebu","color":"yellow","client":"604GERELTU1834","contact":"STEVE","address":"FRA 38 MOIRANS","phone1":"05 61 37 38 78","phone2":"steve.pavie@gefco.net","phone3":"<a href=mailto:steve.pavie@gefco.net> Contactez-moi </a> ","last_purchase_date":"23/04/2018 08:30" },
{ "id":137,"latitude":"49.246379","longitude":"6.224908","type":"zebu","color":"green","client":"604GERELTU1944","contact":"STEVE","address":"FRA 57 TREMERY","phone1":"05 61 37 38 78","phone2":"steve.pavie@gefco.net","phone3":"<a href=mailto:steve.pavie@gefco.net> Contactez-moi </a> ","last_purchase_date":"26/04/2018 11:30" },
{ "id":138,"latitude":"50.734993","longitude":"3.17207","type":"zebu","color":"green","client":"604GERELTU1930","contact":"STEVE","address":"FRA 59 TOURCOING","phone1":"05 61 37 38 78","phone2":"steve.pavie@gefco.net","phone3":"<a href=mailto:steve.pavie@gefco.net> Contactez-moi </a> ","last_purchase_date":"25/04/2018 00:01" },
{ "id":139,"latitude":"47.649788","longitude":"6.18428","type":"zebu","color":"red","client":"604GEREROM2043","contact":"STEVE","address":"FRA 70 VESOUL","phone1":"05 61 37 38 78","phone2":"steve.pavie@gefco.net","phone3":"<a href=mailto:steve.pavie@gefco.net> Contactez-moi </a> ","last_purchase_date":"20/04/2018 09:40" },
{ "id":140,"latitude":"47.659788","longitude":"6.19428","type":"zebu","color":"green","client":"604GERELTU2162","contact":"STEVE","address":"FRA 70 VESOUL","phone1":"05 61 37 38 78","phone2":"steve.pavie@gefco.net","phone3":"<a href=mailto:steve.pavie@gefco.net> Contactez-moi </a> ","last_purchase_date":"24/04/2018 10:00" },
{ "id":141,"latitude":"47.8504856","longitude":"-0.3234185","type":"zebu","color":"yellow","client":"604GERELTU1830","contact":"STEVE","address":"FRA 72 SABLE SUR SARTHE","phone1":"05 61 37 38 78","phone2":"steve.pavie@gefco.net","phone3":"<a href=mailto:steve.pavie@gefco.net> Contactez-moi </a> ","last_purchase_date":"23/04/2018 00:00" },
{ "id":142,"latitude":"46.387104","longitude":"6.542816","type":"zebu","color":"green","client":"604GERELTU1765","contact":"STEVE","address":"FRA 74 PUBLIER","phone1":"05 61 37 38 78","phone2":"steve.pavie@gefco.net","phone3":"<a href=mailto:steve.pavie@gefco.net> Contactez-moi </a> ","last_purchase_date":"25/04/2018 09:30" },
{ "id":143,"latitude":"48.76564","longitude":"8.2285242","type":"zebu","color":"green","client":"604GERELTU1644","contact":"STEVE","address":"DEU 76 BADEN BADEN","phone1":"05 61 37 38 78","phone2":"steve.pavie@gefco.net","phone3":"<a href=mailto:steve.pavie@gefco.net> Contactez-moi </a> ","last_purchase_date":"25/04/2018 00:01" },
{ "id":144,"latitude":"48.8591174","longitude":"8.2059096","type":"zebu","color":"green","client":"604GEREROM2173","contact":"STEVE","address":"DEU 76 RASTATT","phone1":"05 61 37 38 78","phone2":"steve.pavie@gefco.net","phone3":"<a href=mailto:steve.pavie@gefco.net> Contactez-moi </a> ","last_purchase_date":"24/04/2018 00:00" },
{ "id":145,"latitude":"48.8691174","longitude":"8.2159096","type":"zebu","color":"green","client":"604GEREROM2174","contact":"STEVE","address":"DEU 76 RASTATT","phone1":"05 61 37 38 78","phone2":"steve.pavie@gefco.net","phone3":"<a href=mailto:steve.pavie@gefco.net> Contactez-moi </a> ","last_purchase_date":"26/04/2018 00:00" },
{ "id":146,"latitude":"48.8791174","longitude":"8.2259096","type":"zebu","color":"green","client":"604GEREROM2175","contact":"STEVE","address":"DEU 76 RASTATT","phone1":"05 61 37 38 78","phone2":"steve.pavie@gefco.net","phone3":"<a href=mailto:steve.pavie@gefco.net> Contactez-moi </a> ","last_purchase_date":"25/04/2018 00:00" },
{ "id":147,"latitude":"49.872722","longitude":"2.35537","type":"zebu","color":"green","client":"604GERELTU1661","contact":"STEVE","address":"FRA 80 LONGUEAU","phone1":"05 61 37 38 78","phone2":"steve.pavie@gefco.net","phone3":"<a href=mailto:steve.pavie@gefco.net> Contactez-moi </a> ","last_purchase_date":"24/04/2018 06:00" },
{ "id":148,"latitude":"51.21543","longitude":"2.928656","type":"zebu","color":"yellow","client":"604GERELTU1619","contact":"STEVE","address":"BEL 84 OOSTENDE","phone1":"05 61 37 38 78","phone2":"steve.pavie@gefco.net","phone3":"<a href=mailto:steve.pavie@gefco.net> Contactez-moi </a> ","last_purchase_date":"23/04/2018 09:00" },
{ "id":149,"latitude":"48.656473","longitude":"2.385166","type":"zebu","color":"green","client":"604GEREROM2128","contact":"STEVE","address":"FRA 91 GRIGNY","phone1":"05 61 37 38 78","phone2":"steve.pavie@gefco.net","phone3":"<a href=mailto:steve.pavie@gefco.net> Contactez-moi </a> ","last_purchase_date":"24/04/2018 06:00" },
{ "id":150,"latitude":"48.945525","longitude":"2.313275","type":"zebu","color":"yellow","client":"604GERELTU1625","contact":"STEVE","address":"FRA 92 GENNEVILLIER","phone1":"05 61 37 38 78","phone2":"steve.pavie@gefco.net","phone3":"<a href=mailto:steve.pavie@gefco.net> Contactez-moi </a> ","last_purchase_date":"23/04/2018 10:00" },
{ "id":151,"latitude":"48.955525","longitude":"2.323275","type":"zebu","color":"green","client":"604GERELTU1943","contact":"STEVE","address":"FRA 92 GENNEVILLIERS","phone1":"05 61 37 38 78","phone2":"steve.pavie@gefco.net","phone3":"<a href=mailto:steve.pavie@gefco.net> Contactez-moi </a> ","last_purchase_date":"24/04/2018 05:00" },
{ "id":152,"latitude":"48.965525","longitude":"2.333275","type":"zebu","color":"yellow","client":"604GERELTU1806","contact":"STEVE","address":"FRA 92 GENNEVILLIERS","phone1":"05 61 37 38 78","phone2":"steve.pavie@gefco.net","phone3":"<a href=mailto:steve.pavie@gefco.net> Contactez-moi </a> ","last_purchase_date":"23/04/2018 05:00" },
{ "id":153,"latitude":"50.8603396","longitude":"4.3617103","type":"zebu","color":"green","client":"604GERELTU1908","contact":"TIMOTHEE","address":"BEL 11 BRUXELLES","phone1":"05 61 37 39 03","phone2":"timothee.labourdette2@gefco.net","phone3":"<a href=mailto:timothee.labourdette2@gefco.net> Contactez-moi </a> ","last_purchase_date":"26/04/2018 08:00" },
{ "id":154,"latitude":"43.458598","longitude":"5.249703","type":"zebu","color":"green","client":"604GEREBGR1785","contact":"TIMOTHEE","address":"FRA 13 VITROLLES","phone1":"05 61 37 39 03","phone2":"timothee.labourdette2@gefco.net","phone3":"<a href=mailto:timothee.labourdette2@gefco.net> Contactez-moi </a> ","last_purchase_date":"24/04/2018 09:00" },
{ "id":155,"latitude":"44.873449","longitude":"4.9533539","type":"zebu","color":"green","client":"604GERELTU1658","contact":"TIMOTHEE","address":"FRA 26 MONTELEGER","phone1":"05 61 37 39 03","phone2":"timothee.labourdette2@gefco.net","phone3":"<a href=mailto:timothee.labourdette2@gefco.net> Contactez-moi </a> ","last_purchase_date":"24/04/2018 07:00" },
{ "id":156,"latitude":"52.0438616","longitude":"4.5763794","type":"zebu","color":"green","client":"604GEREROM1852","contact":"TIMOTHEE","address":"NLD 27 MOERKAPELLE","phone1":"05 61 37 39 03","phone2":"timothee.labourdette2@gefco.net","phone3":"<a href=mailto:timothee.labourdette2@gefco.net> Contactez-moi </a> ","last_purchase_date":"25/04/2018 14:01" },
{ "id":157,"latitude":"47.09534","longitude":"5.49081","type":"zebu","color":"green","client":"604GEREBGR1784","contact":"TIMOTHEE","address":"FRA 39 DOLE","phone1":"05 61 37 39 03","phone2":"timothee.labourdette2@gefco.net","phone3":"<a href=mailto:timothee.labourdette2@gefco.net> Contactez-moi </a> ","last_purchase_date":"25/04/2018 00:00" },
{ "id":158,"latitude":"47.669788","longitude":"6.20428","type":"zebu","color":"green","client":"604GERELTU1726","contact":"TIMOTHEE","address":"FRA 70 VESOUL","phone1":"05 61 37 39 03","phone2":"timothee.labourdette2@gefco.net","phone3":"<a href=mailto:timothee.labourdette2@gefco.net> Contactez-moi </a> ","last_purchase_date":"24/04/2018 10:20" },
{ "id":159,"latitude":"44.104852","longitude":"1.08468","type":"zebu","color":"blue","client":"604GERELTU1902","contact":"TIMOTHEE","address":"FRA 82 MOISSAC","phone1":"05 61 37 39 03","phone2":"timothee.labourdette2@gefco.net","phone3":"<a href=mailto:timothee.labourdette2@gefco.net> Contactez-moi </a> ","last_purchase_date":"30/04/2018 08:00" },
{ "id":160,"latitude":"51.0643422","longitude":"3.7274243","type":"zebu","color":"green","client":"604GERELTU1751","contact":"TIMOTHEE","address":"BEL 90 GENT","phone1":"05 61 37 39 03","phone2":"timothee.labourdette2@gefco.net","phone3":"<a href=mailto:timothee.labourdette2@gefco.net> Contactez-moi </a> ","last_purchase_date":"24/04/2018 13:30" },
{ "id":161,"latitude":"43.212161","longitude":"2.353663","type":"semem","color":"yellow","client":"600GEREFRA1043","contact":"VALERIE","address":"FRA 11 CARCASSONNE","phone1":"02 99 05 85 75","phone2":"valerie.charrieau@gefco.net","phone3":"<a href=mailto:valerie.charrieau@gefco.net> Contactez-moi </a> ","last_purchase_date":"23/04/2018 10:00" },
{ "id":162,"latitude":"43.676647","longitude":"4.6277769","type":"semem","color":"yellow","client":"600GEREFRA2083","contact":"VALERIE","address":"FRA 13 ARLES","phone1":"02 99 05 85 75","phone2":"valerie.charrieau@gefco.net","phone3":"<a href=mailto:valerie.charrieau@gefco.net> Contactez-moi </a> ","last_purchase_date":"23/04/2018 10:00" },
{ "id":163,"latitude":"43.490621","longitude":"5.632019","type":"semem","color":"yellow","client":"600GEREFRA2015","contact":"VALERIE","address":"FRA 13 ROUSSET","phone1":"02 99 05 85 75","phone2":"valerie.charrieau@gefco.net","phone3":"<a href=mailto:valerie.charrieau@gefco.net> Contactez-moi </a> ","last_purchase_date":"23/04/2018 12:00" },
{ "id":164,"latitude":"46.028559","longitude":"0.199339","type":"semem","color":"yellow","client":"600GEREFRA1093","contact":"VALERIE","address":"FRA 16 RUFFEC","phone1":"02 99 05 85 75","phone2":"valerie.charrieau@gefco.net","phone3":"<a href=mailto:valerie.charrieau@gefco.net> Contactez-moi </a> ","last_purchase_date":"23/04/2018 14:59" },
{ "id":165,"latitude":"45.303688","longitude":"0.7617819","type":"semem","color":"yellow","client":"600GEREFRA2276","contact":"VALERIE","address":"FRA 24 AGONAC","phone1":"02 99 05 85 75","phone2":"valerie.charrieau@gefco.net","phone3":"<a href=mailto:valerie.charrieau@gefco.net> Contactez-moi </a> ","last_purchase_date":"23/04/2018 12:00" },
{ "id":166,"latitude":"44.883449","longitude":"4.9633539","type":"semem","color":"green","client":"600GEREFRA1694","contact":"VALERIE","address":"FRA 26  MONTELEGER","phone1":"02 99 05 85 75","phone2":"valerie.charrieau@gefco.net","phone3":"<a href=mailto:valerie.charrieau@gefco.net> Contactez-moi </a> ","last_purchase_date":"24/04/2018 15:00" },
{ "id":167,"latitude":"44.893449","longitude":"4.9733539","type":"semem","color":"green","client":"600GEREFRA1952","contact":"VALERIE","address":"FRA 26 MONTELEGER","phone1":"02 99 05 85 75","phone2":"valerie.charrieau@gefco.net","phone3":"<a href=mailto:valerie.charrieau@gefco.net> Contactez-moi </a> ","last_purchase_date":"24/04/2018 15:00" },
{ "id":168,"latitude":"48.76764","longitude":"1.194323","type":"semem","color":"yellow","client":"600GEREFRA0903","contact":"VALERIE","address":"FRA 28 ST LUBIN DES JONCHERETS","phone1":"02 99 05 85 75","phone2":"valerie.charrieau@gefco.net","phone3":"<a href=mailto:valerie.charrieau@gefco.net> Contactez-moi </a> ","last_purchase_date":"23/04/2018 10:00" },
{ "id":169,"latitude":"43.656681","longitude":"3.9693","type":"semem","color":"yellow","client":"600GEREFRA2205","contact":"VALERIE","address":"FRA 34 VENDARGUES","phone1":"02 99 05 85 75","phone2":"valerie.charrieau@gefco.net","phone3":"<a href=mailto:valerie.charrieau@gefco.net> Contactez-moi </a> ","last_purchase_date":"23/04/2018 14:00" },
{ "id":170,"latitude":"45.645477","longitude":"4.046971","type":"semem","color":"yellow","client":"600GEREFRA0271","contact":"VALERIE","address":"FRA 42 CHAMPDIEU","phone1":"02 99 05 85 75","phone2":"valerie.charrieau@gefco.net","phone3":"<a href=mailto:valerie.charrieau@gefco.net> Contactez-moi </a> ","last_purchase_date":"23/04/2018 12:00" },
{ "id":171,"latitude":"49.273944","longitude":"4.114794","type":"semem","color":"green","client":"600GEREFRA1044","contact":"VALERIE","address":"FRA 51 CERNAY LES REIMS","phone1":"02 99 05 85 75","phone2":"valerie.charrieau@gefco.net","phone3":"<a href=mailto:valerie.charrieau@gefco.net> Contactez-moi </a> ","last_purchase_date":"25/04/2018 08:00" },
{ "id":172,"latitude":"43.492949","longitude":"-1.474841","type":"semem","color":"green","client":"600GEREFRA0940","contact":"VALERIE","address":"FRA 64 BAYONNE","phone1":"02 99 05 85 75","phone2":"valerie.charrieau@gefco.net","phone3":"<a href=mailto:valerie.charrieau@gefco.net> Contactez-moi </a> ","last_purchase_date":"24/04/2018 07:30" },
{ "id":173,"latitude":"47.750839","longitude":"7.335888","type":"semem","color":"yellow","client":"600GEREFRA2172","contact":"VALERIE","address":"FRA 68 MULHOUSE","phone1":"02 99 05 85 75","phone2":"valerie.charrieau@gefco.net","phone3":"<a href=mailto:valerie.charrieau@gefco.net> Contactez-moi </a> ","last_purchase_date":"23/04/2018 05:00" },
{ "id":174,"latitude":"43.151682","longitude":"6.342202","type":"semem","color":"green","client":"600GEREFRA0819","contact":"VALERIE","address":"FRA 83 BORMES LES MIMOSAS","phone1":"02 99 05 85 75","phone2":"valerie.charrieau@gefco.net","phone3":"<a href=mailto:valerie.charrieau@gefco.net> Contactez-moi </a> ","last_purchase_date":"24/04/2018 08:00" },
{ "id":175,"latitude":"43.949317","longitude":"4.805528","type":"semem","color":"green","client":"600GEREFRA0583","contact":"VALERIE","address":"FRA 84 AVIGNON","phone1":"02 99 05 85 75","phone2":"valerie.charrieau@gefco.net","phone3":"<a href=mailto:valerie.charrieau@gefco.net> Contactez-moi </a> ","last_purchase_date":"25/04/2018 08:00" },
{"id":200,"latitude":"48.858053","longitude":"2.294289","type":"zebu","color":"blue","client":"LA TOUR EIFFEL","contact":"Gustave eiffel","address":"FRA 75 PARIS(CENTRAGE CARTE)","phone1":"05 61 37 39 02","phone2":"vincent.lafay@gefco.net","phone3":"<a href=mailto:vincent.lafay@gefco.net> Contactez-moi </a> ","last_purchase_date":" mars 1889, pour l'Exposition universelle" }]








