[
{ "id":1,"latitude":"50.59252","longitude":"3.165241","type":"semem","color":"yellow","client":"600GEREFRA2055","contact":"ALAIN","address":"FRA 59 SAINGHIN EN MELANTOIS","phone1":"02 99 05 44 91","phone2":"alain.patrel@gefco.net","phone3":"<a href=mailto:alain.patrel@gefco.net> Contactez-moi </a> ","last_purchase_date":"12/08/2017 01:30" },
{ "id":3,"latitude":"49.825494","longitude":"3.285468","type":"semem","color":"yellow","client":"600GEREFRA2104","contact":"CHRISTEL","address":"FRA 02 GAUCHY","phone1":"02 99 05 44 94","phone2":"christel.michel@gefco.net","phone3":"<a href=mailto:christel.michel@gefco.net> Contactez-moi </a> ","last_purchase_date":"10/08/2017 11:00" },
{ "id":4,"latitude":"46.028559","longitude":"0.199339","type":"semem","color":"yellow","client":"600GEREFRA1405","contact":"CHRISTEL","address":"FRA 16 RUFFEC","phone1":"02 99 05 44 94","phone2":"christel.michel@gefco.net","phone3":"<a href=mailto:christel.michel@gefco.net> Contactez-moi </a> ","last_purchase_date":"11/08/2017 08:00" },
{ "id":5,"latitude":"43.458611","longitude":"2.004573","type":"semem","color":"yellow","client":"600GEREFRA2071","contact":"CHRISTEL","address":"FRA 31 REVEL","phone1":"02 99 05 44 94","phone2":"christel.michel@gefco.net","phone3":"<a href=mailto:christel.michel@gefco.net> Contactez-moi </a> ","last_purchase_date":"11/08/2017 10:00" },
{ "id":7,"latitude":"47.51943","longitude":"-1.955267","type":"semem","color":"yellow","client":"600GEREFRA2103","contact":"CHRISTEL","address":"FRA 44 GUENROUET","phone1":"02 99 05 44 94","phone2":"christel.michel@gefco.net","phone3":"<a href=mailto:christel.michel@gefco.net> Contactez-moi </a> ","last_purchase_date":"10/08/2017 14:30" },
{ "id":8,"latitude":"47.705239","longitude":"6.685062","type":"semem","color":"yellow","client":"600GEREFRA1805","contact":"CHRISTEL","address":"FRA 70 CHAMPAGNEY","phone1":"02 99 05 44 94","phone2":"christel.michel@gefco.net","phone3":"<a href=mailto:christel.michel@gefco.net> Contactez-moi </a> ","last_purchase_date":"11/08/2017 10:00" },
{ "id":10,"latitude":"49.0096906","longitude":"2.5479245","type":"semem","color":"yellow","client":"600GEREFRA1960","contact":"CHRISTEL","address":"FRA 95 ROISSY CDG","phone1":"02 99 05 44 94","phone2":"christel.michel@gefco.net","phone3":"<a href=mailto:christel.michel@gefco.net> Contactez-moi </a> ","last_purchase_date":"11/08/2017 05:00" },
{ "id":11,"latitude":"49.0196906","longitude":"2.5579245","type":"semem","color":"yellow","client":"600GEREFRA1541","contact":"CHRISTEL","address":"FRA 95 ROISSY CDG","phone1":"02 99 05 44 94","phone2":"christel.michel@gefco.net","phone3":"<a href=mailto:christel.michel@gefco.net> Contactez-moi </a> ","last_purchase_date":"11/08/2017 07:00" },
{ "id":12,"latitude":"49.0296906","longitude":"2.5679245","type":"semem","color":"red","client":"600GEREFRA1724","contact":"CHRISTEL","address":"FRA 95 ROISSY CDG","phone1":"02 99 05 44 94","phone2":"christel.michel@gefco.net","phone3":"<a href=mailto:christel.michel@gefco.net> Contactez-moi </a> ","last_purchase_date":"07/08/2017 12:00" },
{ "id":13,"latitude":"49.0396906","longitude":"2.5779245","type":"semem","color":"yellow","client":"600GEREFRA2011","contact":"CHRISTEL","address":"FRA 95 ROISSY CDG","phone1":"02 99 05 44 94","phone2":"christel.michel@gefco.net","phone3":"<a href=mailto:christel.michel@gefco.net> Contactez-moi </a> ","last_purchase_date":"10/08/2017 05:00" },
{ "id":14,"latitude":"46.236466","longitude":"5.97991","type":"zebu","color":"yellow","client":"604GERELTU1739","contact":"DANIEL","address":"FRA 01 THOIRY","phone1":"05 61 37 39 26","phone2":"daniel.saez@gefco.net","phone3":"<a href=mailto:daniel.saez@gefco.net> Contactez-moi </a> ","last_purchase_date":"11/08/2017 08:00" },
{ "id":15,"latitude":"50.8771683","longitude":"4.3545087","type":"zebu","color":"yellow","client":"604GEREROM2082","contact":"DANIEL","address":"BEL 10 LAEKEN","phone1":"05 61 37 39 26","phone2":"daniel.saez@gefco.net","phone3":"<a href=mailto:daniel.saez@gefco.net> Contactez-moi </a> ","last_purchase_date":"11/08/2017 06:30" },
{ "id":16,"latitude":"43.676647","longitude":"4.6277769","type":"zebu","color":"yellow","client":"604GERELTU1732","contact":"DANIEL","address":"FRA 13 ARLES","phone1":"05 61 37 39 26","phone2":"daniel.saez@gefco.net","phone3":"<a href=mailto:daniel.saez@gefco.net> Contactez-moi </a> ","last_purchase_date":"11/08/2017 08:00" },
{ "id":17,"latitude":"51.4456","longitude":"4.7383","type":"zebu","color":"green","client":"604GERELTU1625","contact":"DANIEL","address":"BEL 23 MEER","phone1":"05 61 37 39 26","phone2":"daniel.saez@gefco.net","phone3":"<a href=mailto:daniel.saez@gefco.net> Contactez-moi </a> ","last_purchase_date":"14/08/2017 00:00" },
{ "id":18,"latitude":"51.1683102","longitude":"4.3942868","type":"zebu","color":"green","client":"604GERELTU1886","contact":"DANIEL","address":"BEL 26 WILRIJK","phone1":"05 61 37 39 26","phone2":"daniel.saez@gefco.net","phone3":"<a href=mailto:daniel.saez@gefco.net> Contactez-moi </a> ","last_purchase_date":"14/08/2017 08:00" },
{ "id":19,"latitude":"49.04771","longitude":"1.162302","type":"zebu","color":"yellow","client":"604GERELTU1668","contact":"DANIEL","address":"FRA 27 GRAVIGNY","phone1":"05 61 37 39 26","phone2":"daniel.saez@gefco.net","phone3":"<a href=mailto:daniel.saez@gefco.net> Contactez-moi </a> ","last_purchase_date":"11/08/2017 08:00" },
{ "id":21,"latitude":"43.656681","longitude":"3.9693","type":"zebu","color":"green","client":"604GEREROM2017","contact":"DANIEL","address":"FRA 34 VENDARGUES","phone1":"05 61 37 39 26","phone2":"daniel.saez@gefco.net","phone3":"<a href=mailto:daniel.saez@gefco.net> Contactez-moi </a> ","last_purchase_date":"14/08/2017 16:00" },
{ "id":22,"latitude":"50.8157248","longitude":"5.1862508","type":"zebu","color":"yellow","client":"604GERELTU2080","contact":"DANIEL","address":"BEL 38 SINT TRUIDEN","phone1":"05 61 37 39 26","phone2":"daniel.saez@gefco.net","phone3":"<a href=mailto:daniel.saez@gefco.net> Contactez-moi </a> ","last_purchase_date":"11/08/2017 08:00" },
{ "id":23,"latitude":"50.64547","longitude":"5.63488","type":"zebu","color":"green","client":"604GEREROM2141","contact":"DANIEL","address":"BEL 40 JUPILLE SUR MEUSE","phone1":"05 61 37 39 26","phone2":"daniel.saez@gefco.net","phone3":"<a href=mailto:daniel.saez@gefco.net> Contactez-moi </a> ","last_purchase_date":"16/08/2017 08:00" },
{ "id":24,"latitude":"43.893485","longitude":"-0.499782","type":"zebu","color":"yellow","client":"604GERELTU2073","contact":"DANIEL","address":"FRA 40 MONT DE MARSAN","phone1":"05 61 37 39 26","phone2":"daniel.saez@gefco.net","phone3":"<a href=mailto:daniel.saez@gefco.net> Contactez-moi </a> ","last_purchase_date":"10/08/2017 14:00" },
{ "id":25,"latitude":"45.476088","longitude":"4.5127119","type":"zebu","color":"yellow","client":"604GERELTU1838","contact":"DANIEL","address":"FRA 42 ST CHAMOND","phone1":"05 61 37 39 26","phone2":"daniel.saez@gefco.net","phone3":"<a href=mailto:daniel.saez@gefco.net> Contactez-moi </a> ","last_purchase_date":"11/08/2017 08:00" },
{ "id":26,"latitude":"51.4556432","longitude":"7.0115552","type":"zebu","color":"yellow","client":"604GERELTU1633","contact":"DANIEL","address":"DEU 45 ESSEN","phone1":"05 61 37 39 26","phone2":"daniel.saez@gefco.net","phone3":"<a href=mailto:daniel.saez@gefco.net> Contactez-moi </a> ","last_purchase_date":"11/08/2017 00:00" },
{ "id":27,"latitude":"47.868809","longitude":"2.128604","type":"zebu","color":"yellow","client":"604GEREROM2146","contact":"DANIEL","address":"FRA 45 ST DENIS DE L HOTEL","phone1":"05 61 37 39 26","phone2":"daniel.saez@gefco.net","phone3":"<a href=mailto:daniel.saez@gefco.net> Contactez-moi </a> ","last_purchase_date":"11/08/2017 07:00" },
{ "id":28,"latitude":"44.359532","longitude":"1.4062079","type":"zebu","color":"green","client":"604GERELTU2081","contact":"DANIEL","address":"FRA 46 LHOSPITALET","phone1":"05 61 37 39 26","phone2":"daniel.saez@gefco.net","phone3":"<a href=mailto:daniel.saez@gefco.net> Contactez-moi </a> ","last_purchase_date":"17/08/2017 10:00" },
{ "id":29,"latitude":"51.5236773","longitude":"5.0641948","type":"zebu","color":"green","client":"604GERELTU2064","contact":"DANIEL","address":"NLD 50 GOIRLE","phone1":"05 61 37 39 26","phone2":"daniel.saez@gefco.net","phone3":"<a href=mailto:daniel.saez@gefco.net> Contactez-moi </a> ","last_purchase_date":"14/08/2017 08:00" },
{ "id":30,"latitude":"49.258329","longitude":"4.031696","type":"zebu","color":"yellow","client":"604GERELTU1677","contact":"DANIEL","address":"FRA 51 REIMS","phone1":"05 61 37 39 26","phone2":"daniel.saez@gefco.net","phone3":"<a href=mailto:daniel.saez@gefco.net> Contactez-moi </a> ","last_purchase_date":"10/08/2017 12:00" },
{ "id":31,"latitude":"49.1193089","longitude":"6.1757156","type":"zebu","color":"yellow","client":"604GERELTU1735","contact":"DANIEL","address":"FRA 57 METZ","phone1":"05 61 37 39 26","phone2":"daniel.saez@gefco.net","phone3":"<a href=mailto:daniel.saez@gefco.net> Contactez-moi </a> ","last_purchase_date":"10/08/2017 08:00" },
{ "id":32,"latitude":"48.824882","longitude":"7.482779","type":"zebu","color":"yellow","client":"604GERELTU2062","contact":"DANIEL","address":"FRA 67 BOUXWILLER","phone1":"05 61 37 39 26","phone2":"daniel.saez@gefco.net","phone3":"<a href=mailto:daniel.saez@gefco.net> Contactez-moi </a> ","last_purchase_date":"11/08/2017 08:00" },
{ "id":33,"latitude":"51.9646995","longitude":"6.2937736","type":"zebu","color":"yellow","client":"604GEREROM2128","contact":"DANIEL","address":"NLD 70 DOETINCHEM","phone1":"05 61 37 39 26","phone2":"daniel.saez@gefco.net","phone3":"<a href=mailto:daniel.saez@gefco.net> Contactez-moi </a> ","last_purchase_date":"11/08/2017 13:00" },
{ "id":34,"latitude":"47.856758","longitude":"6.334178","type":"zebu","color":"yellow","client":"604GERELTU1644","contact":"DANIEL","address":"FRA 70 FONTAINE LES LUXEUIL","phone1":"05 61 37 39 26","phone2":"daniel.saez@gefco.net","phone3":"<a href=mailto:daniel.saez@gefco.net> Contactez-moi </a> ","last_purchase_date":"11/08/2017 08:00" },
{ "id":35,"latitude":"47.619788","longitude":"6.15428","type":"zebu","color":"yellow","client":"604GERELTU1701","contact":"DANIEL","address":"FRA 70 VESOUL","phone1":"05 61 37 39 26","phone2":"daniel.saez@gefco.net","phone3":"<a href=mailto:daniel.saez@gefco.net> Contactez-moi </a> ","last_purchase_date":"10/08/2017 11:20" },
{ "id":36,"latitude":"48.817223","longitude":"1.949075","type":"zebu","color":"yellow","client":"604GERELTU1885","contact":"DANIEL","address":"FRA 78 PLAISIR","phone1":"05 61 37 39 26","phone2":"daniel.saez@gefco.net","phone3":"<a href=mailto:daniel.saez@gefco.net> Contactez-moi </a> ","last_purchase_date":"11/08/2017 07:00" },
{ "id":37,"latitude":"44.008767","longitude":"4.872757","type":"zebu","color":"yellow","client":"604GERELTU1766","contact":"DANIEL","address":"FRA 84 SORGUES","phone1":"05 61 37 39 26","phone2":"daniel.saez@gefco.net","phone3":"<a href=mailto:daniel.saez@gefco.net> Contactez-moi </a> ","last_purchase_date":"11/08/2017 08:00" },
{ "id":38,"latitude":"51.0543422","longitude":"3.7174243","type":"zebu","color":"yellow","client":"604GERELTU2063","contact":"DANIEL","address":"BEL 90 GENT","phone1":"05 61 37 39 26","phone2":"daniel.saez@gefco.net","phone3":"<a href=mailto:daniel.saez@gefco.net> Contactez-moi </a> ","last_purchase_date":"11/08/2017 10:00" },
{ "id":39,"latitude":"51.0643422","longitude":"3.7274243","type":"zebu","color":"green","client":"604GEREROM2143","contact":"DANIEL","address":"BEL 90 GENT","phone1":"05 61 37 39 26","phone2":"daniel.saez@gefco.net","phone3":"<a href=mailto:daniel.saez@gefco.net> Contactez-moi </a> ","last_purchase_date":"14/08/2017 10:00" },
{ "id":40,"latitude":"51.0743422","longitude":"3.7374243","type":"zebu","color":"yellow","client":"604GEREROM2145","contact":"DANIEL","address":"BEL 90 GENT","phone1":"05 61 37 39 26","phone2":"daniel.saez@gefco.net","phone3":"<a href=mailto:daniel.saez@gefco.net> Contactez-moi </a> ","last_purchase_date":"11/08/2017 10:00" },
{ "id":41,"latitude":"51.2526476","longitude":"4.2786812","type":"zebu","color":"green","client":"604GERELTU2067","contact":"DANIEL","address":"BEL 91 KALLO","phone1":"05 61 37 39 26","phone2":"daniel.saez@gefco.net","phone3":"<a href=mailto:daniel.saez@gefco.net> Contactez-moi </a> ","last_purchase_date":"14/08/2017 08:00" },
{ "id":42,"latitude":"48.925525","longitude":"2.293275","type":"zebu","color":"yellow","client":"604GERELTU1738","contact":"DANIEL","address":"FRA 92 GENNEVILLIERS","phone1":"05 61 37 39 26","phone2":"daniel.saez@gefco.net","phone3":"<a href=mailto:daniel.saez@gefco.net> Contactez-moi </a> ","last_purchase_date":"11/08/2017 08:00" },
{ "id":43,"latitude":"48.825787","longitude":"2.546798","type":"zebu","color":"yellow","client":"604GEREROM2043","contact":"DANIEL","address":"FRA 94 VILLIERS SUR MARNE","phone1":"05 61 37 39 26","phone2":"daniel.saez@gefco.net","phone3":"<a href=mailto:daniel.saez@gefco.net> Contactez-moi </a> ","last_purchase_date":"11/08/2017 07:00" },
{ "id":44,"latitude":"49.328117","longitude":"1.105122","type":"semem","color":"yellow","client":"600GEREFRA2905","contact":"GHISLAIN","address":"FRA 76 TOURVILLE LA RIVIERE","phone1":"02 99 05 44 92","phone2":"ghislain.cailliau@gefco.net","phone3":"<a href=mailto:ghislain.cailliau@gefco.net> Contactez-moi </a> ","last_purchase_date":"11/08/2017 05:00" },
{ "id":45,"latitude":"49.338117","longitude":"1.115122","type":"semem","color":"yellow","client":"600GEREFRA2070","contact":"GHISLAIN","address":"FRA 76 TOURVILLE LA RIVIERE","phone1":"02 99 05 44 92","phone2":"ghislain.cailliau@gefco.net","phone3":"<a href=mailto:ghislain.cailliau@gefco.net> Contactez-moi </a> ","last_purchase_date":"10/08/2017 05:00" },
{ "id":46,"latitude":"44.741163","longitude":"-0.684355","type":"zebu","color":"yellow","client":"568PEPT604FRA0037","contact":"JULIEN","address":"FRA 33 CESTAS","phone1":"05 61 37 39 07","phone2":"julien.breuilh@gefco.net","phone3":"<a href=mailto:julien.breuilh@gefco.net> Contactez-moi </a> ","last_purchase_date":"11/08/2017 11:00" },
{ "id":47,"latitude":"45.38262","longitude":"4.749246","type":"zebu","color":"yellow","client":"568PEPT604FRA0027","contact":"JULIEN","address":"FRA 42 ST PIERRE DE BOEUF","phone1":"05 61 37 39 07","phone2":"julien.breuilh@gefco.net","phone3":"<a href=mailto:julien.breuilh@gefco.net> Contactez-moi </a> ","last_purchase_date":"11/08/2017 08:00" },
{ "id":48,"latitude":"51.4945758","longitude":"4.2871622","type":"zebu","color":"yellow","client":"568PEPT604FRA0090","contact":"JULIEN","address":"NLD 46 BERGEN OP ZOOM","phone1":"05 61 37 39 07","phone2":"julien.breuilh@gefco.net","phone3":"<a href=mailto:julien.breuilh@gefco.net> Contactez-moi </a> ","last_purchase_date":"11/08/2017 15:00" },
{ "id":49,"latitude":"51.5332946","longitude":"4.2162383","type":"zebu","color":"green","client":"568PEPT604FRA0091","contact":"JULIEN","address":"NLD 46 THOLEN","phone1":"05 61 37 39 07","phone2":"julien.breuilh@gefco.net","phone3":"<a href=mailto:julien.breuilh@gefco.net> Contactez-moi </a> ","last_purchase_date":"15/08/2017 08:00" },
{ "id":50,"latitude":"51.5432946","longitude":"4.2262383","type":"zebu","color":"yellow","client":"568PEPT604FRA0119","contact":"JULIEN","address":"NLD 46 THOLEN","phone1":"05 61 37 39 07","phone2":"julien.breuilh@gefco.net","phone3":"<a href=mailto:julien.breuilh@gefco.net> Contactez-moi </a> ","last_purchase_date":"11/08/2017 08:00" },
{ "id":51,"latitude":"49.2175831","longitude":"5.6166101","type":"zebu","color":"yellow","client":"568PEPT604FRA0117","contact":"JULIEN","address":"FRA 55 ETAIN","phone1":"05 61 37 39 07","phone2":"julien.breuilh@gefco.net","phone3":"<a href=mailto:julien.breuilh@gefco.net> Contactez-moi </a> ","last_purchase_date":"11/08/2017 08:00" },
{ "id":52,"latitude":"45.980703","longitude":"3.088235","type":"zebu","color":"green","client":"568PEPT604FRA0092","contact":"JULIEN","address":"FRA 63 COMBRONDE","phone1":"05 61 37 39 07","phone2":"julien.breuilh@gefco.net","phone3":"<a href=mailto:julien.breuilh@gefco.net> Contactez-moi </a> ","last_purchase_date":"14/08/2017 09:00" },
{ "id":53,"latitude":"48.730702","longitude":"7.708784","type":"zebu","color":"yellow","client":"568PEPT604FRA0107","contact":"JULIEN","address":"FRA 67 BRUMATH","phone1":"05 61 37 39 07","phone2":"julien.breuilh@gefco.net","phone3":"<a href=mailto:julien.breuilh@gefco.net> Contactez-moi </a> ","last_purchase_date":"11/08/2017 08:00" },
{ "id":54,"latitude":"45.732041","longitude":"5.001291","type":"zebu","color":"yellow","client":"568PEPT604FRA0079","contact":"JULIEN","address":"FRA 69 GENAS","phone1":"05 61 37 39 07","phone2":"julien.breuilh@gefco.net","phone3":"<a href=mailto:julien.breuilh@gefco.net> Contactez-moi </a> ","last_purchase_date":"11/08/2017 08:00" },
{ "id":55,"latitude":"47.629788","longitude":"6.16428","type":"zebu","color":"yellow","client":"568PEPT604FRA0085","contact":"JULIEN","address":"FRA 70 VESOUL","phone1":"05 61 37 39 07","phone2":"julien.breuilh@gefco.net","phone3":"<a href=mailto:julien.breuilh@gefco.net> Contactez-moi </a> ","last_purchase_date":"10/08/2017 15:00" },
{ "id":56,"latitude":"47.639788","longitude":"6.17428","type":"zebu","color":"green","client":"568PEPT604FRA0123","contact":"JULIEN","address":"FRA 70 VESOUL","phone1":"05 61 37 39 07","phone2":"julien.breuilh@gefco.net","phone3":"<a href=mailto:julien.breuilh@gefco.net> Contactez-moi </a> ","last_purchase_date":"14/08/2017 08:00" },
{ "id":57,"latitude":"44.124633","longitude":"0.825347","type":"zebu","color":"yellow","client":"568PEPT604FRA0104","contact":"JULIEN","address":"FRA 82 LAMAGISTERE","phone1":"05 61 37 39 07","phone2":"julien.breuilh@gefco.net","phone3":"<a href=mailto:julien.breuilh@gefco.net> Contactez-moi </a> ","last_purchase_date":"10/08/2017 08:00" },
{ "id":58,"latitude":"51.3189468","longitude":"3.2068507","type":"zebu","color":"yellow","client":"568PEPT604FRA0108","contact":"JULIEN","address":"BEL 83 ZEEBRUGGE","phone1":"05 61 37 39 07","phone2":"julien.breuilh@gefco.net","phone3":"<a href=mailto:julien.breuilh@gefco.net> Contactez-moi </a> ","last_purchase_date":"11/08/2017 16:00" },
{ "id":59,"latitude":"44.383724","longitude":"4.989187","type":"zebu","color":"green","client":"568PEPT604FRA0103","contact":"JULIEN","address":"FRA 84 VALREAS","phone1":"05 61 37 39 07","phone2":"julien.breuilh@gefco.net","phone3":"<a href=mailto:julien.breuilh@gefco.net> Contactez-moi </a> ","last_purchase_date":"14/08/2017 08:00" },
{ "id":60,"latitude":"45.833619","longitude":"1.261105","type":"zebu","color":"green","client":"568PEPT604FRA0099","contact":"JULIEN","address":"FRA 87 LIMOGES","phone1":"05 61 37 39 07","phone2":"julien.breuilh@gefco.net","phone3":"<a href=mailto:julien.breuilh@gefco.net> Contactez-moi </a> ","last_purchase_date":"14/08/2017 08:00" },
{ "id":61,"latitude":"48.0793589","longitude":"7.358512","type":"semem","color":"green","client":"600GEREFRA0391","contact":"said","address":"FRA 68 COLMAR","phone1":"","phone2":"","phone3":"<a href=mailto:> Contactez-moi </a> ","last_purchase_date":"14/08/2017 11:45" },
{ "id":62,"latitude":"45.832913","longitude":"5.290324","type":"zebu","color":"yellow","client":"604GEREROM1894","contact":"STEVE","address":"FRA 01 ST VULBAS","phone1":"05 61 37 38 78","phone2":"steve.pavie@gefco.net","phone3":"<a href=mailto:steve.pavie@gefco.net> Contactez-moi </a> ","last_purchase_date":"11/08/2017 10:00" },
{ "id":63,"latitude":"46.673042","longitude":"2.908713","type":"zebu","color":"yellow","client":"604GEREROM1851","contact":"STEVE","address":"FRA 03 COULEUVRE","phone1":"05 61 37 38 78","phone2":"steve.pavie@gefco.net","phone3":"<a href=mailto:steve.pavie@gefco.net> Contactez-moi </a> ","last_purchase_date":"11/08/2017 08:00" },
{ "id":64,"latitude":"50.8719066","longitude":"4.2500012","type":"zebu","color":"yellow","client":"604GERELTU2018","contact":"STEVE","address":"BEL 17 GROOT BIJGAARDEN","phone1":"05 61 37 38 78","phone2":"steve.pavie@gefco.net","phone3":"<a href=mailto:steve.pavie@gefco.net> Contactez-moi </a> ","last_purchase_date":"11/08/2017 08:00" },
{ "id":65,"latitude":"51.05983","longitude":"4.36404","type":"zebu","color":"yellow","client":"604GERELTU1931","contact":"STEVE","address":"BEL 28 WILLEBROEK","phone1":"05 61 37 38 78","phone2":"steve.pavie@gefco.net","phone3":"<a href=mailto:steve.pavie@gefco.net> Contactez-moi </a> ","last_purchase_date":"11/08/2017 08:00" },
{ "id":66,"latitude":"45.693133","longitude":"5.130384","type":"zebu","color":"yellow","client":"604GEREROM1852","contact":"STEVE","address":"FRA 38 SATOLAS ET BONCE","phone1":"05 61 37 38 78","phone2":"steve.pavie@gefco.net","phone3":"<a href=mailto:steve.pavie@gefco.net> Contactez-moi </a> ","last_purchase_date":"11/08/2017 13:00" },
{ "id":67,"latitude":"45.486088","longitude":"4.5227119","type":"zebu","color":"green","client":"604GEREROM2130","contact":"STEVE","address":"FRA 42 ST CHAMOND","phone1":"05 61 37 38 78","phone2":"steve.pavie@gefco.net","phone3":"<a href=mailto:steve.pavie@gefco.net> Contactez-moi </a> ","last_purchase_date":"14/08/2017 08:00" },
{ "id":68,"latitude":"47.218371","longitude":"-1.553621","type":"zebu","color":"yellow","client":"604GEREROM1893","contact":"STEVE","address":"FRA 44 NANTES","phone1":"05 61 37 38 78","phone2":"steve.pavie@gefco.net","phone3":"<a href=mailto:steve.pavie@gefco.net> Contactez-moi </a> ","last_purchase_date":"11/08/2017 08:00" },
{ "id":69,"latitude":"50.8747592","longitude":"6.6883728","type":"zebu","color":"green","client":"604GEREROM2129","contact":"STEVE","address":"DEU 50 KERPEN","phone1":"05 61 37 38 78","phone2":"steve.pavie@gefco.net","phone3":"<a href=mailto:steve.pavie@gefco.net> Contactez-moi </a> ","last_purchase_date":"14/08/2017 08:00" },
{ "id":70,"latitude":"51.5852528","longitude":"5.056375","type":"zebu","color":"yellow","client":"604GEREROM1821","contact":"STEVE","address":"NLD 50 TILBURG","phone1":"05 61 37 38 78","phone2":"steve.pavie@gefco.net","phone3":"<a href=mailto:steve.pavie@gefco.net> Contactez-moi </a> ","last_purchase_date":"11/08/2017 08:00" },
{ "id":71,"latitude":"50.155935","longitude":"3.281083","type":"zebu","color":"green","client":"604GEREROM1829","contact":"STEVE","address":"FRA 59 AWOINGT","phone1":"05 61 37 38 78","phone2":"steve.pavie@gefco.net","phone3":"<a href=mailto:steve.pavie@gefco.net> Contactez-moi </a> ","last_purchase_date":"14/08/2017 07:00" },
{ "id":72,"latitude":"45.766821","longitude":"5.003658","type":"zebu","color":"red","client":"604GERELTU1930","contact":"STEVE","address":"FRA 69 MEYZIEU","phone1":"05 61 37 38 78","phone2":"steve.pavie@gefco.net","phone3":"<a href=mailto:steve.pavie@gefco.net> Contactez-moi </a> ","last_purchase_date":"09/08/2017 07:00" },
{ "id":73,"latitude":"49.495267","longitude":"0.360227","type":"zebu","color":"yellow","client":"604GEREROM1848","contact":"STEVE","address":"FRA 76 ST VIGOR D'YMONVILLE","phone1":"05 61 37 38 78","phone2":"steve.pavie@gefco.net","phone3":"<a href=mailto:steve.pavie@gefco.net> Contactez-moi </a> ","last_purchase_date":"11/08/2017 11:00" },
{ "id":74,"latitude":"51.099713","longitude":"3.7642304","type":"zebu","color":"yellow","client":"604GERELTU1834","contact":"STEVE","address":"BEL 90 OOSTAKKER","phone1":"05 61 37 38 78","phone2":"steve.pavie@gefco.net","phone3":"<a href=mailto:steve.pavie@gefco.net> Contactez-moi </a> ","last_purchase_date":"11/08/2017 08:00" },
{ "id":78,"latitude":"48.935525","longitude":"2.303275","type":"zebu","color":"yellow","client":"604GERELTU1807","contact":"STEVE","address":"FRA 92 GENNEVILLIERS","phone1":"05 61 37 38 78","phone2":"steve.pavie@gefco.net","phone3":"<a href=mailto:steve.pavie@gefco.net> Contactez-moi </a> ","last_purchase_date":"11/08/2017 08:00" },
{ "id":79,"latitude":"47.912722","longitude":"1.874149","type":"semem","color":"yellow","client":"600GEREFRA2111","contact":"VALERIE","address":"FRA 45 ST JEAN DE LA RUELLE","phone1":"02 99 05 85 75","phone2":"valerie.charrieau@gefco.net","phone3":"<a href=mailto:valerie.charrieau@gefco.net> Contactez-moi </a> ","last_purchase_date":"11/08/2017 00:01" },
{ "id":80,"latitude":"45.770455","longitude":"-1.140335","type":"zebu","color":"yellow","client":"604GERELTU1907","contact":"VINCENT","address":"FRA 17 LA TREMBLADE","phone1":"05 61 37 39 02","phone2":"vincent.lafay@gefco.net","phone3":"<a href=mailto:vincent.lafay@gefco.net> Contactez-moi </a> ","last_purchase_date":"11/08/2017 08:00" },
{ "id":81,"latitude":"50.8854878","longitude":"4.4709968","type":"zebu","color":"yellow","client":"604GERELTU1725","contact":"VINCENT","address":"BEL 19 ZAVENTEM","phone1":"05 61 37 39 02","phone2":"vincent.lafay@gefco.net","phone3":"<a href=mailto:vincent.lafay@gefco.net> Contactez-moi </a> ","last_purchase_date":"11/08/2017 10:00" },
{ "id":82,"latitude":"44.854003","longitude":"0.565493","type":"zebu","color":"green","client":"604GERELTU1896","contact":"VINCENT","address":"FRA 24 CREYSSE","phone1":"05 61 37 39 02","phone2":"vincent.lafay@gefco.net","phone3":"<a href=mailto:vincent.lafay@gefco.net> Contactez-moi </a> ","last_purchase_date":"14/08/2017 08:15" },
{ "id":83,"latitude":"51.1783102","longitude":"4.4042868","type":"zebu","color":"green","client":"604GERELTU1881","contact":"VINCENT","address":"BEL 26 WILRIJK","phone1":"05 61 37 39 02","phone2":"vincent.lafay@gefco.net","phone3":"<a href=mailto:vincent.lafay@gefco.net> Contactez-moi </a> ","last_purchase_date":"14/08/2017 08:00" },
{ "id":84,"latitude":"51.1883102","longitude":"4.4142868","type":"zebu","color":"yellow","client":"604GERELTU1904","contact":"VINCENT","address":"BEL 26 WILRIJK","phone1":"05 61 37 39 02","phone2":"vincent.lafay@gefco.net","phone3":"<a href=mailto:vincent.lafay@gefco.net> Contactez-moi </a> ","last_purchase_date":"11/08/2017 08:00" },
{ "id":85,"latitude":"51.1983102","longitude":"4.4242868","type":"zebu","color":"green","client":"604GERELTU1641","contact":"VINCENT","address":"BEL 26 WILRIJK","phone1":"05 61 37 39 02","phone2":"vincent.lafay@gefco.net","phone3":"<a href=mailto:vincent.lafay@gefco.net> Contactez-moi </a> ","last_purchase_date":"14/08/2017 08:00" },
{ "id":86,"latitude":"44.873167","longitude":"-0.677914","type":"zebu","color":"yellow","client":"604GERELTU1902","contact":"VINCENT","address":"FRA 33 LE HAILLAN","phone1":"05 61 37 39 02","phone2":"vincent.lafay@gefco.net","phone3":"<a href=mailto:vincent.lafay@gefco.net> Contactez-moi </a> ","last_purchase_date":"11/08/2017 08:00" },
{ "id":87,"latitude":"50.232222","longitude":"7.139444","type":"zebu","color":"green","client":"604GERELTU1658","contact":"VINCENT","address":"DEU 56 KAISERSESCH","phone1":"05 61 37 39 02","phone2":"vincent.lafay@gefco.net","phone3":"<a href=mailto:vincent.lafay@gefco.net> Contactez-moi </a> ","last_purchase_date":"14/08/2017 06:00" },
{ "id":94,"latitude":"47.649788","longitude":"6.18428","type":"zebu","color":"green","client":"604GERELTU1642","contact":"VINCENT","address":"FRA 70 VESOUL","phone1":"05 61 37 39 02","phone2":"vincent.lafay@gefco.net","phone3":"<a href=mailto:vincent.lafay@gefco.net> Contactez-moi </a> ","last_purchase_date":"15/08/2017 08:00" },
{ "id":95,"latitude":"52.5167747","longitude":"6.0830219","type":"zebu","color":"green","client":"604GERELTU1751","contact":"VINCENT","address":"NLD 80 ZWOLLE","phone1":"05 61 37 39 02","phone2":"vincent.lafay@gefco.net","phone3":"<a href=mailto:vincent.lafay@gefco.net> Contactez-moi </a> ","last_purchase_date":"14/08/2017 08:00" },
{ "id":96,"latitude":"51.025477","longitude":"4.1019516","type":"zebu","color":"yellow","client":"604GERELTU1906","contact":"VINCENT","address":"BEL 92 DENDERMONDE","phone1":"05 61 37 39 02","phone2":"vincent.lafay@gefco.net","phone3":"<a href=mailto:vincent.lafay@gefco.net> Contactez-moi </a> ","last_purchase_date":"11/08/2017 08:00" },
{"id":97,"latitude":"48.858053","longitude":"2.294289","type":"zebu","color":"blue","client":"LA TOUR EIFFEL","contact":"Gustave eiffel","address":"FRA 75 PARIS","phone1":"05 61 37 39 02","phone2":"vincent.lafay@gefco.net","phone3":"<a href=mailto:vincent.lafay@gefco.net> Contactez-moi </a> ","last_purchase_date":" mars 1889, pour l'Exposition universelle" }]
