[
{ "Cellule":600"Moyen":600GEREFRA1309"Gestionnaire":ALAIN"Transporteur":LECORNU TRANSPORTS SARL"Origine":FRA"Point de chutte":53 LASSAY LES CHATEAUX"Tracteur":CF 387 YR"Remorque":AZ 747 KZ"Type":TAUT"Hauteur":2.8"Longueur":13.6"Charge":28.45"PTRE Tracteur":40"PTAC Remorque":34"ADR":false"Norme Euro":EURO5"Nb sangles":18"Nb equerres":10"Nb planches":16"Cordon TIR":true"Tapis":true"Hayon":false"Porte palettes":false"Baches armees":true"Norme XL":false"Porte bobine":false"EPI":true"Attestation dechets":true"Commentaires":false
{ "Cellule":600"Moyen":600GEREFRA2014"Gestionnaire":CHRISTEL"Transporteur":DETRAZ FILLOUX TDF"Origine":FRA"Point de chutte":01 TOSSIAT"Tracteur":EA 249 DY"Remorque":EP 796 ZB"Type":TAUT"Hauteur":2.78"Longueur":13.6"Charge":29"PTRE Tracteur":44"PTAC Remorque":38"ADR":true"Norme Euro":EURO 6"Nb sangles":20"Nb equerres":20"Nb planches":34"Cordon TIR":true"Tapis":true"Hayon":false"Porte palettes":false"Baches armees":true"Norme XL":true"Porte bobine":false"EPI":true"Attestation dechets":true"Commentaires":false
{ "Cellule":600"Moyen":600GEREFRA1973"Gestionnaire":GHISLAIN"Transporteur":JEAN BOURGET"Origine":FRA"Point de chutte":38 BEAUREPAIRE"Tracteur":EC-123-SF"Remorque":EC-760-AE"Type":TAUT"Hauteur":2.85"Longueur":13.6"Charge":29"PTRE Tracteur":44"PTAC Remorque":34"ADR":false"Norme Euro":EURO 6"Nb sangles":14"Nb equerres":24"Nb planches":24"Cordon TIR":true"Tapis":false"Hayon":false"Porte palettes":false"Baches armees":true"Norme XL":true"Porte bobine":false"EPI":true"Attestation dechets":true"Commentaires":false
{ "Cellule":600"Moyen":600GEREFRA0819"Gestionnaire":VALERIE"Transporteur":ROUSSILLONAISE"Origine":FRA"Point de chutte":66"Tracteur":AY 393 EW"Remorque":CN 873 EN"Type":TAUT"Hauteur":2.7"Longueur":13.6"Charge":27.5"PTRE Tracteur":44"PTAC Remorque":34"ADR":true"Norme Euro":EURO4"Nb sangles":14"Nb equerres":10"Nb planches":12"Cordon TIR":true"Tapis":true"Hayon":false"Porte palettes":true"Baches armees":false"Norme XL":false"Porte bobine":true"EPI":true"Attestation dechets":true"Commentaires":false
{ "Cellule":600"Moyen":600GEREFRA2016"Gestionnaire":ALAIN"Transporteur":NYD MAMOUR"Origine":FRA"Point de chutte":02 CHAUNY"Tracteur":DS 610 PS"Remorque":DN 248 XJ"Type":TAUT"Hauteur":2.7"Longueur":13.6"Charge":25"PTRE Tracteur":44"PTAC Remorque":42"ADR":false"Norme Euro":EURO6"Nb sangles":12"Nb equerres":20"Nb planches":32"Cordon TIR":true"Tapis":true"Hayon":false"Porte palettes":false"Baches armees":true"Norme XL":false"Porte bobine":false"EPI":true"Attestation dechets":false"Commentaires":false
{ "Cellule":600"Moyen":600GEREFRA0113"Gestionnaire":ALAIN"Transporteur":CHABRIER"Origine":FRA"Point de chutte":ENNEZAT 63"Tracteur":DR 635 CS"Remorque":DV 602 EB"Type":TAUT"Hauteur":2.7"Longueur":13.6"Charge":29"PTRE Tracteur":44"PTAC Remorque":42"ADR":false"Norme Euro":EURO5"Nb sangles":12"Nb equerres":10"Nb planches":24"Cordon TIR":true"Tapis":false"Hayon":false"Porte palettes":false"Baches armees":false"Norme XL":true"Porte bobine":false"EPI":false"Attestation dechets":false"Commentaires":false
{ "Cellule":600"Moyen":600GEREFRA0397"Gestionnaire":ISABELLE"Transporteur":GAUTHIER"Origine":FRA"Point de chutte":HAMARS 14"Tracteur":CV438WV"Remorque":CS093FZ"Type":TAUT"Hauteur":2.75"Longueur":13.6"Charge":28500"PTRE Tracteur":44"PTAC Remorque":38"ADR":false"Norme Euro":EURO 6"Nb sangles":15"Nb equerres":14"Nb planches":24"Cordon TIR":true"Tapis":false"Hayon":false"Porte palettes":true"Baches armees":true"Norme XL":true"Porte bobine":false"EPI":true"Attestation dechets":true"Commentaires":false
{ "Cellule":600"Moyen":600GEREFRA0583"Gestionnaire":VALERIE"Transporteur":LEROY"Origine":FRA"Point de chutte":SALLAUMINES 62"Tracteur":AP 546 TP"Remorque":CJ 498 GK"Type":TAUT"Hauteur":2.7"Longueur":13.6"Charge":28"PTRE Tracteur":44"PTAC Remorque":44"ADR":false"Norme Euro":EURO 5"Nb sangles":18"Nb equerres":22"Nb planches":24"Cordon TIR":true"Tapis":false"Hayon":false"Porte palettes":false"Baches armees":true"Norme XL":false"Porte bobine":false"EPI":true"Attestation dechets":true"Commentaires":false
{ "Cellule":600"Moyen":600GEREFRA1555"Gestionnaire":ALAIN"Transporteur":NYD MAMOUR"Origine":FRA"Point de chutte":27 EVREUX"Tracteur":DS 009 ZE"Remorque":DR 542 RE"Type":TAUT"Hauteur":2.73"Longueur":13.6"Charge":29"PTRE Tracteur":44"PTAC Remorque":38"ADR":false"Norme Euro":EURO6"Nb sangles":12"Nb equerres":24"Nb planches":24"Cordon TIR":true"Tapis":true"Hayon":false"Porte palettes":false"Baches armees":true"Norme XL":true"Porte bobine":false"EPI":true"Attestation dechets":true"Commentaires":false
{ "Cellule":600"Moyen":600GEREFRA1694"Gestionnaire":VALERIE"Transporteur":LEROY"Origine":FRA"Point de chutte":BETHUNE 62"Tracteur":CT 937 RL"Remorque":CS 175 VS"Type":TAUT"Hauteur":2.7"Longueur":13.6"Charge":29"PTRE Tracteur":44"PTAC Remorque":44"ADR":false"Norme Euro":EURO5"Nb sangles":15"Nb equerres":24"Nb planches":24"Cordon TIR":true"Tapis":true"Hayon":false"Porte palettes":false"Baches armees":false"Norme XL":true"Porte bobine":false"EPI":true"Attestation dechets":true"Commentaires":false
{ "Cellule":600"Moyen":600GEREFRA1708"Gestionnaire":ISABELLE"Transporteur":GAUTHIER"Origine":FRA"Point de chutte":CRAON 53"Tracteur":CS640HB"Remorque":EG 804 DK"Type":TAUT"Hauteur":2.82"Longueur":13.6"Charge":28500"PTRE Tracteur":44"PTAC Remorque":38"ADR":true"Norme Euro":EURO 4"Nb sangles":12"Nb equerres":12"Nb planches":24"Cordon TIR":true"Tapis":false"Hayon":false"Porte palettes":false"Baches armees":false"Norme XL":false"Porte bobine":false"EPI":true"Attestation dechets":true"Commentaires":false
{ "Cellule":600"Moyen":600GEREFRA1757"Gestionnaire":ISABELLE"Transporteur":GAUTHIER"Origine":FRA"Point de chutte":CRAON 53"Tracteur":DX 550 YB"Remorque":DE 444 PG"Type":TAUT"Hauteur":2.75"Longueur":13.6"Charge":28500"PTRE Tracteur":44"PTAC Remorque":38"ADR":true"Norme Euro":EURO5"Nb sangles":15"Nb equerres":23"Nb planches":24"Cordon TIR":true"Tapis":false"Hayon":false"Porte palettes":false"Baches armees":true"Norme XL":false"Porte bobine":false"EPI":true"Attestation dechets":true"Commentaires":false
{ "Cellule":600"Moyen":600GEREFRA1792"Gestionnaire":CHRISTEL"Transporteur":GALODE PASCAL"Origine":FRA"Point de chutte":35 VITRE"Tracteur":CN 881 BN"Remorque":CL 044 TS"Type":TAUT"Hauteur":3.04"Longueur":13.6"Charge":28"PTRE Tracteur":44"PTAC Remorque":38"ADR":false"Norme Euro":EURO5"Nb sangles":15"Nb equerres":13"Nb planches":16"Cordon TIR":true"Tapis":false"Hayon":false"Porte palettes":false"Baches armees":false"Norme XL":true"Porte bobine":false"EPI":true"Attestation dechets":false"Commentaires":false
{ "Cellule":600"Moyen":600GEREFRA1854"Gestionnaire":GHISLAIN"Transporteur":CHRONOROUTE"Origine":FRA"Point de chutte":52 LANGRES"Tracteur":EF556ZV"Remorque":CC940WE"Type":TAUT"Hauteur":2.83"Longueur":13.4"Charge":28"PTRE Tracteur":44"PTAC Remorque":38"ADR":false"Norme Euro":EURO5"Nb sangles":16"Nb equerres":8"Nb planches":16"Cordon TIR":true"Tapis":false"Hayon":false"Porte palettes":false"Baches armees":true"Norme XL":false"Porte bobine":false"EPI":true"Attestation dechets":true"Commentaires":false
{ "Cellule":600"Moyen":600GEREFRA2015"Gestionnaire":VALERIE"Transporteur":Transports PIALLA  S.A.S"Origine":FRA"Point de chutte":26 PIERRELATTE"Tracteur":BK 126 KN"Remorque":BC 448 TL"Type":TAUT"Hauteur":2.7"Longueur":13.5"Charge":28"PTRE Tracteur":7.5"PTAC Remorque":6.95"ADR":false"Norme Euro":EURO5"Nb sangles":14"Nb equerres":10"Nb planches":8"Cordon TIR":true"Tapis":true"Hayon":false"Porte palettes":false"Baches armees":false"Norme XL":true"Porte bobine":false"EPI":true"Attestation dechets":true"Commentaires":false
{ "Cellule":600"Moyen":600GEREFRA1405"Gestionnaire":CHRISTEL"Transporteur":GRASA"Origine":FRA"Point de chutte":47"Tracteur":DD015CE"Remorque":CQ486AD"Type":TAUT"Hauteur":2.7"Longueur":13.6"Charge":28"PTRE Tracteur":44"PTAC Remorque":34"ADR":false"Norme Euro":EURO5"Nb sangles":9"Nb equerres":20"Nb planches":24"Cordon TIR":true"Tapis":false"Hayon":false"Porte palettes":false"Baches armees":false"Norme XL":false"Porte bobine":false"EPI":true"Attestation dechets":false"Commentaires":false
{ "Cellule":600"Moyen":600GEREFRA0129"Gestionnaire":ALAIN"Transporteur":BRES"Origine":FRA"Point de chutte":26 MONTELIMAR"Tracteur":DK 794 CW"Remorque":BG 567 RZ"Type":TAUT"Hauteur":2.68"Longueur":13.4"Charge":28.5"PTRE Tracteur":0"PTAC Remorque":0"ADR":true"Norme Euro":EURO6"Nb sangles":14"Nb equerres":26"Nb planches":0"Cordon TIR":true"Tapis":true"Hayon":false"Porte palettes":false"Baches armees":false"Norme XL":false"Porte bobine":false"EPI":true"Attestation dechets":true"Commentaires":false
{ "Cellule":600"Moyen":600GEREFRA0283"Gestionnaire":ALAIN"Transporteur":LEVEQUE"Origine":FRA"Point de chutte":18 VIERZON"Tracteur":DW 189 KM"Remorque":BH 683 JP"Type":TAUT"Hauteur":2.85"Longueur":13.8"Charge":28"PTRE Tracteur":44"PTAC Remorque":44"ADR":false"Norme Euro":EURO6"Nb sangles":17"Nb equerres":24"Nb planches":24"Cordon TIR":true"Tapis":false"Hayon":false"Porte palettes":true"Baches armees":false"Norme XL":true"Porte bobine":false"EPI":true"Attestation dechets":true"Commentaires":false
{ "Cellule":600"Moyen":600GEREFRA1044"Gestionnaire":VALERIE"Transporteur":ROUSSILLONAISE"Origine":FRA"Point de chutte":66"Tracteur":AY 897 ET"Remorque":CW 214 KE"Type":TAUT"Hauteur":2.6"Longueur":13.6"Charge":28"PTRE Tracteur":44"PTAC Remorque":34"ADR":false"Norme Euro":EURO4"Nb sangles":14"Nb equerres":10"Nb planches":12"Cordon TIR":true"Tapis":false"Hayon":false"Porte palettes":false"Baches armees":false"Norme XL":false"Porte bobine":false"EPI":true"Attestation dechets":true"Commentaires":false
{ "Cellule":600"Moyen":600GEREFRA0343"Gestionnaire":ALAIN"Transporteur":CHABRIER"Origine":FRA"Point de chutte":ENNEZAT 63"Tracteur":EG 950 NH"Remorque":BN 679 EQ"Type":TAUT"Hauteur":2.7"Longueur":13.7"Charge":29"PTRE Tracteur":44"PTAC Remorque":44"ADR":false"Norme Euro":EURO4"Nb sangles":16"Nb equerres":16"Nb planches":24"Cordon TIR":true"Tapis":false"Hayon":false"Porte palettes":false"Baches armees":true"Norme XL":true"Porte bobine":false"EPI":true"Attestation dechets":false"Commentaires":false
{ "Cellule":600"Moyen":600GEREFRA0940"Gestionnaire":VALERIE"Transporteur":T M F"Origine":FRA"Point de chutte":36 BAZAIGES"Tracteur":BH 238 RC"Remorque":BJ 422 KJ"Type":TAUT"Hauteur":2.7"Longueur":13.6"Charge":28"PTRE Tracteur":44"PTAC Remorque":38"ADR":false"Norme Euro":EURO5"Nb sangles":13"Nb equerres":15"Nb planches":14"Cordon TIR":true"Tapis":false"Hayon":false"Porte palettes":false"Baches armees":false"Norme XL":false"Porte bobine":false"EPI":true"Attestation dechets":true"Commentaires":false
{ "Cellule":600"Moyen":600GEREFRA2020"Gestionnaire":GHISLAIN"Transporteur":EURO FRET EXPRESS"Origine":FRA"Point de chutte":78 POISSY"Tracteur":EM 905 GE"Remorque":CW 955 GB"Type":TAUT"Hauteur":2.7"Longueur":13.6"Charge":27"PTRE Tracteur":8.29"PTAC Remorque":6.3"ADR":false"Norme Euro":EURO6"Nb sangles":15"Nb equerres":24"Nb planches":24"Cordon TIR":true"Tapis":false"Hayon":false"Porte palettes":false"Baches armees":true"Norme XL":true"Porte bobine":false"EPI":true"Attestation dechets":false"Commentaires":false
{ "Cellule":600"Moyen":600GEREFRA1160"Gestionnaire":ISABELLE"Transporteur":MOISSON"Origine":FRA"Point de chutte":51 ISLES SUR SUIPPE"Tracteur":DJ 503 GR"Remorque":BN 315 YG"Type":SAVOYARDE"Hauteur":2.7"Longueur":13.6"Charge":28"PTRE Tracteur":44"PTAC Remorque":38"ADR":false"Norme Euro":EURO6"Nb sangles":15"Nb equerres":20"Nb planches":15"Cordon TIR":true"Tapis":true"Hayon":false"Porte palettes":false"Baches armees":true"Norme XL":false"Porte bobine":false"EPI":true"Attestation dechets":false"Commentaires":false
{ "Cellule":600"Moyen":600GEREFRA1960"Gestionnaire":CHRISTEL"Transporteur":SARL TRANSPORTS PASTEUR"Origine":FRA"Point de chutte":70 MARNAY"Tracteur":DK 343 WB"Remorque":CR 091 LA"Type":TAUT"Hauteur":2.7"Longueur":13.4"Charge":29"PTRE Tracteur":44"PTAC Remorque":38"ADR":true"Norme Euro":EURO5"Nb sangles":10"Nb equerres":25"Nb planches":24"Cordon TIR":true"Tapis":false"Hayon":false"Porte palettes":false"Baches armees":true"Norme XL":false"Porte bobine":false"EPI":true"Attestation dechets":false"Commentaires":false
{ "Cellule":600"Moyen":600GEREFRA1439"Gestionnaire":CHRISTEL"Transporteur":WALZER LOUIS"Origine":FRA"Point de chutte":68 SOPPE LE HAUT"Tracteur":BE 631 YR"Remorque":DM 389 FS"Type":TAUT"Hauteur":2.68"Longueur":13.5"Charge":29"PTRE Tracteur":0"PTAC Remorque":0"ADR":false"Norme Euro":EURO5"Nb sangles":14"Nb equerres":26"Nb planches":24"Cordon TIR":true"Tapis":true"Hayon":false"Porte palettes":false"Baches armees":false"Norme XL":false"Porte bobine":false"EPI":true"Attestation dechets":true"Commentaires":false
{ "Cellule":600"Moyen":600GEREFRA0461"Gestionnaire":ISABELLE"Transporteur":LELORRAIN"Origine":FRA"Point de chutte":88 VAUDONCOURT"Tracteur":DH 460 MS"Remorque":CZ 512 DC"Type":TAUT"Hauteur":2.8"Longueur":13.6"Charge":29"PTRE Tracteur":44"PTAC Remorque":44"ADR":false"Norme Euro":EURO6"Nb sangles":16"Nb equerres":24"Nb planches":32"Cordon TIR":true"Tapis":true"Hayon":false"Porte palettes":false"Baches armees":true"Norme XL":false"Porte bobine":false"EPI":true"Attestation dechets":true"Commentaires":false
{ "Cellule":600"Moyen":600GEREFRA1159"Gestionnaire":ISABELLE"Transporteur":MOISSON"Origine":FRA"Point de chutte":51 ISLES SUR SUIPPE"Tracteur":DW 410 ET"Remorque":BN 728 YH"Type":SAVOYARDE"Hauteur":2.7"Longueur":13.6"Charge":28.7"PTRE Tracteur":44"PTAC Remorque":44"ADR":false"Norme Euro":EURO4"Nb sangles":13"Nb equerres":22"Nb planches":24"Cordon TIR":true"Tapis":false"Hayon":false"Porte palettes":false"Baches armees":false"Norme XL":false"Porte bobine":false"EPI":true"Attestation dechets":false"Commentaires":false
{ "Cellule":600"Moyen":600GEREFRA1541"Gestionnaire":CHRISTEL"Transporteur":MARTIN ET FILS"Origine":FRA"Point de chutte":70 GEVIGNEY-MERCEY"Tracteur":DQ 668 JS"Remorque":CK 215 QC"Type":TAUT"Hauteur":2.7"Longueur":13.5"Charge":29"PTRE Tracteur":44"PTAC Remorque":44"ADR":false"Norme Euro":EURO6"Nb sangles":12"Nb equerres":24"Nb planches":24"Cordon TIR":true"Tapis":true"Hayon":false"Porte palettes":false"Baches armees":false"Norme XL":false"Porte bobine":false"EPI":true"Attestation dechets":true"Commentaires":false
{ "Cellule":600"Moyen":600GEREFRA1690"Gestionnaire":ALAIN"Transporteur":LORIOT MICHEL"Origine":FRA"Point de chutte":70 VESOUL"Tracteur":AV 493 RL"Remorque":BQ 131 CN"Type":TAUT"Hauteur":2.7"Longueur":13.6"Charge":29"PTRE Tracteur":44"PTAC Remorque":44"ADR":false"Norme Euro":EURO5"Nb sangles":20"Nb equerres":26"Nb planches":24"Cordon TIR":true"Tapis":true"Hayon":false"Porte palettes":false"Baches armees":true"Norme XL":false"Porte bobine":false"EPI":true"Attestation dechets":false"Commentaires":false
{ "Cellule":600"Moyen":600GEREFRA1865"Gestionnaire":VALERIE"Transporteur":ROUX-VOISARD"Origine":FRA"Point de chutte":25 EXINCOURT"Tracteur":DS 978 EA"Remorque":BX 983 HZ"Type":TAUT"Hauteur":2.69"Longueur":13.6"Charge":29"PTRE Tracteur":44"PTAC Remorque":0"ADR":false"Norme Euro":EURO6"Nb sangles":22"Nb equerres":26"Nb planches":29"Cordon TIR":true"Tapis":true"Hayon":false"Porte palettes":false"Baches armees":false"Norme XL":true"Porte bobine":false"EPI":true"Attestation dechets":true"Commentaires":false
{ "Cellule":600"Moyen":600GEREFRA0903"Gestionnaire":VALERIE"Transporteur":T M F"Origine":FRA"Point de chutte":36 BAZAIGES"Tracteur":DT 668 MW"Remorque":AX 804 SF"Type":TAUT"Hauteur":2.7"Longueur":13.6"Charge":28"PTRE Tracteur":44"PTAC Remorque":38"ADR":false"Norme Euro":EURO5"Nb sangles":0"Nb equerres":15"Nb planches":24"Cordon TIR":true"Tapis":false"Hayon":false"Porte palettes":false"Baches armees":false"Norme XL":false"Porte bobine":false"EPI":true"Attestation dechets":true"Commentaires":false
{ "Cellule":600"Moyen":600GEREFRA0401"Gestionnaire":GHISLAIN"Transporteur":BATTELIER"Origine":FRA"Point de chutte":10 POUAN LES VALLEES"Tracteur":BF 658 RB"Remorque":EA 585 XR"Type":TAUT"Hauteur":2.7"Longueur":13.4"Charge":29"PTRE Tracteur":44"PTAC Remorque":38"ADR":false"Norme Euro":EURO5"Nb sangles":13"Nb equerres":4"Nb planches":24"Cordon TIR":true"Tapis":false"Hayon":false"Porte palettes":false"Baches armees":false"Norme XL":false"Porte bobine":false"EPI":true"Attestation dechets":true"Commentaires":false
{ "Cellule":600"Moyen":600GEREFRA0986"Gestionnaire":GHISLAIN"Transporteur":LEVERT"Origine":FRA"Point de chutte":MESSEI 61"Tracteur":AV 915 FW"Remorque":CE 375 BK"Type":TAUT"Hauteur":2.7"Longueur":13.6"Charge":28"PTRE Tracteur":44"PTAC Remorque":44"ADR":false"Norme Euro":EURO5"Nb sangles":15"Nb equerres":20"Nb planches":32"Cordon TIR":true"Tapis":true"Hayon":false"Porte palettes":false"Baches armees":true"Norme XL":false"Porte bobine":false"EPI":true"Attestation dechets":true"Commentaires":false
{ "Cellule":600"Moyen":600GEREFRA1702"Gestionnaire":GHISLAIN"Transporteur":CHRONOROUTE"Origine":FRA"Point de chutte":35 CREVIN"Tracteur":EG 174 AW"Remorque":CS 068 VF"Type":TAUT"Hauteur":2.85"Longueur":13.4"Charge":28.24"PTRE Tracteur":44"PTAC Remorque":44"ADR":false"Norme Euro":EURO6"Nb sangles":16"Nb equerres":20"Nb planches":24"Cordon TIR":true"Tapis":true"Hayon":true"Porte palettes":false"Baches armees":true"Norme XL":true"Porte bobine":false"EPI":true"Attestation dechets":true"Commentaires":false
{ "Cellule":600"Moyen":600GEREFRA1855"Gestionnaire":ALAIN"Transporteur":CHABRIER"Origine":FRA"Point de chutte":ENNEZAT 63"Tracteur":EJ 605 BT"Remorque":DN 497 RE"Type":TAUT"Hauteur":2.7"Longueur":13.6"Charge":28.8"PTRE Tracteur":44"PTAC Remorque":38"ADR":false"Norme Euro":EURO5"Nb sangles":15"Nb equerres":14"Nb planches":24"Cordon TIR":true"Tapis":true"Hayon":false"Porte palettes":false"Baches armees":false"Norme XL":true"Porte bobine":false"EPI":true"Attestation dechets":true"Commentaires":false
{ "Cellule":600"Moyen":600GEREFRA1771"Gestionnaire":ALAIN"Transporteur":CHABRIER"Origine":FRA"Point de chutte":63 ENNEZAT"Tracteur":CT 845 TL"Remorque":AX 903 BM"Type":TAUT"Hauteur":2.65"Longueur":13.6"Charge":28"PTRE Tracteur":44"PTAC Remorque":38"ADR":false"Norme Euro":EURO6"Nb sangles":10"Nb equerres":10"Nb planches":24"Cordon TIR":true"Tapis":false"Hayon":false"Porte palettes":false"Baches armees":true"Norme XL":false"Porte bobine":false"EPI":true"Attestation dechets":false"Commentaires":false
{ "Cellule":600"Moyen":600GEREFRA1952"Gestionnaire":VALERIE"Transporteur":LEROY"Origine":FRA"Point de chutte":62 VIMY"Tracteur":DR 880 LY"Remorque":BV 506 EY"Type":TAUT"Hauteur":2.7"Longueur":13.6"Charge":28"PTRE Tracteur":8.068"PTAC Remorque":7.4"ADR":false"Norme Euro":EURO5"Nb sangles":15"Nb equerres":28"Nb planches":24"Cordon TIR":true"Tapis":true"Hayon":false"Porte palettes":false"Baches armees":true"Norme XL":false"Porte bobine":false"EPI":true"Attestation dechets":true"Commentaires":false
{ "Cellule":600"Moyen":600GEREFRA0028"Gestionnaire":ALAIN"Transporteur":BRES"Origine":FRA"Point de chutte":26 MONTELIMAR"Tracteur":DK 887 CW"Remorque":AD 047 GV"Type":TAUT"Hauteur":2.7"Longueur":13.4"Charge":28.8"PTRE Tracteur":0"PTAC Remorque":0"ADR":true"Norme Euro":EURO6"Nb sangles":14"Nb equerres":26"Nb planches":24"Cordon TIR":true"Tapis":true"Hayon":false"Porte palettes":false"Baches armees":true"Norme XL":false"Porte bobine":false"EPI":true"Attestation dechets":true"Commentaires":false
{ "Cellule":600"Moyen":600GEREFRA1043"Gestionnaire":VALERIE"Transporteur":ROUSSILLONAISE"Origine":FRA"Point de chutte":66"Tracteur":EJ 369 EZ"Remorque":CX594MY"Type":TAUT"Hauteur":2.7"Longueur":13.6"Charge":28"PTRE Tracteur":44"PTAC Remorque":38"ADR":false"Norme Euro":EURO4"Nb sangles":14"Nb equerres":10"Nb planches":12"Cordon TIR":true"Tapis":false"Hayon":false"Porte palettes":false"Baches armees":false"Norme XL":false"Porte bobine":false"EPI":true"Attestation dechets":true"Commentaires":false
{ "Cellule":600"Moyen":600GEREFRA1724"Gestionnaire":CHRISTEL"Transporteur":MARTIN ET FILS"Origine":FRA"Point de chutte":70 GEVIGNEY-MERCEY"Tracteur":CN 380 DN"Remorque":BA 993 CT"Type":TAUT"Hauteur":2.7"Longueur":13.5"Charge":29"PTRE Tracteur":44"PTAC Remorque":44"ADR":false"Norme Euro":EURO5"Nb sangles":12"Nb equerres":24"Nb planches":32"Cordon TIR":true"Tapis":false"Hayon":false"Porte palettes":false"Baches armees":false"Norme XL":false"Porte bobine":false"EPI":true"Attestation dechets":true"Commentaires":false
{ "Cellule":600"Moyen":600GEREFRA1890"Gestionnaire":ISABELLE"Transporteur":MOISSON"Origine":FRA"Point de chutte":51 ISLES SUR SUIPPE"Tracteur":AX 739 DC"Remorque":BN 086 YH"Type":TAUT"Hauteur":2.7"Longueur":13.6"Charge":28"PTRE Tracteur":0"PTAC Remorque":0"ADR":false"Norme Euro":EURO6"Nb sangles":15"Nb equerres":30"Nb planches":24"Cordon TIR":true"Tapis":true"Hayon":false"Porte palettes":false"Baches armees":false"Norme XL":false"Porte bobine":false"EPI":true"Attestation dechets":false"Commentaires":false
{ "Cellule":600"Moyen":600GEREFRA1170"Gestionnaire":ALAIN"Transporteur":SAS TRANSPORTS ET AUTOCARS VINCENDO"Origine":FRA"Point de chutte":88 SAULXURES SUR MOSELOTTE"Tracteur":BY 236 CC"Remorque":CR-929-VR"Type":TAUT"Hauteur":2.68"Longueur":13.5"Charge":29"PTRE Tracteur":0"PTAC Remorque":0"ADR":false"Norme Euro":EURO4"Nb sangles":18"Nb equerres":0"Nb planches":0"Cordon TIR":true"Tapis":true"Hayon":false"Porte palettes":false"Baches armees":false"Norme XL":false"Porte bobine":false"EPI":true"Attestation dechets":false"Commentaires":false
{ "Cellule":600"Moyen":600GEREFRA1062"Gestionnaire":ISABELLE"Transporteur":MOISSON"Origine":FRA"Point de chutte":51 ISLES SUR SUIPPE"Tracteur":CA 657 QM"Remorque":DP 399 YY"Type":SAVOYARDE"Hauteur":2.7"Longueur":13.6"Charge":29"PTRE Tracteur":44"PTAC Remorque":44"ADR":false"Norme Euro":EURO5"Nb sangles":15"Nb equerres":30"Nb planches":24"Cordon TIR":true"Tapis":false"Hayon":false"Porte palettes":false"Baches armees":true"Norme XL":false"Porte bobine":false"EPI":true"Attestation dechets":false"Commentaires":false
{ "Cellule":600"Moyen":600GEREFRA1563"Gestionnaire":VALERIE"Transporteur":ROUX-VOISARD"Origine":FRA"Point de chutte":25 EXINCOURT"Tracteur":EB 017 TE"Remorque":CH 975 YT"Type":TAUT"Hauteur":2.65"Longueur":13.5"Charge":28.2"PTRE Tracteur":44"PTAC Remorque":38"ADR":false"Norme Euro":EURO6"Nb sangles":14"Nb equerres":30"Nb planches":40"Cordon TIR":false"Tapis":true"Hayon":false"Porte palettes":false"Baches armees":false"Norme XL":true"Porte bobine":false"EPI":true"Attestation dechets":true"Commentaires":false
{ "Cellule":600"Moyen":600GEREFRA2011"Gestionnaire":CHRISTEL"Transporteur":SARL TRANSPORTS PASTEUR"Origine":FRA"Point de chutte":70 VESOUL"Tracteur":EM 697 SP"Remorque":EC 642 QD"Type":TAUT"Hauteur":2.7"Longueur":0"Charge":0"PTRE Tracteur":0"PTAC Remorque":19"ADR":false"Norme Euro":EURO 5"Nb sangles":12"Nb equerres":24"Nb planches":0"Cordon TIR":true"Tapis":true"Hayon":false"Porte palettes":false"Baches armees":false"Norme XL":true"Porte bobine":false"EPI":true"Attestation dechets":false"Commentaires":false
{ "Cellule":600"Moyen":600GEREFRA1022"Gestionnaire":ISABELLE"Transporteur":T D E"Origine":FRA"Point de chutte":35 BRUZ"Tracteur":DN 986 LR"Remorque":BL 077 WG"Type":TAUT"Hauteur":2.8"Longueur":13.5"Charge":25"PTRE Tracteur":40"PTAC Remorque":34"ADR":false"Norme Euro":EURO5"Nb sangles":14"Nb equerres":18"Nb planches":24"Cordon TIR":true"Tapis":false"Hayon":false"Porte palettes":false"Baches armees":false"Norme XL":true"Porte bobine":false"EPI":true"Attestation dechets":true"Commentaires":false
{ "Cellule":600"Moyen":600GEREFRA0271"Gestionnaire":VALERIE"Transporteur":T M F"Origine":FRA"Point de chutte":36 BAZAIGES"Tracteur":EC 087 SG"Remorque":EC 987 TE"Type":TAUT"Hauteur":2.7"Longueur":13.6"Charge":28"PTRE Tracteur":44"PTAC Remorque":38"ADR":false"Norme Euro":EURO6"Nb sangles":15"Nb equerres":30"Nb planches":24"Cordon TIR":true"Tapis":true"Hayon":false"Porte palettes":false"Baches armees":false"Norme XL":true"Porte bobine":false"EPI":true"Attestation dechets":true"Commentaires":false
{ "Cellule":600"Moyen":600GEREFRA1632"Gestionnaire":GHISLAIN"Transporteur":BATTELIER"Origine":FRA"Point de chutte":10 POUAN LES VALLEES"Tracteur":CS 327 EZ"Remorque":DN 194 FZ"Type":TAUT"Hauteur":2.7"Longueur":44"Charge":28"PTRE Tracteur":44"PTAC Remorque":38"ADR":false"Norme Euro":EURO5"Nb sangles":12"Nb equerres":8"Nb planches":24"Cordon TIR":true"Tapis":false"Hayon":false"Porte palettes":false"Baches armees":false"Norme XL":false"Porte bobine":false"EPI":true"Attestation dechets":false"Commentaires":false
{ "Cellule":600"Moyen":600GEREFRA1756"Gestionnaire":ISABELLE"Transporteur":GAUTHIER"Origine":FRA"Point de chutte":CRAON 53"Tracteur":DD 859 WG"Remorque":CS 790 HN"Type":TAUT"Hauteur":2.75"Longueur":13.6"Charge":28500"PTRE Tracteur":44"PTAC Remorque":44"ADR":true"Norme Euro":EURO5"Nb sangles":12"Nb equerres":11"Nb planches":24"Cordon TIR":true"Tapis":false"Hayon":false"Porte palettes":false"Baches armees":false"Norme XL":true"Porte bobine":false"EPI":true"Attestation dechets":true"Commentaires":false
{ "Cellule":600"Moyen":600GEREFRA1901"Gestionnaire":VALERIE"Transporteur":PMG"Origine":FRA"Point de chutte":61 FLERS OU 28 NOGENT"Tracteur":BR 948 ZA  --(EB 242 NT)"Remorque":DQ 839 AM"Type":TAUT"Hauteur":2.7"Longueur":13.6"Charge":25"PTRE Tracteur":40"PTAC Remorque":38"ADR":false"Norme Euro":EURO5"Nb sangles":14"Nb equerres":12"Nb planches":24"Cordon TIR":true"Tapis":true"Hayon":false"Porte palettes":false"Baches armees":false"Norme XL":false"Porte bobine":false"EPI":true"Attestation dechets":false"Commentaires":false
{ "Cellule":600"Moyen":600GEREFRA0045"Gestionnaire":CHRISTEL"Transporteur":CANET ALAIN"Origine":FRA"Point de chutte":53 LAVAL"Tracteur":CP683HS"Remorque":AC226KD"Type":TAUT"Hauteur":3"Longueur":13.6"Charge":28"PTRE Tracteur":44.25"PTAC Remorque":38"ADR":false"Norme Euro":EURO5"Nb sangles":35"Nb equerres":30"Nb planches":24"Cordon TIR":true"Tapis":true"Hayon":false"Porte palettes":false"Baches armees":true"Norme XL":false"Porte bobine":false"EPI":true"Attestation dechets":true"Commentaires":false
{ "Cellule":600"Moyen":600GEREFRA1093"Gestionnaire":VALERIE"Transporteur":LEROY"Origine":FRA"Point de chutte":SALLAUMINES 62"Tracteur":BJ 265 XR"Remorque":CT 939 YM"Type":TAUT"Hauteur":2.7"Longueur":13.6"Charge":28"PTRE Tracteur":44"PTAC Remorque":38"ADR":false"Norme Euro":EURO5"Nb sangles":15"Nb equerres":20"Nb planches":24"Cordon TIR":true"Tapis":true"Hayon":false"Porte palettes":false"Baches armees":true"Norme XL":false"Porte bobine":false"EPI":true"Attestation dechets":false"Commentaires":false
{ "Cellule":600"Moyen":600GEREFRA0124"Gestionnaire":ALAIN"Transporteur":CHABRIER"Origine":FRA"Point de chutte":ENNEZAT 63"Tracteur":DC 861 EA"Remorque":CE 990 QT"Type":TAUT"Hauteur":2.7"Longueur":13.6"Charge":29"PTRE Tracteur":44"PTAC Remorque":44"ADR":false"Norme Euro":EURO5"Nb sangles":12"Nb equerres":14"Nb planches":24"Cordon TIR":true"Tapis":true"Hayon":false"Porte palettes":false"Baches armees":false"Norme XL":true"Porte bobine":false"EPI":true"Attestation dechets":false"Commentaires":false
{ "Cellule":600"Moyen":600GEREFRA0387"Gestionnaire":ALAIN"Transporteur":SA  TRS BERTRAND"Origine":FRA"Point de chutte":88 SAINT AME"Tracteur":BZ 038 ZE"Remorque":CT 634 EA"Type":TAUT REH"Hauteur":3.05"Longueur":13.6"Charge":27.5"PTRE Tracteur":44"PTAC Remorque":38"ADR":false"Norme Euro":EURO5"Nb sangles":15"Nb equerres":20"Nb planches":32"Cordon TIR":true"Tapis":true"Hayon":false"Porte palettes":false"Baches armees":false"Norme XL":true"Porte bobine":true"EPI":true"Attestation dechets":false"Commentaires":false
{ "Cellule":600"Moyen":600GEREFRA0391"Gestionnaire":GHISLAIN"Transporteur":CORDIER TRANSPORTS"Origine":FRA"Point de chutte":25 SAINTE MARIE"Tracteur":EE 817 FQ"Remorque":CY 924 RV"Type":TAUT"Hauteur":2.8"Longueur":13.5"Charge":28"PTRE Tracteur":0"PTAC Remorque":0"ADR":false"Norme Euro":EURO5"Nb sangles":15"Nb equerres":24"Nb planches":0"Cordon TIR":true"Tapis":true"Hayon":false"Porte palettes":false"Baches armees":false"Norme XL":false"Porte bobine":false"EPI":true"Attestation dechets":true"Commentaires":false
{ "Cellule":600"Moyen":600GEREFRA1230"Gestionnaire":ISABELLE"Transporteur":MOISSON"Origine":FRA"Point de chutte":51 ISLES SUR SUIPPE"Tracteur":DD 077 MH"Remorque":BN 438 YJ"Type":SAVOYARDE"Hauteur":2.7"Longueur":13.6"Charge":29"PTRE Tracteur":44"PTAC Remorque":0"ADR":false"Norme Euro":EURO6"Nb sangles":15"Nb equerres":27"Nb planches":15"Cordon TIR":true"Tapis":true"Hayon":false"Porte palettes":false"Baches armees":false"Norme XL":false"Porte bobine":false"EPI":true"Attestation dechets":false"Commentaires":false
{ "Cellule":600"Moyen":600GEREFRA1747"Gestionnaire":CHRISTEL"Transporteur":TPMO"Origine":FRA"Point de chutte":37 DESCARTES"Tracteur":DR 287 SE"Remorque":AD 136 SB"Type":TAUT"Hauteur":2.7"Longueur":13.6"Charge":28.3"PTRE Tracteur":44"PTAC Remorque":38"ADR":false"Norme Euro":EURO6"Nb sangles":15"Nb equerres":10"Nb planches":16"Cordon TIR":false"Tapis":true"Hayon":false"Porte palettes":true"Baches armees":false"Norme XL":true"Porte bobine":false"EPI":true"Attestation dechets":true"Commentaires":false
{ "Cellule":600"Moyen":600GEREFRA1709"Gestionnaire":GHISLAIN"Transporteur":CHRONOROUTE"Origine":FRA"Point de chutte":35 CREVIN"Tracteur":EG 626 CV"Remorque":EC 826 SL"Type":TAUT"Hauteur":2.8"Longueur":13.6"Charge":28"PTRE Tracteur":44"PTAC Remorque":38"ADR":false"Norme Euro":EURO6"Nb sangles":20"Nb equerres":10"Nb planches":24"Cordon TIR":true"Tapis":true"Hayon":true"Porte palettes":false"Baches armees":true"Norme XL":true"Porte bobine":false"EPI":true"Attestation dechets":true"Commentaires":false
{ "Cellule":600"Moyen":600GEREFRA0551"Gestionnaire":ISABELLE"Transporteur":LAMAISON HUBERT"Origine":FRA"Point de chutte":40"Tracteur":DC696WW"Remorque":EM-812-FV"Type":TAUT"Hauteur":2.7"Longueur":13.6"Charge":28.5"PTRE Tracteur":44"PTAC Remorque":38"ADR":false"Norme Euro":EURO5"Nb sangles":16"Nb equerres":24"Nb planches":24"Cordon TIR":true"Tapis":true"Hayon":false"Porte palettes":false"Baches armees":false"Norme XL":false"Porte bobine":false"EPI":true"Attestation dechets":false"Commentaires":false
{ "Cellule":600"Moyen":600GEREFRA0451"Gestionnaire":ISABELLE"Transporteur":LAGARDE BERTRAND"Origine":FRA"Point de chutte":88 MOYENMOUTIER"Tracteur":CR 194 SK"Remorque":CK 940 AF"Type":TAUT"Hauteur":2.7"Longueur":13.6"Charge":29"PTRE Tracteur":44"PTAC Remorque":44"ADR":false"Norme Euro":EURO5"Nb sangles":15"Nb equerres":10"Nb planches":24"Cordon TIR":true"Tapis":true"Hayon":false"Porte palettes":false"Baches armees":false"Norme XL":false"Porte bobine":false"EPI":true"Attestation dechets":true"Commentaires":false
{ "Cellule":600"Moyen":600GEREFRA1805"Gestionnaire":CHRISTEL"Transporteur":MARTIN ET FILS"Origine":FRA"Point de chutte":70 GEVIGNEY-MERCEY"Tracteur":EC 498 RL"Remorque":CK-215-QC"Type":TAUT"Hauteur":2.7"Longueur":13.5"Charge":29"PTRE Tracteur":0"PTAC Remorque":0"ADR":true"Norme Euro":EURO5"Nb sangles":16"Nb equerres":25"Nb planches":4"Cordon TIR":true"Tapis":false"Hayon":false"Porte palettes":false"Baches armees":false"Norme XL":false"Porte bobine":false"EPI":true"Attestation dechets":false"Commentaires":false
{ "Cellule":600"Moyen":600GEREFRA0870"Gestionnaire":ISABELLE"Transporteur":SATEG"Origine":FRA"Point de chutte":68 RIXHEIM"Tracteur":EQ 706 XM"Remorque":CT 741 DJ"Type":TAUT REH"Hauteur":3"Longueur":13.4"Charge":28"PTRE Tracteur":0"PTAC Remorque":0"ADR":false"Norme Euro":EURO5"Nb sangles":14"Nb equerres":24"Nb planches":24"Cordon TIR":true"Tapis":true"Hayon":false"Porte palettes":false"Baches armees":false"Norme XL":false"Porte bobine":false"EPI":true"Attestation dechets":true"Commentaires":false
{ "Cellule":600"Moyen":600GEREFRA1999"Gestionnaire":GHISLAIN"Transporteur":TRPS BOUCHEIX SIMON TBS"Origine":FRA"Point de chutte":CLERMONT FERRAND"Tracteur":DV682HX"Remorque":DC124GB"Type":TAUT"Hauteur":2.7"Longueur":13.4"Charge":29.2"PTRE Tracteur":0"PTAC Remorque":0"ADR":false"Norme Euro":EURO5"Nb sangles":15"Nb equerres":60"Nb planches":0"Cordon TIR":true"Tapis":false"Hayon":false"Porte palettes":false"Baches armees":false"Norme XL":false"Porte bobine":false"EPI":false"Attestation dechets":true"Commentaires":false
{ "Cellule":600"Moyen":600GEREFRA1768"Gestionnaire":GHISLAIN"Transporteur":TRPS BOUCHEIX SIMON TBS"Origine":FRA"Point de chutte":CLERMONT FERRAND"Tracteur":CJ245BC"Remorque":CE751NW"Type":TAUT"Hauteur":2.7"Longueur":13.5"Charge":28"PTRE Tracteur":0"PTAC Remorque":44"ADR":false"Norme Euro":EURO5"Nb sangles":12"Nb equerres":12"Nb planches":0"Cordon TIR":true"Tapis":false"Hayon":false"Porte palettes":false"Baches armees":false"Norme XL":false"Porte bobine":false"EPI":false"Attestation dechets":true"Commentaires":false
{ "Cellule":600"Moyen":600GEREFRA0032"Gestionnaire":ISABELLE"Transporteur":LEBLANC ROBERT"Origine":FRA"Point de chutte":70 AUTREY LES GRAY"Tracteur":AW 615 MW"Remorque":BT 094 WC"Type":TAUT"Hauteur":2.7"Longueur":13.4"Charge":28.5"PTRE Tracteur":0"PTAC Remorque":0"ADR":false"Norme Euro":EURO5"Nb sangles":0"Nb equerres":0"Nb planches":0"Cordon TIR":true"Tapis":false"Hayon":false"Porte palettes":false"Baches armees":false"Norme XL":true"Porte bobine":false"EPI":true"Attestation dechets":false"Commentaires":false
{ "Cellule":600"Moyen":600GEREFRA2038"Gestionnaire":ISABELLE"Transporteur":PKM LGISTIQUE"Origine":FRA"Point de chutte":02 LAON"Tracteur":DG 726 NL"Remorque":CH 327 EV"Type":TAUT"Hauteur":2.9"Longueur":13.4"Charge":29"PTRE Tracteur":0"PTAC Remorque":44"ADR":false"Norme Euro":EURO 6"Nb sangles":12"Nb equerres":12"Nb planches":0"Cordon TIR":true"Tapis":true"Hayon":false"Porte palettes":false"Baches armees":true"Norme XL":false"Porte bobine":false"EPI":true"Attestation dechets":false"Commentaires":false
{ "Cellule":600"Moyen":600GEREFRA2055"Gestionnaire":CYRIAC"Transporteur":SAUNIER"Origine":FRA"Point de chutte":28DAMBRON"Tracteur":DM 955 KK"Remorque":"Type":TAUT"Hauteur":2.7"Longueur":13.5"Charge":29"PTRE Tracteur":0"PTAC Remorque":0"ADR":false"Norme Euro":EURO5"Nb sangles":12"Nb equerres":24"Nb planches":0"Cordon TIR":true"Tapis":false"Hayon":false"Porte palettes":false"Baches armees":false"Norme XL":true"Porte bobine":false"EPI":false"Attestation dechets":false"Commentaires":true
{ "Cellule":600"Moyen":600GEREFRA2070"Gestionnaire":GHISLAIN"Transporteur":CASSITRANS"Origine":70"Point de chutte":70 PORT SUR SAONE"Tracteur":CC-728-JJ"Remorque":CW-648-WX"Type":TAUT"Hauteur":2.7"Longueur":13.4"Charge":29728"PTRE Tracteur":0"PTAC Remorque":0"ADR":false"Norme Euro":EURO6"Nb sangles":12"Nb equerres":15"Nb planches":0"Cordon TIR":true"Tapis":false"Hayon":false"Porte palettes":false"Baches armees":false"Norme XL":false"Porte bobine":false"EPI":false"Attestation dechets":false"Commentaires":false
{ "Cellule":600"Moyen":600GEREFRA2071"Gestionnaire":CHRISTEL"Transporteur":TRANSPORT GOMILA"Origine":31 VILLENEUVE LES BOULOC"Point de chutte":31 BOULOC"Tracteur":DH-168-HP"Remorque":DC-602-MR"Type":TAUT"Hauteur":2.85"Longueur":13.4"Charge":28"PTRE Tracteur":0"PTAC Remorque":44"ADR":false"Norme Euro":EURO6"Nb sangles":10"Nb equerres":10"Nb planches":0"Cordon TIR":true"Tapis":false"Hayon":false"Porte palettes":true"Baches armees":true"Norme XL":true"Porte bobine":false"EPI":true"Attestation dechets":false"Commentaires":false
{ "Cellule":600"Moyen":600GEREFRA2083"Gestionnaire":VALERIE"Transporteur":Transports PIALLA  S.A.S"Origine":FRA"Point de chutte":26 PIERRELATTE"Tracteur":CN 284 BC"Remorque":DN-695-YW"Type":TAUT"Hauteur":2.7"Longueur":13.6"Charge":28.5"PTRE Tracteur":44"PTAC Remorque":44"ADR":false"Norme Euro":EURO5"Nb sangles":14"Nb equerres":12"Nb planches":0"Cordon TIR":true"Tapis":false"Hayon":false"Porte palettes":true"Baches armees":false"Norme XL":true"Porte bobine":false"EPI":true"Attestation dechets":true"Commentaires":false
{ "Cellule":600"Moyen":600GEREFRA2084"Gestionnaire":GHISLAIN"Transporteur":TRANSPORTS DELILLE ET CHAUSSE"Origine":FRA"Point de chutte":36 MONTIERCHAUME- 36CELON"Tracteur":EP-693-LF"Remorque":AE-270-HV"Type":TAUT"Hauteur":2.7"Longueur":13.4"Charge":29641"PTRE Tracteur":0"PTAC Remorque":44"ADR":false"Norme Euro":EURO6"Nb sangles":20"Nb equerres":20"Nb planches":0"Cordon TIR":true"Tapis":false"Hayon":false"Porte palettes":false"Baches armees":true"Norme XL":false"Porte bobine":false"EPI":false"Attestation dechets":false"Commentaires":false
{ "Cellule":600"Moyen":600GEREFRA0686"Gestionnaire":GHISLAIN"Transporteur":TLTB"Origine":FRA"Point de chutte":90 ANGEOT"Tracteur":CV-675-TE"Remorque":CV-693-YZ"Type":TAUT"Hauteur":2.75"Longueur":13.6"Charge":29"PTRE Tracteur":0"PTAC Remorque":0"ADR":true"Norme Euro":EURO5"Nb sangles":20"Nb equerres":26"Nb planches":32"Cordon TIR":true"Tapis":true"Hayon":false"Porte palettes":false"Baches armees":true"Norme XL":false"Porte bobine":false"EPI":true"Attestation dechets":true"Commentaires":false
{ "Cellule":600"Moyen":600GEREFRA2103"Gestionnaire":CHRISTEL"Transporteur":LC TRANS"Origine":FRA"Point de chutte":42 St BONET D'OULES"Tracteur":CX-520-DG"Remorque":EH 044 CQ"Type":TAUT"Hauteur":2.7"Longueur":2.5"Charge":29.862"PTRE Tracteur":44"PTAC Remorque":38"ADR":false"Norme Euro":EURO 5"Nb sangles":14"Nb equerres":26"Nb planches":18"Cordon TIR":true"Tapis":false"Hayon":false"Porte palettes":false"Baches armees":false"Norme XL":false"Porte bobine":false"EPI":true"Attestation dechets":false"Commentaires":false
{ "Cellule":600"Moyen":600GEREFRA2104"Gestionnaire":CHRISTEL"Transporteur":LC TRANS"Origine":FRA"Point de chutte":42 St BONET LES OULES"Tracteur":DB 946 NS"Remorque":DT 566 WN"Type":TAUT"Hauteur":2.7"Longueur":2.5"Charge":29.862"PTRE Tracteur":44"PTAC Remorque":38"ADR":false"Norme Euro":EURO5"Nb sangles":14"Nb equerres":26"Nb planches":18"Cordon TIR":true"Tapis":false"Hayon":false"Porte palettes":false"Baches armees":false"Norme XL":false"Porte bobine":false"EPI":true"Attestation dechets":false"Commentaires":false
{ "Cellule":600"Moyen":600GEREFRA2111"Gestionnaire":GHISLAIN"Transporteur":TRANSPORTS COQUELET"Origine":36"Point de chutte":35 TORCE"Tracteur":AV 778 QZ"Remorque":CN 283 NR"Type":TAUT"Hauteur":2.7"Longueur":13.4"Charge":28"PTRE Tracteur":44"PTAC Remorque":44"ADR":false"Norme Euro":EURO5"Nb sangles":10"Nb equerres":6"Nb planches":30"Cordon TIR":true"Tapis":false"Hayon":false"Porte palettes":false"Baches armees":false"Norme XL":false"Porte bobine":false"EPI":true"Attestation dechets":true"Commentaires":false
{ "Cellule":600"Moyen":600GEREFRA2142"Gestionnaire":CHRISTEL"Transporteur":LC TRANS"Origine":42"Point de chutte":42 saint romain les atheux"Tracteur":BQ 299 LD"Remorque":CN-512-AS"Type":TAUT"Hauteur":2.7"Longueur":13.5"Charge":29800"PTRE Tracteur":44"PTAC Remorque":0"ADR":true"Norme Euro":EURO5"Nb sangles":14"Nb equerres":24"Nb planches":0"Cordon TIR":true"Tapis":false"Hayon":false"Porte palettes":false"Baches armees":false"Norme XL":false"Porte bobine":false"EPI":false"Attestation dechets":false"Commentaires":false
{ "Cellule":600"Moyen":600GEREFRA2172"Gestionnaire":VALERIE"Transporteur":JFB TRANS"Origine":70 CLAIREGOUTTE"Point de chutte":70 CLAIREGOUTTE"Tracteur":DB-026-MA"Remorque":"Type":TAUT"Hauteur":0"Longueur":0"Charge":0"PTRE Tracteur":44"PTAC Remorque":0"ADR":false"Norme Euro":EURO5"Nb sangles":12"Nb equerres":0"Nb planches":0"Cordon TIR":false"Tapis":false"Hayon":false"Porte palettes":false"Baches armees":false"Norme XL":false"Porte bobine":false"EPI":false"Attestation dechets":false"Commentaires":false
{ "Cellule":600"Moyen":600GEREFRA2177"Gestionnaire":CHRISTEL"Transporteur":TRANSPORT GOMILA"Origine":31 TOULOUSE"Point de chutte":31 TOULOUSE"Tracteur":EP-823-NZ"Remorque":CG-323-HE"Type":TAUT"Hauteur":2.7"Longueur":13.4"Charge":29"PTRE Tracteur":44"PTAC Remorque":38"ADR":false"Norme Euro":EURO6"Nb sangles":12"Nb equerres":12"Nb planches":24"Cordon TIR":true"Tapis":false"Hayon":false"Porte palettes":false"Baches armees":true"Norme XL":false"Porte bobine":false"EPI":false"Attestation dechets":false"Commentaires":false
{ "Cellule":604"Moyen":604GEREROM1829"Gestionnaire":STEVE PAVIE"Transporteur":PFENNING ROMANIA"Origine":ROM"Point de chutte":Sourcing"Tracteur":B68RRU"Remorque":B35NJV"Type":TAUT"Hauteur":2.7"Longueur":13.6"Charge":24"PTRE Tracteur":40"PTAC Remorque":31"ADR":false"Norme Euro":EURO5"Nb sangles":15"Nb equerres":20"Nb planches":0"Cordon TIR":true"Tapis":true"Hayon":false"Porte palettes":false"Baches armees":false"Norme XL":true"Porte bobine":false"EPI":true"Attestation dechets":false"Commentaires":false
{ "Cellule":604"Moyen":604GEREROM1850"Gestionnaire":STEVE PAVIE"Transporteur":PFENNING ROMANIA"Origine":ROM"Point de chutte":Sourcing"Tracteur":B67NZD"Remorque":B27BPD"Type":TAUT"Hauteur":2.7"Longueur":13.6"Charge":24"PTRE Tracteur":40"PTAC Remorque":31"ADR":false"Norme Euro":EURO6"Nb sangles":15"Nb equerres":20"Nb planches":0"Cordon TIR":true"Tapis":true"Hayon":false"Porte palettes":false"Baches armees":false"Norme XL":false"Porte bobine":false"EPI":true"Attestation dechets":false"Commentaires":false
{ "Cellule":604"Moyen":604GEREROM1893"Gestionnaire":STEVE PAVIE"Transporteur":PFENNING ROMANIA"Origine":ROM"Point de chutte":Sourcing"Tracteur":B63GBS"Remorque":B26JFM"Type":TAUT"Hauteur":2.7"Longueur":13.6"Charge":24"PTRE Tracteur":40"PTAC Remorque":31"ADR":false"Norme Euro":EURO6"Nb sangles":15"Nb equerres":20"Nb planches":0"Cordon TIR":true"Tapis":true"Hayon":false"Porte palettes":false"Baches armees":false"Norme XL":false"Porte bobine":false"EPI":true"Attestation dechets":false"Commentaires":false
{ "Cellule":604"Moyen":604GEREROM1852"Gestionnaire":STEVE PAVIE"Transporteur":PFENNING ROMANIA"Origine":ROM"Point de chutte":Sourcing"Tracteur":B 68 RRL"Remorque":B 35 NKT"Type":TAUT"Hauteur":2.7"Longueur":13.6"Charge":24"PTRE Tracteur":40"PTAC Remorque":31"ADR":false"Norme Euro":EURO 6"Nb sangles":15"Nb equerres":20"Nb planches":0"Cordon TIR":true"Tapis":true"Hayon":false"Porte palettes":false"Baches armees":false"Norme XL":false"Porte bobine":false"EPI":true"Attestation dechets":false"Commentaires":false
{ "Cellule":604"Moyen":604GERELTU1701"Gestionnaire":DANIEL SAEZ"Transporteur":LAGERA UAB"Origine":LTU"Point de chutte":Sourcing"Tracteur":GDA643"Remorque":EL928"Type":TAUT"Hauteur":2.7"Longueur":13.6"Charge":25"PTRE Tracteur":40"PTAC Remorque":34"ADR":false"Norme Euro":EURO5"Nb sangles":16"Nb equerres":0"Nb planches":0"Cordon TIR":true"Tapis":true"Hayon":false"Porte palettes":false"Baches armees":false"Norme XL":true"Porte bobine":false"EPI":true"Attestation dechets":false"Commentaires":false
{ "Cellule":604"Moyen":604GERELTU1735"Gestionnaire":DANIEL SAEZ"Transporteur":LAGERA UAB"Origine":LTU"Point de chutte":Sourcing"Tracteur":FBT022"Remorque":CJ552"Type":TAUT"Hauteur":2.7"Longueur":13.6"Charge":25"PTRE Tracteur":40"PTAC Remorque":34"ADR":false"Norme Euro":EURO5"Nb sangles":16"Nb equerres":0"Nb planches":0"Cordon TIR":true"Tapis":true"Hayon":false"Porte palettes":false"Baches armees":false"Norme XL":true"Porte bobine":false"EPI":true"Attestation dechets":false"Commentaires":false
{ "Cellule":604"Moyen":604GERELTU1739"Gestionnaire":DANIEL SAEZ"Transporteur":LAGERA UAB"Origine":LTU"Point de chutte":Sourcing"Tracteur":GTG390"Remorque":FC167"Type":TAUT"Hauteur":2.7"Longueur":13.6"Charge":25"PTRE Tracteur":40"PTAC Remorque":34"ADR":false"Norme Euro":EURO5"Nb sangles":16"Nb equerres":0"Nb planches":0"Cordon TIR":true"Tapis":true"Hayon":false"Porte palettes":false"Baches armees":false"Norme XL":true"Porte bobine":false"EPI":true"Attestation dechets":false"Commentaires":false
{ "Cellule":604"Moyen":604GERELTU1738"Gestionnaire":DANIEL SAEZ"Transporteur":LAGERA UAB"Origine":LTU"Point de chutte":Sourcing"Tracteur":CFJ175"Remorque":BG225"Type":TAUT"Hauteur":2.7"Longueur":13.6"Charge":25"PTRE Tracteur":40"PTAC Remorque":34"ADR":false"Norme Euro":EURO4"Nb sangles":16"Nb equerres":0"Nb planches":0"Cordon TIR":true"Tapis":true"Hayon":false"Porte palettes":false"Baches armees":false"Norme XL":true"Porte bobine":false"EPI":true"Attestation dechets":false"Commentaires":false
{ "Cellule":604"Moyen":604GERELTU1885"Gestionnaire":DANIEL SAEZ"Transporteur":LAGERA UAB"Origine":LTU"Point de chutte":Sourcing"Tracteur":GNG685"Remorque":ET617"Type":TAUT"Hauteur":2.7"Longueur":13.6"Charge":25"PTRE Tracteur":40"PTAC Remorque":34"ADR":false"Norme Euro":EURO5"Nb sangles":16"Nb equerres":0"Nb planches":0"Cordon TIR":true"Tapis":true"Hayon":false"Porte palettes":false"Baches armees":false"Norme XL":true"Porte bobine":false"EPI":true"Attestation dechets":false"Commentaires":false
{ "Cellule":604"Moyen":604GERELTU1625"Gestionnaire":DANIEL SAEZ"Transporteur":UAB SAUSUMOS LAIVAI"Origine":LTU"Point de chutte":Sourcing"Tracteur":GGA338"Remorque":BU634"Type":TAUT"Hauteur":2.7"Longueur":13.6"Charge":24"PTRE Tracteur":40"PTAC Remorque":34"ADR":false"Norme Euro":EURO5"Nb sangles":16"Nb equerres":32"Nb planches":0"Cordon TIR":true"Tapis":true"Hayon":false"Porte palettes":false"Baches armees":false"Norme XL":true"Porte bobine":false"EPI":true"Attestation dechets":false"Commentaires":false
{ "Cellule":604"Moyen":604GERELTU1644"Gestionnaire":DANIEL SAEZ"Transporteur":UAB SAUSUMOS LAIVAI"Origine":LTU"Point de chutte":Sourcing"Tracteur":GGA583"Remorque":BU636"Type":TAUT"Hauteur":2.7"Longueur":13.6"Charge":24"PTRE Tracteur":40"PTAC Remorque":34"ADR":false"Norme Euro":EURO5"Nb sangles":16"Nb equerres":32"Nb planches":0"Cordon TIR":true"Tapis":true"Hayon":false"Porte palettes":false"Baches armees":false"Norme XL":true"Porte bobine":false"EPI":true"Attestation dechets":false"Commentaires":false
{ "Cellule":604"Moyen":604GERELTU1765"Gestionnaire":DANIEL SAEZ"Transporteur":UAB SAUSUMOS LAIVAI"Origine":LTU"Point de chutte":Sourcing"Tracteur":GGB199"Remorque":DF059"Type":TAUT"Hauteur":2.7"Longueur":13.6"Charge":24"PTRE Tracteur":40"PTAC Remorque":34"ADR":false"Norme Euro":EURO5"Nb sangles":16"Nb equerres":32"Nb planches":0"Cordon TIR":true"Tapis":true"Hayon":false"Porte palettes":false"Baches armees":false"Norme XL":true"Porte bobine":false"EPI":true"Attestation dechets":false"Commentaires":false
{ "Cellule":604"Moyen":604GERELTU1642"Gestionnaire":VINCENT LAFAY"Transporteur":UAB TRANSGESTA"Origine":LTU"Point de chutte":Sourcing"Tracteur":HZR224"Remorque":FZ150"Type":TAUT"Hauteur":2.7"Longueur":13.6"Charge":25"PTRE Tracteur":40"PTAC Remorque":34"ADR":false"Norme Euro":EURO6"Nb sangles":16"Nb equerres":32"Nb planches":0"Cordon TIR":true"Tapis":true"Hayon":false"Porte palettes":false"Baches armees":false"Norme XL":true"Porte bobine":false"EPI":true"Attestation dechets":false"Commentaires":false
{ "Cellule":604"Moyen":604GERELTU1712"Gestionnaire":VINCENT LAFAY"Transporteur":UAB TRANSGESTA"Origine":LTU"Point de chutte":Sourcing"Tracteur":HCT949"Remorque":FB487"Type":TAUT"Hauteur":2.7"Longueur":13.6"Charge":25"PTRE Tracteur":40"PTAC Remorque":34"ADR":false"Norme Euro":EURO5"Nb sangles":16"Nb equerres":32"Nb planches":0"Cordon TIR":true"Tapis":true"Hayon":false"Porte palettes":false"Baches armees":false"Norme XL":true"Porte bobine":false"EPI":true"Attestation dechets":false"Commentaires":false
{ "Cellule":604"Moyen":604GERELTU1725"Gestionnaire":VINCENT LAFAY"Transporteur":UAB TRANSGESTA"Origine":LTU"Point de chutte":Sourcing"Tracteur":HCT929"Remorque":FN015"Type":TAUT"Hauteur":2.7"Longueur":13.6"Charge":25"PTRE Tracteur":40"PTAC Remorque":34"ADR":false"Norme Euro":EURO6"Nb sangles":16"Nb equerres":32"Nb planches":0"Cordon TIR":true"Tapis":true"Hayon":false"Porte palettes":false"Baches armees":false"Norme XL":true"Porte bobine":false"EPI":true"Attestation dechets":false"Commentaires":false
{ "Cellule":604"Moyen":604GERELTU1881"Gestionnaire":VINCENT LAFAY"Transporteur":UAB TRANSGESTA"Origine":LTU"Point de chutte":Sourcing"Tracteur":HZR251"Remorque":FN013"Type":TAUT"Hauteur":2.7"Longueur":13.6"Charge":25"PTRE Tracteur":40"PTAC Remorque":34"ADR":false"Norme Euro":EURO6"Nb sangles":16"Nb equerres":32"Nb planches":0"Cordon TIR":true"Tapis":true"Hayon":false"Porte palettes":false"Baches armees":false"Norme XL":true"Porte bobine":false"EPI":true"Attestation dechets":false"Commentaires":false
{ "Cellule":604"Moyen":604GERELTU1882"Gestionnaire":VINCENT LAFAY"Transporteur":UAB TRANSGESTA"Origine":LTU"Point de chutte":Sourcing"Tracteur":HET726"Remorque":FT576"Type":TAUT"Hauteur":2.7"Longueur":13.6"Charge":25"PTRE Tracteur":40"PTAC Remorque":34"ADR":false"Norme Euro":EURO6"Nb sangles":16"Nb equerres":32"Nb planches":0"Cordon TIR":true"Tapis":true"Hayon":false"Porte palettes":false"Baches armees":false"Norme XL":true"Porte bobine":false"EPI":true"Attestation dechets":false"Commentaires":false
{ "Cellule":604"Moyen":604GERELTU1902"Gestionnaire":VINCENT LAFAY"Transporteur":UAB TRANSGESTA"Origine":LTU"Point de chutte":Sourcing"Tracteur":GNB408"Remorque":FN021"Type":TAUT"Hauteur":2.7"Longueur":13.6"Charge":25"PTRE Tracteur":40"PTAC Remorque":34"ADR":false"Norme Euro":EURO5"Nb sangles":16"Nb equerres":0"Nb planches":0"Cordon TIR":true"Tapis":true"Hayon":false"Porte palettes":false"Baches armees":false"Norme XL":false"Porte bobine":false"EPI":true"Attestation dechets":false"Commentaires":false
{ "Cellule":604"Moyen":604GERELTU1905"Gestionnaire":VINCENT LAFAY"Transporteur":UAB TRANSGESTA"Origine":LTU"Point de chutte":Sourcing"Tracteur":HCT959"Remorque":EP014"Type":TAUT"Hauteur":2.7"Longueur":13.6"Charge":25"PTRE Tracteur":40"PTAC Remorque":34"ADR":false"Norme Euro":EURO6"Nb sangles":16"Nb equerres":32"Nb planches":0"Cordon TIR":true"Tapis":true"Hayon":false"Porte palettes":false"Baches armees":false"Norme XL":true"Porte bobine":false"EPI":true"Attestation dechets":false"Commentaires":false
{ "Cellule":604"Moyen":604GERELTU1908"Gestionnaire":VINCENT LAFAY"Transporteur":UAB TRANSGESTA"Origine":LTU"Point de chutte":Sourcing"Tracteur":GNB408"Remorque":FN021"Type":TAUT"Hauteur":2.7"Longueur":13.6"Charge":25"PTRE Tracteur":40"PTAC Remorque":34"ADR":false"Norme Euro":EURO5"Nb sangles":16"Nb equerres":0"Nb planches":0"Cordon TIR":true"Tapis":true"Hayon":false"Porte palettes":false"Baches armees":false"Norme XL":false"Porte bobine":false"EPI":true"Attestation dechets":false"Commentaires":false
{ "Cellule":604"Moyen":604GERELTU1910"Gestionnaire":VINCENT LAFAY"Transporteur":UAB TRANSGESTA"Origine":LTU"Point de chutte":Sourcing"Tracteur":GNB408"Remorque":FN021"Type":TAUT"Hauteur":2.7"Longueur":13.6"Charge":25"PTRE Tracteur":40"PTAC Remorque":34"ADR":false"Norme Euro":EURO5"Nb sangles":16"Nb equerres":0"Nb planches":0"Cordon TIR":true"Tapis":true"Hayon":false"Porte palettes":false"Baches armees":false"Norme XL":false"Porte bobine":false"EPI":true"Attestation dechets":false"Commentaires":false
{ "Cellule":604"Moyen":604GERELTU2018"Gestionnaire":STEVE PAVIE"Transporteur":OST WEST CARGO BALTIC"Origine":LTU"Point de chutte":Sourcing"Tracteur":GUM568"Remorque":FM640"Type":TAUT"Hauteur":2.65"Longueur":13.4"Charge":25"PTRE Tracteur":40"PTAC Remorque":34"ADR":false"Norme Euro":EURO 5"Nb sangles":15"Nb equerres":30"Nb planches":0"Cordon TIR":true"Tapis":true"Hayon":false"Porte palettes":false"Baches armees":false"Norme XL":false"Porte bobine":false"EPI":true"Attestation dechets":true"Commentaires":false
{ "Cellule":604"Moyen":604GERELTU1943"Gestionnaire":STEVE PAVIE"Transporteur":OST WEST CARGO BALTIC"Origine":LTU"Point de chutte":Bche arme"Tracteur":GHS 074"Remorque":FC591"Type":TAUT"Hauteur":2.7"Longueur":13.6"Charge":25"PTRE Tracteur":40"PTAC Remorque":34"ADR":false"Norme Euro":EURO5"Nb sangles":15"Nb equerres":0"Nb planches":0"Cordon TIR":true"Tapis":true"Hayon":false"Porte palettes":false"Baches armees":true"Norme XL":true"Porte bobine":false"EPI":true"Attestation dechets":true"Commentaires":false
{ "Cellule":604"Moyen":604GERELTU1906"Gestionnaire":VINCENT LAFAY"Transporteur":UAB TRANSGESTA"Origine":LTU"Point de chutte":Sourcing"Tracteur":HET725"Remorque":ET006"Type":TAUT"Hauteur":2.7"Longueur":13.6"Charge":25"PTRE Tracteur":40"PTAC Remorque":34"ADR":false"Norme Euro":EURO6"Nb sangles":16"Nb equerres":32"Nb planches":0"Cordon TIR":true"Tapis":true"Hayon":false"Porte palettes":false"Baches armees":false"Norme XL":true"Porte bobine":false"EPI":true"Attestation dechets":false"Commentaires":false
{ "Cellule":604"Moyen":604GERELTU1916"Gestionnaire":STEVE PAVIE"Transporteur":OST WEST CARGO BALTIC"Origine":LTU"Point de chutte":Bche arme"Tracteur":HJN 691"Remorque":EB277"Type":TAUT"Hauteur":2.7"Longueur":13.6"Charge":25"PTRE Tracteur":40"PTAC Remorque":34"ADR":false"Norme Euro":EURO5"Nb sangles":15"Nb equerres":0"Nb planches":0"Cordon TIR":true"Tapis":true"Hayon":false"Porte palettes":false"Baches armees":true"Norme XL":true"Porte bobine":false"EPI":true"Attestation dechets":true"Commentaires":false
{ "Cellule":604"Moyen":604GERELTU1807"Gestionnaire":STEVE PAVIE"Transporteur":OST WEST CARGO BALTIC"Origine":LTU"Point de chutte":Bche arme"Tracteur":GHS 073"Remorque":FC580"Type":TAUT"Hauteur":2.7"Longueur":13.6"Charge":25"PTRE Tracteur":40"PTAC Remorque":34"ADR":false"Norme Euro":EURO5"Nb sangles":15"Nb equerres":0"Nb planches":0"Cordon TIR":true"Tapis":true"Hayon":false"Porte palettes":false"Baches armees":true"Norme XL":true"Porte bobine":false"EPI":true"Attestation dechets":false"Commentaires":false
{ "Cellule":604"Moyen":568PEPT604FRA0027"Gestionnaire":JULIEN BREUILH"Transporteur":PATINTER PORTUGUESA, LDA"Origine":PRT"Point de chutte":Sourcing"Tracteur":77-QQ-49"Remorque":GD-1018"Type":TAUT"Hauteur":2.8"Longueur":13.6"Charge":24"PTRE Tracteur":40"PTAC Remorque":34"ADR":false"Norme Euro":EURO5"Nb sangles":12"Nb equerres":0"Nb planches":0"Cordon TIR":true"Tapis":true"Hayon":false"Porte palettes":false"Baches armees":false"Norme XL":true"Porte bobine":false"EPI":true"Attestation dechets":true"Commentaires":true
{ "Cellule":604"Moyen":568PEPT604FRA0037"Gestionnaire":JULIEN BREUILH"Transporteur":PATINTER PORTUGUESA, LDA"Origine":PRT"Point de chutte":Sourcing"Tracteur":42-PL-59"Remorque":GD-1095"Type":TAUT"Hauteur":2.8"Longueur":13.6"Charge":24"PTRE Tracteur":40"PTAC Remorque":34"ADR":false"Norme Euro":EURO5"Nb sangles":12"Nb equerres":0"Nb planches":0"Cordon TIR":true"Tapis":true"Hayon":false"Porte palettes":false"Baches armees":false"Norme XL":true"Porte bobine":false"EPI":true"Attestation dechets":true"Commentaires":true
{ "Cellule":604"Moyen":568PEPT604FRA0078"Gestionnaire":JULIEN BREUILH"Transporteur":PATINTER PORTUGUESA, LDA"Origine":PRT"Point de chutte":Sourcing"Tracteur":04-PI-26"Remorque":VI-8102"Type":TAUT"Hauteur":2.8"Longueur":13.6"Charge":24"PTRE Tracteur":40"PTAC Remorque":34"ADR":false"Norme Euro":EURO5"Nb sangles":12"Nb equerres":0"Nb planches":0"Cordon TIR":true"Tapis":true"Hayon":false"Porte palettes":false"Baches armees":false"Norme XL":false"Porte bobine":false"EPI":true"Attestation dechets":true"Commentaires":true
{ "Cellule":604"Moyen":568PEPT604FRA0085"Gestionnaire":JULIEN BREUILH"Transporteur":PATINTER PORTUGUESA, LDA"Origine":PRT"Point de chutte":Sourcing"Tracteur":06-PG-80"Remorque":LE-1558"Type":TAUT"Hauteur":2.8"Longueur":13.6"Charge":24"PTRE Tracteur":40"PTAC Remorque":34"ADR":false"Norme Euro":EURO5"Nb sangles":12"Nb equerres":0"Nb planches":0"Cordon TIR":true"Tapis":true"Hayon":false"Porte palettes":false"Baches armees":false"Norme XL":true"Porte bobine":false"EPI":true"Attestation dechets":true"Commentaires":true
{ "Cellule":604"Moyen":568PEPT604FRA0091"Gestionnaire":JULIEN BREUILH"Transporteur":PATINTER PORTUGUESA, LDA"Origine":PRT"Point de chutte":Sourcing"Tracteur":78PZ20"Remorque":VI8392"Type":TAUT"Hauteur":2.95"Longueur":13.6"Charge":24"PTRE Tracteur":40"PTAC Remorque":34"ADR":false"Norme Euro":EURO5"Nb sangles":12"Nb equerres":0"Nb planches":0"Cordon TIR":true"Tapis":true"Hayon":false"Porte palettes":false"Baches armees":false"Norme XL":false"Porte bobine":false"EPI":true"Attestation dechets":true"Commentaires":true
{ "Cellule":604"Moyen":568PEPT604FRA0093"Gestionnaire":JULIEN BREUILH"Transporteur":PATINTER PORTUGUESA, LDA"Origine":PRT"Point de chutte":Sourcing"Tracteur":06-PG-82"Remorque":GD-793"Type":TAUT"Hauteur":2.8"Longueur":13.6"Charge":24"PTRE Tracteur":40"PTAC Remorque":34"ADR":false"Norme Euro":EURO5"Nb sangles":12"Nb equerres":0"Nb planches":0"Cordon TIR":true"Tapis":true"Hayon":false"Porte palettes":false"Baches armees":false"Norme XL":true"Porte bobine":false"EPI":true"Attestation dechets":true"Commentaires":true
{ "Cellule":604"Moyen":568PEPT604FRA0104"Gestionnaire":JULIEN BREUILH"Transporteur":PATINTER PORTUGUESA, LDA"Origine":PRT"Point de chutte":Sourcing"Tracteur":72-PD-42"Remorque":GD-849"Type":TAUT"Hauteur":2.8"Longueur":13.6"Charge":24"PTRE Tracteur":40"PTAC Remorque":34"ADR":false"Norme Euro":EURO5"Nb sangles":12"Nb equerres":0"Nb planches":0"Cordon TIR":true"Tapis":true"Hayon":false"Porte palettes":false"Baches armees":false"Norme XL":true"Porte bobine":false"EPI":true"Attestation dechets":true"Commentaires":true
{ "Cellule":604"Moyen":568PEPT604FRA0106"Gestionnaire":JULIEN BREUILH"Transporteur":PATINTER PORTUGUESA, LDA"Origine":PRT"Point de chutte":Sourcing"Tracteur":89-QF-10"Remorque":GD-1197"Type":TAUT"Hauteur":2.8"Longueur":13.6"Charge":24"PTRE Tracteur":40"PTAC Remorque":34"ADR":false"Norme Euro":EURO5"Nb sangles":12"Nb equerres":0"Nb planches":0"Cordon TIR":true"Tapis":true"Hayon":false"Porte palettes":false"Baches armees":false"Norme XL":true"Porte bobine":false"EPI":true"Attestation dechets":true"Commentaires":true
{ "Cellule":604"Moyen":568PEPT604FRA0108"Gestionnaire":JULIEN BREUILH"Transporteur":PATINTER PORTUGUESA, LDA"Origine":PRT"Point de chutte":Sourcing"Tracteur":89-QF-07"Remorque":GD-1100"Type":TAUT"Hauteur":2.8"Longueur":13.6"Charge":24"PTRE Tracteur":40"PTAC Remorque":34"ADR":false"Norme Euro":EURO5"Nb sangles":12"Nb equerres":0"Nb planches":0"Cordon TIR":true"Tapis":true"Hayon":false"Porte palettes":false"Baches armees":false"Norme XL":true"Porte bobine":false"EPI":true"Attestation dechets":true"Commentaires":true
{ "Cellule":604"Moyen":568PEPT604FRA0117"Gestionnaire":JULIEN BREUILH"Transporteur":PATINTER PORTUGUESA, LDA"Origine":PRT"Point de chutte":Sourcing"Tracteur":41-QB-94"Remorque":GD-1206"Type":TAUT"Hauteur":2.8"Longueur":13.6"Charge":24"PTRE Tracteur":40"PTAC Remorque":34"ADR":false"Norme Euro":EURO5"Nb sangles":12"Nb equerres":0"Nb planches":0"Cordon TIR":true"Tapis":true"Hayon":false"Porte palettes":false"Baches armees":false"Norme XL":true"Porte bobine":false"EPI":true"Attestation dechets":true"Commentaires":true
{ "Cellule":604"Moyen":568PEPT604FRA0123"Gestionnaire":JULIEN BREUILH"Transporteur":PATINTER PORTUGUESA, LDA"Origine":PRT"Point de chutte":Sourcing"Tracteur":99OB76"Remorque":SE2849"Type":TAUT"Hauteur":2.95"Longueur":13.6"Charge":24"PTRE Tracteur":40"PTAC Remorque":34"ADR":false"Norme Euro":EURO5"Nb sangles":0"Nb equerres":0"Nb planches":0"Cordon TIR":false"Tapis":false"Hayon":false"Porte palettes":false"Baches armees":false"Norme XL":false"Porte bobine":false"EPI":true"Attestation dechets":true"Commentaires":true
{ "Cellule":604"Moyen":604GERELTU1904"Gestionnaire":VINCENT LAFAY"Transporteur":UAB TRANSGESTA"Origine":LTU"Point de chutte":Sourcing"Tracteur":HPN859"Remorque":FT581"Type":TAUT"Hauteur":2.7"Longueur":13.6"Charge":25"PTRE Tracteur":40"PTAC Remorque":34"ADR":false"Norme Euro":EURO6"Nb sangles":16"Nb equerres":32"Nb planches":0"Cordon TIR":true"Tapis":true"Hayon":false"Porte palettes":false"Baches armees":false"Norme XL":true"Porte bobine":false"EPI":true"Attestation dechets":false"Commentaires":false
{ "Cellule":604"Moyen":604GEREROM1849"Gestionnaire":STEVE PAVIE"Transporteur":PFENNING ROMANIA"Origine":ROM"Point de chutte":Sourcing"Tracteur":B74SIX"Remorque":B27BNN"Type":TAUT"Hauteur":2.7"Longueur":13.6"Charge":24"PTRE Tracteur":40"PTAC Remorque":31"ADR":false"Norme Euro":EURO5"Nb sangles":15"Nb equerres":20"Nb planches":0"Cordon TIR":true"Tapis":true"Hayon":false"Porte palettes":false"Baches armees":false"Norme XL":true"Porte bobine":false"EPI":true"Attestation dechets":false"Commentaires":false
{ "Cellule":604"Moyen":604GEREROM1894"Gestionnaire":STEVE PAVIE"Transporteur":PFENNING ROMANIA"Origine":ROM"Point de chutte":Sourcing"Tracteur":B 67 NZD"Remorque":B 27 BPD"Type":TAUT"Hauteur":2.7"Longueur":13.6"Charge":24"PTRE Tracteur":40"PTAC Remorque":31"ADR":false"Norme Euro":EURO 6"Nb sangles":15"Nb equerres":20"Nb planches":0"Cordon TIR":true"Tapis":true"Hayon":false"Porte palettes":false"Baches armees":false"Norme XL":false"Porte bobine":false"EPI":true"Attestation dechets":false"Commentaires":false
{ "Cellule":604"Moyen":604GERELTU1732"Gestionnaire":DANIEL SAEZ"Transporteur":LAGERA UAB"Origine":LTU"Point de chutte":Sourcing"Tracteur":GDB284"Remorque":et613"Type":TAUT"Hauteur":2.7"Longueur":13.6"Charge":25"PTRE Tracteur":40"PTAC Remorque":34"ADR":false"Norme Euro":EURO5"Nb sangles":16"Nb equerres":0"Nb planches":0"Cordon TIR":true"Tapis":true"Hayon":false"Porte palettes":false"Baches armees":false"Norme XL":true"Porte bobine":false"EPI":true"Attestation dechets":false"Commentaires":false
{ "Cellule":604"Moyen":604GERELTU1766"Gestionnaire":DANIEL SAEZ"Transporteur":LAGERA UAB"Origine":LTU"Point de chutte":Sourcing"Tracteur":GDA644"Remorque":EL933"Type":TAUT"Hauteur":2.7"Longueur":13.6"Charge":25"PTRE Tracteur":40"PTAC Remorque":34"ADR":false"Norme Euro":EURO5"Nb sangles":16"Nb equerres":0"Nb planches":0"Cordon TIR":true"Tapis":true"Hayon":false"Porte palettes":false"Baches armees":false"Norme XL":true"Porte bobine":false"EPI":true"Attestation dechets":false"Commentaires":false
{ "Cellule":604"Moyen":604GERELTU1619"Gestionnaire":DANIEL SAEZ"Transporteur":UAB SAUSUMOS LAIVAI"Origine":LTU"Point de chutte":Sourcing"Tracteur":"Remorque":"Type":TAUT"Hauteur":2.7"Longueur":13.6"Charge":24"PTRE Tracteur":40"PTAC Remorque":34"ADR":false"Norme Euro":EURO6"Nb sangles":16"Nb equerres":32"Nb planches":0"Cordon TIR":true"Tapis":true"Hayon":false"Porte palettes":false"Baches armees":false"Norme XL":true"Porte bobine":false"EPI":true"Attestation dechets":false"Commentaires":false
{ "Cellule":604"Moyen":604GERELTU1661"Gestionnaire":DANIEL SAEZ"Transporteur":UAB SAUSUMOS LAIVAI"Origine":LTU"Point de chutte":Sourcing"Tracteur":GTK296"Remorque":KV789"Type":TAUT"Hauteur":2.7"Longueur":13.6"Charge":24"PTRE Tracteur":40"PTAC Remorque":34"ADR":false"Norme Euro":EURO 5"Nb sangles":16"Nb equerres":32"Nb planches":0"Cordon TIR":true"Tapis":true"Hayon":false"Porte palettes":false"Baches armees":false"Norme XL":true"Porte bobine":false"EPI":true"Attestation dechets":false"Commentaires":false
{ "Cellule":604"Moyen":604GERELTU1830"Gestionnaire":DANIEL SAEZ"Transporteur":UAB SAUSUMOS LAIVAI"Origine":LTU"Point de chutte":Sourcing"Tracteur":GDT089"Remorque":BU637"Type":TAUT"Hauteur":2.7"Longueur":13.6"Charge":24"PTRE Tracteur":40"PTAC Remorque":34"ADR":false"Norme Euro":EURO5"Nb sangles":16"Nb equerres":32"Nb planches":0"Cordon TIR":true"Tapis":true"Hayon":false"Porte palettes":false"Baches armees":false"Norme XL":true"Porte bobine":false"EPI":true"Attestation dechets":false"Commentaires":false
{ "Cellule":604"Moyen":604GERELTU1726"Gestionnaire":VINCENT LAFAY"Transporteur":UAB TRANSGESTA"Origine":LTU"Point de chutte":Sourcing"Tracteur":HCT939"Remorque":FN013"Type":TAUT"Hauteur":2.7"Longueur":13.6"Charge":25"PTRE Tracteur":40"PTAC Remorque":34"ADR":false"Norme Euro":EURO5"Nb sangles":16"Nb equerres":0"Nb planches":0"Cordon TIR":true"Tapis":true"Hayon":false"Porte palettes":false"Baches armees":false"Norme XL":false"Porte bobine":false"EPI":true"Attestation dechets":false"Commentaires":false
{ "Cellule":604"Moyen":604GERELTU1883"Gestionnaire":VINCENT LAFAY"Transporteur":UAB TRANSGESTA"Origine":LTU"Point de chutte":Sourcing"Tracteur":HCT939"Remorque":FN014"Type":TAUT"Hauteur":2.7"Longueur":13.6"Charge":25"PTRE Tracteur":40"PTAC Remorque":34"ADR":false"Norme Euro":EURO6"Nb sangles":16"Nb equerres":32"Nb planches":0"Cordon TIR":true"Tapis":true"Hayon":false"Porte palettes":false"Baches armees":false"Norme XL":true"Porte bobine":false"EPI":true"Attestation dechets":false"Commentaires":false
{ "Cellule":604"Moyen":604GERELTU1903"Gestionnaire":VINCENT LAFAY"Transporteur":UAB TRANSGESTA"Origine":LTU"Point de chutte":Sourcing"Tracteur":HPN903"Remorque":FN017"Type":TAUT"Hauteur":2.7"Longueur":13.6"Charge":25"PTRE Tracteur":40"PTAC Remorque":34"ADR":false"Norme Euro":EURO6"Nb sangles":16"Nb equerres":32"Nb planches":0"Cordon TIR":true"Tapis":true"Hayon":false"Porte palettes":false"Baches armees":false"Norme XL":true"Porte bobine":false"EPI":true"Attestation dechets":false"Commentaires":false
{ "Cellule":604"Moyen":604GERELTU1909"Gestionnaire":VINCENT LAFAY"Transporteur":UAB TRANSGESTA"Origine":LTU"Point de chutte":Sourcing"Tracteur":GNB408"Remorque":FN021"Type":TAUT"Hauteur":2.7"Longueur":13.6"Charge":25"PTRE Tracteur":40"PTAC Remorque":34"ADR":false"Norme Euro":EURO5"Nb sangles":16"Nb equerres":0"Nb planches":0"Cordon TIR":true"Tapis":true"Hayon":false"Porte palettes":false"Baches armees":false"Norme XL":false"Porte bobine":false"EPI":true"Attestation dechets":false"Commentaires":false
{ "Cellule":604"Moyen":604GERELTU1944"Gestionnaire":STEVE PAVIE"Transporteur":OST WEST CARGO BALTIC"Origine":LTU"Point de chutte":Bche arme"Tracteur":GUL941"Remorque":FH480"Type":TAUT"Hauteur":2.7"Longueur":13.6"Charge":25"PTRE Tracteur":40"PTAC Remorque":34"ADR":false"Norme Euro":EURO5"Nb sangles":15"Nb equerres":0"Nb planches":0"Cordon TIR":true"Tapis":true"Hayon":false"Porte palettes":false"Baches armees":true"Norme XL":true"Porte bobine":false"EPI":true"Attestation dechets":true"Commentaires":false
{ "Cellule":604"Moyen":604GERELTU1834"Gestionnaire":STEVE PAVIE"Transporteur":OST WEST CARGO BALTIC"Origine":LTU"Point de chutte":Sourcing"Tracteur":HAC506"Remorque":FJ645"Type":TAUT"Hauteur":2.7"Longueur":13.6"Charge":24"PTRE Tracteur":40"PTAC Remorque":34"ADR":false"Norme Euro":EURO5"Nb sangles":15"Nb equerres":28"Nb planches":0"Cordon TIR":true"Tapis":true"Hayon":false"Porte palettes":false"Baches armees":false"Norme XL":true"Porte bobine":false"EPI":true"Attestation dechets":true"Commentaires":false
{ "Cellule":604"Moyen":568PEPT604FRA0012"Gestionnaire":JULIEN BREUILH"Transporteur":PATINTER PORTUGUESA, LDA"Origine":PRT"Point de chutte":Sourcing"Tracteur":42-PL-56"Remorque":LE-1010"Type":TAUT"Hauteur":2.8"Longueur":13.6"Charge":24"PTRE Tracteur":40"PTAC Remorque":34"ADR":false"Norme Euro":EURO5"Nb sangles":12"Nb equerres":0"Nb planches":0"Cordon TIR":true"Tapis":true"Hayon":false"Porte palettes":false"Baches armees":false"Norme XL":true"Porte bobine":false"EPI":true"Attestation dechets":true"Commentaires":true
{ "Cellule":604"Moyen":568PEPT604FRA0090"Gestionnaire":JULIEN BREUILH"Transporteur":PATINTER PORTUGUESA, LDA"Origine":PRT"Point de chutte":Sourcing"Tracteur":89-QF-11"Remorque":GD-1227"Type":TAUT"Hauteur":2.8"Longueur":13.6"Charge":24"PTRE Tracteur":40"PTAC Remorque":34"ADR":false"Norme Euro":EURO5"Nb sangles":12"Nb equerres":0"Nb planches":0"Cordon TIR":true"Tapis":true"Hayon":false"Porte palettes":false"Baches armees":false"Norme XL":true"Porte bobine":false"EPI":true"Attestation dechets":true"Commentaires":true
{ "Cellule":604"Moyen":568PEPT604FRA0094"Gestionnaire":JULIEN BREUILH"Transporteur":PATINTER PORTUGUESA, LDA"Origine":PRT"Point de chutte":Sourcing"Tracteur":49PF46"Remorque":GD1042"Type":TAUT"Hauteur":2.95"Longueur":13.6"Charge":24"PTRE Tracteur":40"PTAC Remorque":34"ADR":false"Norme Euro":EURO5"Nb sangles":12"Nb equerres":0"Nb planches":0"Cordon TIR":true"Tapis":true"Hayon":false"Porte palettes":false"Baches armees":false"Norme XL":false"Porte bobine":false"EPI":true"Attestation dechets":true"Commentaires":true
{ "Cellule":604"Moyen":568PEPT604FRA0099"Gestionnaire":JULIEN BREUILH"Transporteur":PATINTER PORTUGUESA, LDA"Origine":PRT"Point de chutte":Sourcing"Tracteur":23-PE-32"Remorque":LE-1526"Type":TAUT"Hauteur":2.8"Longueur":13.6"Charge":24"PTRE Tracteur":40"PTAC Remorque":34"ADR":false"Norme Euro":EURO5"Nb sangles":12"Nb equerres":0"Nb planches":0"Cordon TIR":true"Tapis":true"Hayon":false"Porte palettes":false"Baches armees":false"Norme XL":true"Porte bobine":false"EPI":true"Attestation dechets":true"Commentaires":true
{ "Cellule":604"Moyen":568PEPT604FRA0103"Gestionnaire":JULIEN BREUILH"Transporteur":PATINTER PORTUGUESA, LDA"Origine":PRT"Point de chutte":Sourcing"Tracteur":04-PI-28"Remorque":LE-1553"Type":TAUT"Hauteur":2.95"Longueur":13.6"Charge":24"PTRE Tracteur":40"PTAC Remorque":34"ADR":false"Norme Euro":EURO5"Nb sangles":12"Nb equerres":0"Nb planches":0"Cordon TIR":true"Tapis":true"Hayon":false"Porte palettes":false"Baches armees":false"Norme XL":true"Porte bobine":false"EPI":true"Attestation dechets":true"Commentaires":true
{ "Cellule":604"Moyen":568PEPT604FRA0107"Gestionnaire":JULIEN BREUILH"Transporteur":PATINTER PORTUGUESA, LDA"Origine":PRT"Point de chutte":Sourcing"Tracteur":43-PG-19"Remorque":GD-1001"Type":TAUT"Hauteur":2.8"Longueur":13.6"Charge":24"PTRE Tracteur":40"PTAC Remorque":34"ADR":false"Norme Euro":EURO5"Nb sangles":12"Nb equerres":0"Nb planches":0"Cordon TIR":true"Tapis":true"Hayon":false"Porte palettes":false"Baches armees":false"Norme XL":true"Porte bobine":false"EPI":true"Attestation dechets":true"Commentaires":true
{ "Cellule":604"Moyen":568PEPT604FRA0119"Gestionnaire":JULIEN BREUILH"Transporteur":PATINTER PORTUGUESA, LDA"Origine":PRT"Point de chutte":Sourcing"Tracteur":93PE89"Remorque":GD1038"Type":TAUT"Hauteur":2.95"Longueur":13.6"Charge":24"PTRE Tracteur":40"PTAC Remorque":34"ADR":false"Norme Euro":EURO5"Nb sangles":12"Nb equerres":0"Nb planches":0"Cordon TIR":true"Tapis":true"Hayon":false"Porte palettes":false"Baches armees":false"Norme XL":false"Porte bobine":false"EPI":true"Attestation dechets":true"Commentaires":true
{ "Cellule":604"Moyen":604GEREROM1848"Gestionnaire":STEVE PAVIE"Transporteur":PFENNING ROMANIA"Origine":ROM"Point de chutte":Sourcing"Tracteur":B74SIJ"Remorque":B38NEZ"Type":TAUT"Hauteur":2.7"Longueur":13.6"Charge":24"PTRE Tracteur":40"PTAC Remorque":31"ADR":false"Norme Euro":EURO 6"Nb sangles":15"Nb equerres":20"Nb planches":0"Cordon TIR":true"Tapis":true"Hayon":false"Porte palettes":false"Baches armees":false"Norme XL":false"Porte bobine":false"EPI":true"Attestation dechets":false"Commentaires":false
{ "Cellule":604"Moyen":604GERELTU1751"Gestionnaire":VINCENT LAFAY"Transporteur":UAB TRANSGESTA"Origine":LTU"Point de chutte":Sourcing"Tracteur":HUR386"Remorque":FN026"Type":TAUT"Hauteur":2.7"Longueur":13.6"Charge":25"PTRE Tracteur":40"PTAC Remorque":34"ADR":false"Norme Euro":EURO6"Nb sangles":16"Nb equerres":32"Nb planches":0"Cordon TIR":true"Tapis":true"Hayon":false"Porte palettes":false"Baches armees":false"Norme XL":true"Porte bobine":false"EPI":true"Attestation dechets":false"Commentaires":false
{ "Cellule":604"Moyen":604GEREROM1851"Gestionnaire":STEVE PAVIE"Transporteur":PFENNING ROMANIA"Origine":ROM"Point de chutte":Sourcing"Tracteur":B63GBP"Remorque":B38MVF"Type":TAUT"Hauteur":2.7"Longueur":13.6"Charge":24"PTRE Tracteur":40"PTAC Remorque":31"ADR":false"Norme Euro":EURO5"Nb sangles":15"Nb equerres":20"Nb planches":0"Cordon TIR":true"Tapis":true"Hayon":false"Porte palettes":false"Baches armees":false"Norme XL":false"Porte bobine":false"EPI":true"Attestation dechets":false"Commentaires":false
{ "Cellule":604"Moyen":604GERELTU1677"Gestionnaire":DANIEL SAEZ"Transporteur":LAGERA UAB"Origine":LTU"Point de chutte":Sourcing"Tracteur":GCG432"Remorque":EL799"Type":TAUT"Hauteur":2.7"Longueur":13.6"Charge":25"PTRE Tracteur":40"PTAC Remorque":34"ADR":false"Norme Euro":EURO5"Nb sangles":16"Nb equerres":0"Nb planches":0"Cordon TIR":true"Tapis":true"Hayon":false"Porte palettes":false"Baches armees":false"Norme XL":true"Porte bobine":false"EPI":true"Attestation dechets":false"Commentaires":false
{ "Cellule":604"Moyen":604GERELTU1886"Gestionnaire":DANIEL SAEZ"Transporteur":LAGERA UAB"Origine":LTU"Point de chutte":Sourcing"Tracteur":FTB033"Remorque":DF216"Type":TAUT"Hauteur":2.7"Longueur":13.6"Charge":25"PTRE Tracteur":40"PTAC Remorque":34"ADR":false"Norme Euro":EURO5"Nb sangles":16"Nb equerres":0"Nb planches":0"Cordon TIR":true"Tapis":true"Hayon":false"Porte palettes":false"Baches armees":false"Norme XL":true"Porte bobine":false"EPI":true"Attestation dechets":false"Commentaires":false
{ "Cellule":604"Moyen":604GERELTU1752"Gestionnaire":VINCENT LAFAY"Transporteur":UAB TRANSGESTA"Origine":LTU"Point de chutte":Sourcing"Tracteur":HET732"Remorque":FN018"Type":TAUT"Hauteur":2.7"Longueur":13.6"Charge":25"PTRE Tracteur":40"PTAC Remorque":34"ADR":false"Norme Euro":EURO6"Nb sangles":16"Nb equerres":32"Nb planches":0"Cordon TIR":true"Tapis":true"Hayon":false"Porte palettes":false"Baches armees":false"Norme XL":true"Porte bobine":false"EPI":true"Attestation dechets":false"Commentaires":false
{ "Cellule":604"Moyen":604GERELTU1641"Gestionnaire":VINCENT LAFAY"Transporteur":UAB TRANSGESTA"Origine":LTU"Point de chutte":Sourcing"Tracteur":HPN904"Remorque":FF856"Type":TAUT"Hauteur":2.7"Longueur":13.6"Charge":25"PTRE Tracteur":40"PTAC Remorque":34"ADR":false"Norme Euro":EURO5"Nb sangles":16"Nb equerres":32"Nb planches":0"Cordon TIR":true"Tapis":true"Hayon":false"Porte palettes":false"Baches armees":false"Norme XL":true"Porte bobine":false"EPI":true"Attestation dechets":false"Commentaires":false
{ "Cellule":604"Moyen":604GERELTU1907"Gestionnaire":VINCENT LAFAY"Transporteur":UAB TRANSGESTA"Origine":LTU"Point de chutte":Sourcing"Tracteur":GNB408"Remorque":FN021"Type":TAUT"Hauteur":2.7"Longueur":13.6"Charge":25"PTRE Tracteur":40"PTAC Remorque":34"ADR":false"Norme Euro":EURO5"Nb sangles":16"Nb equerres":0"Nb planches":0"Cordon TIR":true"Tapis":true"Hayon":false"Porte palettes":false"Baches armees":false"Norme XL":false"Porte bobine":false"EPI":true"Attestation dechets":false"Commentaires":false
{ "Cellule":604"Moyen":604GERELTU1806"Gestionnaire":STEVE PAVIE"Transporteur":OST WEST CARGO BALTIC"Origine":LTU"Point de chutte":Bche arme"Tracteur":GZV147"Remorque":FJ642"Type":TAUT"Hauteur":2.7"Longueur":13.6"Charge":25"PTRE Tracteur":40"PTAC Remorque":34"ADR":false"Norme Euro":EURO5"Nb sangles":15"Nb equerres":0"Nb planches":0"Cordon TIR":true"Tapis":true"Hayon":false"Porte palettes":false"Baches armees":true"Norme XL":true"Porte bobine":false"EPI":true"Attestation dechets":true"Commentaires":false
{ "Cellule":604"Moyen":568PEPT604FRA0079"Gestionnaire":JULIEN BREUILH"Transporteur":PATINTER PORTUGUESA, LDA"Origine":PRT"Point de chutte":Sourcing"Tracteur":98-QD-82"Remorque":GD-1050"Type":TAUT"Hauteur":2.8"Longueur":13.6"Charge":24"PTRE Tracteur":40"PTAC Remorque":34"ADR":false"Norme Euro":EURO5"Nb sangles":12"Nb equerres":0"Nb planches":0"Cordon TIR":true"Tapis":true"Hayon":false"Porte palettes":false"Baches armees":false"Norme XL":true"Porte bobine":false"EPI":true"Attestation dechets":true"Commentaires":true
{ "Cellule":604"Moyen":604GERELTU1896"Gestionnaire":VINCENT LAFAY"Transporteur":UAB TRANSGESTA"Origine":LTU"Point de chutte":Sourcing"Tracteur":GNB408"Remorque":FN021"Type":TAUT"Hauteur":2.7"Longueur":13.6"Charge":25"PTRE Tracteur":40"PTAC Remorque":34"ADR":false"Norme Euro":EURO5"Nb sangles":16"Nb equerres":0"Nb planches":0"Cordon TIR":true"Tapis":true"Hayon":false"Porte palettes":false"Baches armees":false"Norme XL":false"Porte bobine":false"EPI":true"Attestation dechets":false"Commentaires":false
{ "Cellule":604"Moyen":604GEREROM1821"Gestionnaire":STEVE PAVIE"Transporteur":PFENNING ROMANIA"Origine":ROM"Point de chutte":Sourcing"Tracteur":B68RRV"Remorque":B27BPN"Type":TAUT"Hauteur":2.7"Longueur":13.6"Charge":24"PTRE Tracteur":40"PTAC Remorque":31"ADR":false"Norme Euro":EURO5"Nb sangles":15"Nb equerres":20"Nb planches":0"Cordon TIR":true"Tapis":true"Hayon":false"Porte palettes":false"Baches armees":false"Norme XL":false"Porte bobine":false"EPI":true"Attestation dechets":false"Commentaires":false
{ "Cellule":604"Moyen":604GERELTU1633"Gestionnaire":DANIEL SAEZ"Transporteur":UAB SAUSUMOS LAIVAI"Origine":LTU"Point de chutte":Sourcing"Tracteur":"Remorque":"Type":TAUT"Hauteur":2.7"Longueur":13.6"Charge":24"PTRE Tracteur":40"PTAC Remorque":34"ADR":false"Norme Euro":EURO 5"Nb sangles":16"Nb equerres":32"Nb planches":0"Cordon TIR":true"Tapis":true"Hayon":false"Porte palettes":false"Baches armees":false"Norme XL":true"Porte bobine":false"EPI":true"Attestation dechets":false"Commentaires":false
{ "Cellule":604"Moyen":604GERELTU1911"Gestionnaire":VINCENT LAFAY"Transporteur":UAB TRANSGESTA"Origine":LTU"Point de chutte":Sourcing"Tracteur":HOO053"Remorque":FB487"Type":TAUT"Hauteur":2.7"Longueur":13.6"Charge":25"PTRE Tracteur":40"PTAC Remorque":34"ADR":false"Norme Euro":EURO6"Nb sangles":16"Nb equerres":32"Nb planches":0"Cordon TIR":true"Tapis":true"Hayon":false"Porte palettes":false"Baches armees":false"Norme XL":true"Porte bobine":false"EPI":true"Attestation dechets":false"Commentaires":false
{ "Cellule":604"Moyen":604GERELTU1930"Gestionnaire":STEVE PAVIE"Transporteur":OST WEST CARGO BALTIC"Origine":LTU"Point de chutte":Bche arme"Tracteur":GUM 568"Remorque":FM460"Type":TAUT"Hauteur":2.7"Longueur":13.6"Charge":25"PTRE Tracteur":40"PTAC Remorque":34"ADR":false"Norme Euro":EURO5"Nb sangles":15"Nb equerres":0"Nb planches":0"Cordon TIR":true"Tapis":true"Hayon":false"Porte palettes":false"Baches armees":true"Norme XL":true"Porte bobine":false"EPI":true"Attestation dechets":true"Commentaires":false
{ "Cellule":604"Moyen":568PEPT604FRA0110"Gestionnaire":JULIEN BREUILH"Transporteur":PATINTER PORTUGUESA, LDA"Origine":PRT"Point de chutte":Sourcing"Tracteur":66-PF-85"Remorque":GD-1264"Type":TAUT"Hauteur":2.8"Longueur":13.6"Charge":24"PTRE Tracteur":40"PTAC Remorque":34"ADR":false"Norme Euro":EURO5"Nb sangles":12"Nb equerres":0"Nb planches":0"Cordon TIR":true"Tapis":true"Hayon":false"Porte palettes":false"Baches armees":false"Norme XL":true"Porte bobine":false"EPI":true"Attestation dechets":true"Commentaires":true
{ "Cellule":604"Moyen":604GEREROM1791"Gestionnaire":STEVE PAVIE"Transporteur":PFENNING ROMANIA"Origine":ROM"Point de chutte":Sourcing"Tracteur":B74SHA"Remorque":B35NKT"Type":TAUT"Hauteur":2.7"Longueur":13.6"Charge":24"PTRE Tracteur":40"PTAC Remorque":31"ADR":false"Norme Euro":EURO5"Nb sangles":15"Nb equerres":20"Nb planches":0"Cordon TIR":true"Tapis":true"Hayon":false"Porte palettes":false"Baches armees":false"Norme XL":false"Porte bobine":false"EPI":true"Attestation dechets":false"Commentaires":false
{ "Cellule":604"Moyen":604GERELTU1658"Gestionnaire":VINCENT LAFAY"Transporteur":UAB TRANSGESTA"Origine":LTU"Point de chutte":Sourcing"Tracteur":HOO153"Remorque":FN019"Type":TAUT"Hauteur":2.7"Longueur":13.6"Charge":25"PTRE Tracteur":40"PTAC Remorque":34"ADR":false"Norme Euro":EURO6"Nb sangles":16"Nb equerres":32"Nb planches":0"Cordon TIR":true"Tapis":true"Hayon":false"Porte palettes":false"Baches armees":false"Norme XL":true"Porte bobine":false"EPI":true"Attestation dechets":false"Commentaires":false
{ "Cellule":604"Moyen":568PEPT604FRA0101"Gestionnaire":JULIEN BREUILH"Transporteur":PATINTER PORTUGUESA, LDA"Origine":PRT"Point de chutte":Sourcing"Tracteur":33-PH-01"Remorque":GD-1226"Type":TAUT"Hauteur":2.8"Longueur":13.6"Charge":24"PTRE Tracteur":40"PTAC Remorque":34"ADR":false"Norme Euro":EURO5"Nb sangles":12"Nb equerres":0"Nb planches":0"Cordon TIR":true"Tapis":true"Hayon":false"Porte palettes":false"Baches armees":false"Norme XL":true"Porte bobine":false"EPI":true"Attestation dechets":true"Commentaires":true
{ "Cellule":604"Moyen":604GERELTU1668"Gestionnaire":DANIEL SAEZ"Transporteur":LAGERA UAB"Origine":LTU"Point de chutte":Sourcing"Tracteur":GCG433"Remorque":EL798"Type":TAUT"Hauteur":2.7"Longueur":13.6"Charge":25"PTRE Tracteur":40"PTAC Remorque":34"ADR":false"Norme Euro":EURO5"Nb sangles":16"Nb equerres":0"Nb planches":0"Cordon TIR":true"Tapis":true"Hayon":false"Porte palettes":false"Baches armees":false"Norme XL":true"Porte bobine":false"EPI":true"Attestation dechets":false"Commentaires":false
{ "Cellule":604"Moyen":568PEPT604FRA0036"Gestionnaire":JULIEN BREUILH"Transporteur":PATINTER PORTUGUESA, LDA"Origine":PRT"Point de chutte":Sourcing"Tracteur":06-PG-88"Remorque":GD-1305"Type":TAUT"Hauteur":2.8"Longueur":13.6"Charge":24"PTRE Tracteur":40"PTAC Remorque":34"ADR":false"Norme Euro":EURO5"Nb sangles":12"Nb equerres":0"Nb planches":0"Cordon TIR":true"Tapis":true"Hayon":false"Porte palettes":false"Baches armees":false"Norme XL":true"Porte bobine":false"EPI":true"Attestation dechets":true"Commentaires":true
{ "Cellule":604"Moyen":604GERELTU1838"Gestionnaire":DANIEL SAEZ"Transporteur":UAB SAUSUMOS LAIVAI"Origine":LTU"Point de chutte":Sourcing"Tracteur":GGA339"Remorque":FT334"Type":TAUT"Hauteur":2.7"Longueur":13.6"Charge":24"PTRE Tracteur":40"PTAC Remorque":34"ADR":false"Norme Euro":EURO5"Nb sangles":16"Nb equerres":32"Nb planches":0"Cordon TIR":true"Tapis":true"Hayon":false"Porte palettes":false"Baches armees":false"Norme XL":true"Porte bobine":false"EPI":true"Attestation dechets":false"Commentaires":false
{ "Cellule":604"Moyen":604GERESVK1868"Gestionnaire":VINCENT LAFAY"Transporteur":OBOLON S.R.O."Origine":SVK"Point de chutte":sourcing"Tracteur":SC 017DH"Remorque":SC 907YF"Type":TAUT"Hauteur":2.8"Longueur":13.6"Charge":25"PTRE Tracteur":0"PTAC Remorque":0"ADR":true"Norme Euro":EURO5"Nb sangles":14"Nb equerres":26"Nb planches":24"Cordon TIR":true"Tapis":true"Hayon":false"Porte palettes":false"Baches armees":false"Norme XL":false"Porte bobine":false"EPI":true"Attestation dechets":true"Commentaires":false
{ "Cellule":604"Moyen":604GERESVK1869"Gestionnaire":VINCENT LAFAY"Transporteur":OBOLON S.R.O."Origine":SVK"Point de chutte":sourcing"Tracteur":SC 122DF"Remorque":SC 778YF"Type":TAUT"Hauteur":2.8"Longueur":13.6"Charge":25"PTRE Tracteur":0"PTAC Remorque":0"ADR":false"Norme Euro":EURO5"Nb sangles":14"Nb equerres":26"Nb planches":24"Cordon TIR":true"Tapis":true"Hayon":false"Porte palettes":false"Baches armees":false"Norme XL":false"Porte bobine":false"EPI":true"Attestation dechets":true"Commentaires":false
{ "Cellule":604"Moyen":604GERESVK1877"Gestionnaire":VINCENT LAFAY"Transporteur":OBOLON S.R.O."Origine":SVK"Point de chutte":sourcing"Tracteur":SC 511DG"Remorque":SC 823YF"Type":TAUT"Hauteur":2.8"Longueur":13.6"Charge":25"PTRE Tracteur":0"PTAC Remorque":0"ADR":true"Norme Euro":EURO5"Nb sangles":14"Nb equerres":26"Nb planches":24"Cordon TIR":true"Tapis":true"Hayon":false"Porte palettes":false"Baches armees":false"Norme XL":false"Porte bobine":false"EPI":true"Attestation dechets":true"Commentaires":false
{ "Cellule":604"Moyen":604GERESVK1878"Gestionnaire":VINCENT LAFAY"Transporteur":OBOLON S.R.O."Origine":SVK"Point de chutte":sourcing"Tracteur":SC 028DD"Remorque":SC 678YF"Type":TAUT"Hauteur":2.8"Longueur":13.6"Charge":25"PTRE Tracteur":0"PTAC Remorque":0"ADR":false"Norme Euro":EURO5"Nb sangles":14"Nb equerres":26"Nb planches":24"Cordon TIR":true"Tapis":true"Hayon":false"Porte palettes":false"Baches armees":false"Norme XL":false"Porte bobine":false"EPI":true"Attestation dechets":true"Commentaires":false
{ "Cellule":604"Moyen":604GERESVK1920"Gestionnaire":VINCENT LAFAY"Transporteur":OBOLON S.R.O."Origine":SVK"Point de chutte":sourcing"Tracteur":SC 816DN"Remorque":SC 215YG"Type":TAUT"Hauteur":2.8"Longueur":13.6"Charge":25"PTRE Tracteur":0"PTAC Remorque":0"ADR":true"Norme Euro":EURO5"Nb sangles":14"Nb equerres":26"Nb planches":24"Cordon TIR":true"Tapis":true"Hayon":false"Porte palettes":false"Baches armees":false"Norme XL":false"Porte bobine":false"EPI":true"Attestation dechets":true"Commentaires":false
{ "Cellule":604"Moyen":604GERESVK1876"Gestionnaire":VINCENT LAFAY"Transporteur":OBOLON S.R.O."Origine":SVK"Point de chutte":sourcing"Tracteur":SC 542DM"Remorque":SC 605YF"Type":TAUT"Hauteur":2.8"Longueur":13.6"Charge":25"PTRE Tracteur":0"PTAC Remorque":0"ADR":false"Norme Euro":EURO5"Nb sangles":14"Nb equerres":26"Nb planches":24"Cordon TIR":true"Tapis":true"Hayon":false"Porte palettes":false"Baches armees":false"Norme XL":false"Porte bobine":true"EPI":true"Attestation dechets":true"Commentaires":false
{ "Cellule":604"Moyen":604GERESVK2039"Gestionnaire":VINCENT LAFAY"Transporteur":OBOLON S.R.O."Origine":SVK"Point de chutte":sourcing"Tracteur":SC507DZ"Remorque":SC823YG"Type":TAUT"Hauteur":2.8"Longueur":13.6"Charge":25"PTRE Tracteur":0"PTAC Remorque":0"ADR":false"Norme Euro":EURO5"Nb sangles":14"Nb equerres":26"Nb planches":24"Cordon TIR":true"Tapis":true"Hayon":false"Porte palettes":false"Baches armees":false"Norme XL":false"Porte bobine":false"EPI":true"Attestation dechets":true"Commentaires":false
{ "Cellule":604"Moyen":604GEREPRT2047"Gestionnaire":STEVE PAVIE"Transporteur":KSSD"Origine":PRT"Point de chutte":Sourcing"Tracteur":08-RE-16"Remorque":DV-108-FF"Type":TAUT"Hauteur":2.9"Longueur":13.6"Charge":25.5"PTRE Tracteur":40"PTAC Remorque":34"ADR":false"Norme Euro":Euro5"Nb sangles":15"Nb equerres":30"Nb planches":0"Cordon TIR":true"Tapis":true"Hayon":false"Porte palettes":false"Baches armees":false"Norme XL":false"Porte bobine":false"EPI":true"Attestation dechets":false"Commentaires":false
{ "Cellule":604"Moyen":604GERELTU2062"Gestionnaire":DANIEL SAEZ"Transporteur":LAGERA UAB"Origine":LTU"Point de chutte":Sourcing"Tracteur":FFE.395"Remorque":CP003QJ    6/12"Type":TAUT"Hauteur":2.7"Longueur":13.6"Charge":25"PTRE Tracteur":40"PTAC Remorque":34"ADR":false"Norme Euro":EURO5"Nb sangles":16"Nb equerres":0"Nb planches":0"Cordon TIR":true"Tapis":true"Hayon":false"Porte palettes":false"Baches armees":false"Norme XL":true"Porte bobine":false"EPI":true"Attestation dechets":false"Commentaires":false
{ "Cellule":604"Moyen":604GERELTU2063"Gestionnaire":DANIEL SAEZ"Transporteur":LAGERA UAB"Origine":LTU"Point de chutte":Sourcing"Tracteur":FBT.077"Remorque":8/12 CP915QL"Type":TAUT"Hauteur":2.7"Longueur":13.6"Charge":25"PTRE Tracteur":40"PTAC Remorque":34"ADR":false"Norme Euro":EURO5"Nb sangles":16"Nb equerres":0"Nb planches":0"Cordon TIR":true"Tapis":true"Hayon":false"Porte palettes":false"Baches armees":false"Norme XL":true"Porte bobine":false"EPI":true"Attestation dechets":false"Commentaires":false
{ "Cellule":604"Moyen":604GERELTU2064"Gestionnaire":DANIEL SAEZ"Transporteur":LAGERA UAB"Origine":LTU"Point de chutte":Sourcing"Tracteur":GDA643"Remorque":CP560QM 7/12"Type":TAUT"Hauteur":2.7"Longueur":13.6"Charge":25"PTRE Tracteur":40"PTAC Remorque":34"ADR":false"Norme Euro":EURO5"Nb sangles":16"Nb equerres":0"Nb planches":0"Cordon TIR":true"Tapis":true"Hayon":false"Porte palettes":false"Baches armees":false"Norme XL":true"Porte bobine":false"EPI":true"Attestation dechets":false"Commentaires":false
{ "Cellule":604"Moyen":604GERELTU2067"Gestionnaire":DANIEL SAEZ"Transporteur":LAGERA UAB"Origine":LTU"Point de chutte":Sourcing"Tracteur":GDB285"Remorque":CP466PI  7/12"Type":TAUT"Hauteur":2.7"Longueur":13.6"Charge":25"PTRE Tracteur":40"PTAC Remorque":34"ADR":false"Norme Euro":EURO5"Nb sangles":16"Nb equerres":0"Nb planches":0"Cordon TIR":true"Tapis":true"Hayon":false"Porte palettes":false"Baches armees":false"Norme XL":true"Porte bobine":false"EPI":true"Attestation dechets":false"Commentaires":false
{ "Cellule":604"Moyen":604GERELTU1931"Gestionnaire":STEVE PAVIE"Transporteur":SOLOTRANSA"Origine":LTU"Point de chutte":sourcing"Tracteur":HES901"Remorque":FZ137"Type":TAUT"Hauteur":2.7"Longueur":13.6"Charge":24"PTRE Tracteur":40"PTAC Remorque":34"ADR":false"Norme Euro":EURO5"Nb sangles":12"Nb equerres":20"Nb planches":24"Cordon TIR":true"Tapis":true"Hayon":false"Porte palettes":false"Baches armees":false"Norme XL":false"Porte bobine":false"EPI":true"Attestation dechets":false"Commentaires":false
{ "Cellule":604"Moyen":604GEREROM1966"Gestionnaire":DANIEL SAEZ @"Transporteur":TOTAL NSA SRL"Origine":ROM"Point de chutte":sourcing"Tracteur":B-322-NSA"Remorque":"Type":TAUT"Hauteur":3"Longueur":13.6"Charge":24.531"PTRE Tracteur":8180"PTAC Remorque":7289"ADR":true"Norme Euro":EURO6"Nb sangles":15"Nb equerres":30"Nb planches":0"Cordon TIR":true"Tapis":false"Hayon":false"Porte palettes":false"Baches armees":false"Norme XL":true"Porte bobine":false"EPI":false"Attestation dechets":false"Commentaires":false
{ "Cellule":604"Moyen":604GEREROM2043"Gestionnaire":DANIEL SAEZ @"Transporteur":TOTAL NSA SRL"Origine":ROM"Point de chutte":sourcing"Tracteur":SB 66 TOT"Remorque":SB 66 TAL"Type":TAUT"Hauteur":2.95"Longueur":13.6"Charge":24.531"PTRE Tracteur":8180"PTAC Remorque":7289"ADR":true"Norme Euro":EURO6"Nb sangles":15"Nb equerres":30"Nb planches":0"Cordon TIR":true"Tapis":true"Hayon":false"Porte palettes":false"Baches armees":false"Norme XL":true"Porte bobine":false"EPI":true"Attestation dechets":false"Commentaires":false
{ "Cellule":604"Moyen":604GEREBGR1784"Gestionnaire":STEVE PAVIE"Transporteur":GLOBAL BIOMET"Origine":BGR"Point de chutte":sourcing"Tracteur":CB 7624 BA"Remorque":C2394EC"Type":TAUT"Hauteur":2.7"Longueur":13.6"Charge":25"PTRE Tracteur":40"PTAC Remorque":34"ADR":false"Norme Euro":EURO5"Nb sangles":15"Nb equerres":24"Nb planches":24"Cordon TIR":true"Tapis":false"Hayon":false"Porte palettes":false"Baches armees":false"Norme XL":false"Porte bobine":false"EPI":true"Attestation dechets":false"Commentaires":true
{ "Cellule":604"Moyen":604GEREBGR1785"Gestionnaire":STEVE PAVIE"Transporteur":GLOBAL BIOMET"Origine":BGR"Point de chutte":sourcing"Tracteur":CB9759AP"Remorque":C2394EC"Type":TAUT"Hauteur":2.7"Longueur":13.6"Charge":25"PTRE Tracteur":40"PTAC Remorque":34"ADR":false"Norme Euro":EURO5"Nb sangles":15"Nb equerres":24"Nb planches":24"Cordon TIR":true"Tapis":false"Hayon":false"Porte palettes":false"Baches armees":false"Norme XL":false"Porte bobine":false"EPI":true"Attestation dechets":false"Commentaires":true
{ "Cellule":604"Moyen":604GEREROM2017"Gestionnaire":DANIEL SAEZ @"Transporteur":TOTAL NSA SRL"Origine":ROM"Point de chutte":sourcing"Tracteur":B-401-NSA"Remorque":"Type":TAUT"Hauteur":3"Longueur":13.6"Charge":24.531"PTRE Tracteur":8180"PTAC Remorque":7289"ADR":true"Norme Euro":EURO6"Nb sangles":15"Nb equerres":30"Nb planches":0"Cordon TIR":true"Tapis":false"Hayon":false"Porte palettes":false"Baches armees":false"Norme XL":true"Porte bobine":false"EPI":false"Attestation dechets":false"Commentaires":false
{ "Cellule":604"Moyen":604GERELTU2073"Gestionnaire":DANIEL SAEZ"Transporteur":LAGERA UAB"Origine":LTU"Point de chutte":Sourcing"Tracteur":ERA.083"Remorque":CP003QJ"Type":TAUT"Hauteur":2.7"Longueur":13.6"Charge":25"PTRE Tracteur":40"PTAC Remorque":34"ADR":false"Norme Euro":EURO5"Nb sangles":16"Nb equerres":0"Nb planches":0"Cordon TIR":true"Tapis":true"Hayon":false"Porte palettes":false"Baches armees":false"Norme XL":true"Porte bobine":false"EPI":true"Attestation dechets":false"Commentaires":false
{ "Cellule":604"Moyen":604GERELTU2080"Gestionnaire":DANIEL SAEZ @"Transporteur":LAGERA UAB"Origine":LTU"Point de chutte":Sourcing"Tracteur":FHJ 521"Remorque":BP 065"Type":TAUT"Hauteur":2.7"Longueur":13.6"Charge":25"PTRE Tracteur":40"PTAC Remorque":34"ADR":true"Norme Euro":EURO6"Nb sangles":16"Nb equerres":0"Nb planches":0"Cordon TIR":true"Tapis":true"Hayon":false"Porte palettes":false"Baches armees":false"Norme XL":true"Porte bobine":false"EPI":true"Attestation dechets":false"Commentaires":false
{ "Cellule":604"Moyen":604GERELTU2081"Gestionnaire":DANIEL SAEZ @"Transporteur":LAGERA UAB"Origine":LTU"Point de chutte":Sourcing"Tracteur":HZF 824"Remorque":GJ 279"Type":TAUT"Hauteur":2.7"Longueur":13.6"Charge":25"PTRE Tracteur":40"PTAC Remorque":34"ADR":true"Norme Euro":EURO6"Nb sangles":16"Nb equerres":0"Nb planches":0"Cordon TIR":true"Tapis":true"Hayon":false"Porte palettes":false"Baches armees":false"Norme XL":true"Porte bobine":false"EPI":true"Attestation dechets":false"Commentaires":false
{ "Cellule":604"Moyen":604GEREROM2082"Gestionnaire":DANIEL SAEZ @"Transporteur":TOTAL NSA SRL"Origine":ROM"Point de chutte":sourcing"Tracteur":SB 62 TOT"Remorque":SB 62 TAL"Type":TAUT"Hauteur":2.95"Longueur":13.6"Charge":24.531"PTRE Tracteur":8180"PTAC Remorque":7289"ADR":true"Norme Euro":EURO6"Nb sangles":15"Nb equerres":30"Nb planches":0"Cordon TIR":true"Tapis":true"Hayon":false"Porte palettes":false"Baches armees":false"Norme XL":true"Porte bobine":false"EPI":true"Attestation dechets":false"Commentaires":false
{ "Cellule":604"Moyen":604GERESVK2122"Gestionnaire":VINCENT LAFAY"Transporteur":OBOLON S.R.O."Origine":SVK"Point de chutte":sourcing"Tracteur":SC468EE"Remorque":SC272YH"Type":TAUT"Hauteur":2.7"Longueur":13.6"Charge":25"PTRE Tracteur":0"PTAC Remorque":0"ADR":true"Norme Euro":EURO6"Nb sangles":15"Nb equerres":15"Nb planches":40"Cordon TIR":true"Tapis":true"Hayon":false"Porte palettes":false"Baches armees":false"Norme XL":false"Porte bobine":false"EPI":true"Attestation dechets":true"Commentaires":false
{ "Cellule":604"Moyen":604GERESVK2123"Gestionnaire":VINCENT LAFAY"Transporteur":OBOLON S.R.O."Origine":SVK"Point de chutte":sourcing"Tracteur":SC476EE"Remorque":SC279YH"Type":TAUT"Hauteur":2.7"Longueur":13.6"Charge":25"PTRE Tracteur":0"PTAC Remorque":0"ADR":true"Norme Euro":EURO6"Nb sangles":15"Nb equerres":15"Nb planches":40"Cordon TIR":true"Tapis":true"Hayon":false"Porte palettes":false"Baches armees":false"Norme XL":false"Porte bobine":false"EPI":true"Attestation dechets":true"Commentaires":false
{ "Cellule":604"Moyen":604GEREROM2128"Gestionnaire":DANIEL SAEZ @"Transporteur":TOTAL NSA SRL"Origine":ROM"Point de chutte":sourcing"Tracteur":SB-41-NST"Remorque":SB-42-NST"Type":TAUT"Hauteur":2.95"Longueur":13.6"Charge":24.531"PTRE Tracteur":8180"PTAC Remorque":7289"ADR":true"Norme Euro":EURO6"Nb sangles":15"Nb equerres":30"Nb planches":0"Cordon TIR":true"Tapis":true"Hayon":false"Porte palettes":false"Baches armees":false"Norme XL":true"Porte bobine":false"EPI":true"Attestation dechets":false"Commentaires":false
{ "Cellule":604"Moyen":604GEREROM2129"Gestionnaire":STEVE PAVIE"Transporteur":PFENNING ROMANIA"Origine":ROM"Point de chutte":Sourcing"Tracteur":B63VNZ"Remorque":B38NDD"Type":TAUT"Hauteur":2.7"Longueur":13.6"Charge":24"PTRE Tracteur":40"PTAC Remorque":31"ADR":false"Norme Euro":EURO 6"Nb sangles":15"Nb equerres":20"Nb planches":0"Cordon TIR":true"Tapis":true"Hayon":false"Porte palettes":false"Baches armees":false"Norme XL":false"Porte bobine":false"EPI":true"Attestation dechets":false"Commentaires":false
{ "Cellule":604"Moyen":604GEREROM2130"Gestionnaire":STEVE PAVIE"Transporteur":PFENNING ROMANIA"Origine":ROM"Point de chutte":Sourcing"Tracteur":B74SIJ"Remorque":B35NKT"Type":TAUT"Hauteur":2.7"Longueur":13.6"Charge":24"PTRE Tracteur":40"PTAC Remorque":31"ADR":false"Norme Euro":EURO 6"Nb sangles":15"Nb equerres":20"Nb planches":0"Cordon TIR":true"Tapis":true"Hayon":false"Porte palettes":false"Baches armees":false"Norme XL":false"Porte bobine":false"EPI":true"Attestation dechets":false"Commentaires":false
{ "Cellule":604"Moyen":604GEREROM2141"Gestionnaire":DANIEL SAEZ @"Transporteur":TOTAL NSA SRL"Origine":ROM"Point de chutte":sourcing"Tracteur":SB85NST"Remorque":SB83NST"Type":TAUT"Hauteur":3"Longueur":13.6"Charge":24.531"PTRE Tracteur":8180"PTAC Remorque":7289"ADR":true"Norme Euro":EURO6"Nb sangles":15"Nb equerres":30"Nb planches":0"Cordon TIR":true"Tapis":false"Hayon":false"Porte palettes":false"Baches armees":false"Norme XL":true"Porte bobine":false"EPI":false"Attestation dechets":false"Commentaires":false
{ "Cellule":604"Moyen":604GEREROM2143"Gestionnaire":DANIEL SAEZ @"Transporteur":TOTAL NSA SRL"Origine":ROM"Point de chutte":sourcing"Tracteur":SB37NST"Remorque":SB38NST"Type":TAUT"Hauteur":3"Longueur":13.6"Charge":24.531"PTRE Tracteur":8180"PTAC Remorque":7289"ADR":true"Norme Euro":EURO6"Nb sangles":15"Nb equerres":30"Nb planches":0"Cordon TIR":true"Tapis":false"Hayon":false"Porte palettes":false"Baches armees":false"Norme XL":true"Porte bobine":false"EPI":false"Attestation dechets":false"Commentaires":false
{ "Cellule":604"Moyen":604GEREROM2145"Gestionnaire":DANIEL SAEZ @"Transporteur":TOTAL NSA SRL"Origine":ROM"Point de chutte":sourcing"Tracteur":SB37NST"Remorque":SB38NST"Type":TAUT"Hauteur":3"Longueur":13.6"Charge":24.531"PTRE Tracteur":8180"PTAC Remorque":7289"ADR":true"Norme Euro":EURO6"Nb sangles":15"Nb equerres":30"Nb planches":0"Cordon TIR":true"Tapis":false"Hayon":false"Porte palettes":false"Baches armees":false"Norme XL":true"Porte bobine":false"EPI":false"Attestation dechets":false"Commentaires":false
{ "Cellule":604"Moyen":604GEREROM2146"Gestionnaire":DANIEL SAEZ @"Transporteur":TOTAL NSA SRL"Origine":ROM"Point de chutte":sourcing"Tracteur":SB37NST"Remorque":SB38NST"Type":TAUT"Hauteur":3"Longueur":13.6"Charge":24.531"PTRE Tracteur":8180"PTAC Remorque":7289"ADR":true"Norme Euro":EURO6"Nb sangles":15"Nb equerres":30"Nb planches":0"Cordon TIR":true"Tapis":false"Hayon":false"Porte palettes":false"Baches armees":false"Norme XL":true"Porte bobine":false"EPI":false"Attestation dechets":false"Commentaires":false
{ "Cellule":604"Moyen":604GERELTU2162"Gestionnaire":STEVE PAVIE"Transporteur":OST WEST CARGO BALTIC"Origine":LTU"Point de chutte":Bche arme"Tracteur":GHS079"Remorque":FC594"Type":TAUT"Hauteur":2.65"Longueur":13.4"Charge":25"PTRE Tracteur":40"PTAC Remorque":34"ADR":false"Norme Euro":EURO5"Nb sangles":15"Nb equerres":30"Nb planches":0"Cordon TIR":true"Tapis":true"Hayon":false"Porte palettes":false"Baches armees":true"Norme XL":true"Porte bobine":false"EPI":true"Attestation dechets":true"Commentaires":false
{ "Cellule":604"Moyen":604GERELTU2171"Gestionnaire":STEVE PAVIE"Transporteur":OST WEST CARGO BALTIC"Origine":LTU"Point de chutte":Bche arme"Tracteur":HGJ 367"Remorque":FT 137"Type":TAUT"Hauteur":2.7"Longueur":13.6"Charge":25"PTRE Tracteur":40"PTAC Remorque":34"ADR":false"Norme Euro":EURO5"Nb sangles":15"Nb equerres":0"Nb planches":0"Cordon TIR":true"Tapis":true"Hayon":false"Porte palettes":false"Baches armees":true"Norme XL":true"Porte bobine":false"EPI":true"Attestation dechets":false"Commentaires":false
{ "Cellule":604"Moyen":604GEREROM2173"Gestionnaire":STEVE PAVIE @"Transporteur":TOTAL NSA SRL"Origine":ROM"Point de chutte":sourcing"Tracteur":B 114 NSA"Remorque":B 814 NSA"Type":TAUT"Hauteur":3"Longueur":13.6"Charge":24.531"PTRE Tracteur":8180"PTAC Remorque":7289"ADR":false"Norme Euro":EURO6"Nb sangles":15"Nb equerres":30"Nb planches":0"Cordon TIR":true"Tapis":false"Hayon":false"Porte palettes":false"Baches armees":false"Norme XL":true"Porte bobine":false"EPI":false"Attestation dechets":false"Commentaires":false
{ "Cellule":604"Moyen":604GEREROM2174"Gestionnaire":STEVE PAVIE @"Transporteur":TOTAL NSA SRL"Origine":ROM"Point de chutte":sourcing"Tracteur":B 405 NSA"Remorque":B 406 NSA"Type":TAUT"Hauteur":3"Longueur":13.6"Charge":24.531"PTRE Tracteur":8180"PTAC Remorque":7289"ADR":false"Norme Euro":EURO6"Nb sangles":15"Nb equerres":30"Nb planches":0"Cordon TIR":true"Tapis":false"Hayon":false"Porte palettes":false"Baches armees":false"Norme XL":true"Porte bobine":false"EPI":false"Attestation dechets":false"Commentaires":false
{ "Cellule":604"Moyen":604GEREROM2175"Gestionnaire":STEVE PAVIE @"Transporteur":TOTAL NSA SRL"Origine":ROM"Point de chutte":sourcing"Tracteur":B 306 NSA"Remorque":B 307 NSA"Type":TAUT"Hauteur":3"Longueur":13.6"Charge":24.531"PTRE Tracteur":8180"PTAC Remorque":7289"ADR":false"Norme Euro":EURO6"Nb sangles":15"Nb equerres":30"Nb planches":0"Cordon TIR":true"Tapis":false"Hayon":false"Porte palettes":false"Baches armees":false"Norme XL":true"Porte bobine":false"EPI":false"Attestation dechets":false"Commentaires":false
]
